Workbook

Sheet Read me
A1: Sheriff Sale Underwriting Model, Philadelphia Nov 3 2026
A3: How to use
A4: 1. Put each property on the Deals sheet (yellow cells). ARV and rent come from the comps work; liens and lien position from the title check.
A5: 2. Change any assumption on the Assumptions sheet. Every number in the model reads from there.
A6: 3. Underwriting shows the best exit, the highest bid that still hits the target, and the cash it takes.
A7: 4. Bid Ladder shows profit and return at a range of bids. Portfolio adds up the cash against the $1M cap.
A9: How the max bid is found
A10: Flip: highest bid where ARV minus selling costs, rehab, carry, legal, possession, liens, fees and the 1.5% premium still leaves the $50k target.
A11: Value-add hold: highest bid where stabilized NOI divided by all-in cost is at least 12% (yield on cost, unlevered). Switch Assumptions > 'Value-add: measure' to Cash-on-cash to test levered cash flow after a refi on the cash left in instead.
A12: Wholesale: bid you could pay and still assign the bid to a flipper who needs 15% of ARV, keeping a $15k fee. Shown as an alternative only.
A13: Teardown: new units sold at the per-unit value you enter, less demo, build, soft costs and carry, with a 15% developer margin.
A15: Sale rules built in
... A22: Risk the sale is pulled, set aside or voided by bankruptcy (cash is tied up but returned). IRS 120-day redemption. Opportunity cost of cash. Price changes during the long hold.

Sheet DCF matrix 8%
A1: 2731 Reno St: max bid by rehab scope x resale price (NPV at 8%/yr leaves $50k; breakeven in second block)
A2: Rehab incl. 20% contingency + $10k: Light $35.2k (2 mo), Medium $64.2k (3 mo, incl $8k roof/front), Heavy $81.4k (4 mo), Gut $112k (5 mo). Selling costs 9.3%. Carry: tax $333/mo from sale, insurance+upkeep $325/mo from deed, utilities from possession. Source: research/max_bid_dcf_8pct.py
A4: Fast: deed 9 mo, keys 2 mo, $7.5k | Max bid ($50k NPV@8%)
A5: Scope \ Resale | B5: 365000 | C5: 380000 | D5: 395000 | E5: 410000 | F5: 430000
A6: Light | B6: 192500 | C6: 204600 | D6: 216700 | E6: 228900 | F6: 245100
A7: Medium | B7: 163600 | C7: 175600 | D7: 187700 | E7: 199700 | F7: 215800
A8: Heavy | B8: 145600 | C8: 157600 | D8: 169500 | E8: 181500 | F8: 197500
A9: Gut | B9: 115600 | C9: 127500 | D9: 139400 | E9: 151300 | F9: 167100
A11: Fast: deed 9 mo, keys 2 mo, $7.5k | Breakeven bid (NPV@8% = 0)
A12: Scope \ Resale | B12: 365000 | C12: 380000 | D12: 395000 | E12: 410000 | F12: 430000
A13: Light | B13: 241900 | C13: 254000 | D13: 266100 | E13: 278300 | F13: 294500
A14: Medium | B14: 213000 | C14: 225000 | D14: 237100 | E14: 249100 | F14: 265200
A15: Heavy | B15: 195000 | C15: 207000 | D15: 218900 | E15: 230900 | F15: 246900
A16: Gut | B16: 165000 | C16: 176900 | D16: 188800 | E16: 200700 | F16: 216500
A18: Base: deed 12 mo, cash for keys/ejectment 8 mo, $10k | Max bid ($50k NPV@8%)
A19: Scope \ Resale | B19: 365000 | C19: 380000 | D19: 395000 | E19: 410000 | F19: 430000
A20: Light | B20: 171700 | C20: 183100 | D20: 194600 | E20: 206000 | F20: 221300
A21: Medium | B21: 144400 | C21: 155800 | D21: 167100 | E21: 178500 | F21: 193700
A22: Heavy | B22: 127400 | C22: 138700 | D22: 150000 | E22: 161300 | F22: 176400
A23: Gut | B23: 99100 | C23: 110300 | D23: 121500 | E23: 132800 | F23: 147700
A25: Base: deed 12 mo, cash for keys/ejectment 8 mo, $10k | Breakeven bid (NPV@8% = 0)
A26: Scope \ Resale | B26: 365000 | C26: 380000 | D26: 395000 | E26: 410000 | F26: 430000
A27: Light | B27: 221100 | C27: 232500 | D27: 244000 | E27: 255400 | F27: 270700
A28: Medium | B28: 193800 | C28: 205200 | D28: 216500 | E28: 227900 | F28: 243100
A29: Heavy | B29: 176800 | C29: 188100 | D29: 199400 | E29: 210700 | F29: 225800
A30: Gut | B30: 148500 | C30: 159700 | D30: 170900 | E30: 182200 | F30: 197100
A32: Slow: deed 15 mo, contested ejectment 11 mo, $15k | Max bid ($50k NPV@8%)
A33: Scope \ Resale | B33: 365000 | C33: 380000 | D33: 395000 | E33: 410000 | F33: 430000
A34: Light | B34: 156000 | C34: 167000 | D34: 178000 | E34: 189000 | F34: 203700
A35: Medium | B35: 129700 | C35: 140600 | D35: 151600 | E35: 162500 | F35: 177100
A36: Heavy | B36: 113400 | C36: 124200 | D36: 135100 | E36: 146000 | F36: 160500
A37: Gut | B37: 86100 | C37: 96900 | D37: 107700 | E37: 118500 | F37: 132900
A39: Slow: deed 15 mo, contested ejectment 11 mo, $15k | Breakeven bid (NPV@8% = 0)
A40: Scope \ Resale | B40: 365000 | C40: 380000 | D40: 395000 | E40: 410000 | F40: 430000
A41: Light | B41: 205400 | C41: 216400 | D41: 227400 | E41: 238400 | F41: 253100
A42: Medium | B42: 179100 | C42: 190100 | D42: 201000 | E42: 211900 | F42: 226500
A43: Heavy | B43: 162800 | C43: 173600 | D43: 184500 | E43: 195400 | F43: 209900
A44: Gut | B44: 135500 | C44: 146300 | D44: 157100 | E44: 167900 | F44: 182300

Sheet Assumptions
A1: Assumptions (yellow cells are inputs; every sheet reads from here)
A3: Assumption | B3: Value | C3: Note
A4: Targets (ryan's buy box)
A5: Flip: minimum profit | B5: 50000 | C5: ryan's target: $50k profit per flip
A6: Flip: minimum annualized return on cash (0 = off) | B6: 0.15 | C6: Second test so big-ticket flips can't pass on $50k alone over a 2-year hold. Simple annualized: profit / peak cash / years held. ryan confirmed 15% on Oct 20
A7: Flip: all-in cost ceiling (bid + rehab + costs) | B7: 300000 | C7: Ideal box. A deal over this is flagged, not excluded
A8: Value-add: target annual return | B8: 0.12 | C8: ryan's target: 12%
A9: Value-add: measure the 12% is tested on | B9: Yield on cost | C9: Yield on cost = stabilized NOI / all-in cost (unlevered). Cash-on-cash = cash flow after refi debt service / cash left in after refi
A10: Total cash available | B10: 1000000 | C10: ryan's maximum cash
A11: Sale terms (Philadelphia Sheriff, Nov 3 2026)
A12: Buyer's premium | B12: 0.015 | C12: 1.5% of price, paid with the 10% down
A13: Down payment due Nov 4 | B13: 0.1 | C13: 10% + premium by 5 PM Nov 4; $10k deposit counts toward it
A14: Sheriff / Bid4Assets fees per lot | B14: 70 | C14: $35 processing + $35 balance fee
A15: Bidder deposit (credited to the Nov 4 down payment) | B15: 5000 | C15: $5,000 + $35 fee, received by Bid4Assets 4 PM ET Oct 27 (wire, certified check, money order)
A16: Realty transfer tax taken out of the bid | B16: 0.04578 | C16: Sheriff pays it from the price, before city claims
A17: Sheriff costs paid from the bid before city claims | B17: 2500 | C17: Poundage, advertising, service. Estimate; check the distribution schedule
A18: Title insurance and recording after deed | B18: 2000 | C18: Transfer tax on purchase is paid from the bid, so $0 here
A19: Legal: petition to compel deed / docket review | B19: 2500 | C19: Deeds running 12+ months; budget counsel on every lot
A20: Timeline (months)
A21: Sale to recorded deed | B21: 12 | C21: Rules research: 9-15 months, base 12
A22: Deed to vacant possession if occupied | B22: 8 | C22: Ejectment 3-6 months if uncontested
A23: Treat unknown occupancy as occupied? (Y/N) | B23: Y | C23: Conservative default until the drive-by
A24: Flip: list to closed sale | B24: 3
A25: Hold: rehab done to rent starts | B25: 2
A26: Carry while waiting / rehabbing (per month)
A27: Real estate tax rate (of OPA market value) | B27: 0.013998 | C27: Philadelphia 2026
A28: Vacant-property insurance | B28: 175
A29: Securing, lawn, trash, inspections | B29: 150 | C29: Includes L&I vacant-property upkeep
A30: Utilities | B30: 100
A31: Condo/HOA arrears that survive (months) | B31: 6 | C31: 68 Pa.C.S. 3315 / 5315
A32: Possession
A33: Possession cost if occupied | B33: 10000 | C33: Ejectment counsel + $325 writ + lockout/trash-out, or cash for keys
A34: Rehab (interior unseen)
A35: Blind-interior contingency on $/sf budget | B35: 0.2 | C35: No interior access before purchase
A36: Fixed allowance per property | B36: 10000 | C36: Cleanout, permits, lead/asbestos test, utility reconnects, systems surprises
A37: Flip exit
A38: Listing + buyer agent commission | B38: 0.05
A39: Seller share of realty transfer tax | B39: 0.02289 | C39: Half of 4.578%
A40: Other seller closing costs | B40: 0.01
A41: Buyer concessions / price cuts | B41: 0.01
A42: Value-add hold / BRRRR exit
A43: Vacancy and credit loss | B43: 0.07 | C43: Of gross rent
A44: Property management | B44: 0.08 | C44: Of collected rent
A45: Repairs and maintenance | B45: 0.07 | C45: Of collected rent
A46: Capital reserve | B46: 0.05 | C46: Of collected rent
A47: Landlord insurance per unit per year | B47: 1200
A48: Water/sewer, license, other per unit per year | B48: 700 | C48: Landlord usually carries water in Philly; rental license ~$75/unit
A49: Refi loan-to-value (of ARV) | B49: 0.75 | C49: DSCR lender, after the deed records
A50: Refi interest rate | B50: 0.0725
A51: Refi amortization (years) | B51: 30
A52: Minimum debt service coverage | B52: 1.2 | C52: Loan is sized down if NOI is thin
A53: Refi closing costs (of loan) | B53: 0.03
A54: Wholesale (assign the bid)
A55: End buyer's required profit (of ARV) | B55: 0.15 | C55: Assign by notarized assignment of bid within 15 days; you stay on the hook if they default
A56: Your minimum assignment fee | B56: 15000
A57: Teardown / added units
A58: Demolition and site prep | B58: 30000
A59: New construction hard cost per sf | B59: 225
A60: Soft costs (design, permits, zoning, financing) | B60: 0.15 | C60: Of hard cost
A61: Permit + build months | B61: 14
A62: Developer profit target (of sale revenue) | B62: 0.15 | C62: Or the flip target, whichever is higher
A64: Rehab scope table | B64: $/sf | C64: Months | D64: What it covers
A65: Light | B65: 30 | C65: 2 | D65: Paint, floors, fixtures, minor kitchen/bath refresh
A66: Medium | B66: 55 | C66: 3 | D66: New kitchen and bath, some systems, windows
A67: Heavy | B67: 85 | C67: 5 | D67: All systems, kitchen, baths, drywall, roof repair
A68: Gut | B68: 125 | C68: 7 | D68: Down to studs: structure, roof, all systems, full finishes

Sheet Deals
A1: Property inputs. One row per property; yellow cells are inputs. Rows flow automatically to Underwriting, Bid Ladder and Portfolio.
A2: Auction ID | B2: Address | C2: ZIP | D2: Opening bid | E2: Judgment / debt | F2: Plaintiff lien position | G2: Building sf | H2: Lot sf | I2: Year built | J2: Units (after rehab) | K2: OPA market value | L2: As-is value | M2: ARV | N2: Market rent / mo (all units) | O2: Rehab scope | P2: Exterior / known adders | Q2: Occupancy | R2: Surviving liens not covered by bid | S2: City claims owed (RE tax, water/sewer, other) | T2: Condo/HOA dues / mo | U2: Teardown: units possible | V2: Teardown: new-build sf | W2: Teardown: sale value / unit | X2: Data status / notes
A3: 1318974-0 | B3: 0 Bench screen (ARV 354k, Heavy, occupied) | C3: 19130 | D3: 24700 | E3: 275615 | F3: 1st | G3: 700 | H3: 520 | I3: 1920 | J3: 1 | K3: 285300 | L3: 240000 | M3: 354000 | N3: 2600 | O3: Heavy | P3: 0 | Q3: Occupied | R3: 2500 | X3: 2731 Reno St deep dive; bench screen inputs re-run with 8-month possession
A4: 1318974-1 | B4: 1 Base: ARV 395k, Medium (+$8k roof/front), occupied | C4: 19130 | D4: 24700 | E4: 275615 | F4: 1st | G4: 700 | H4: 520 | I4: 1920 | J4: 1 | K4: 285300 | L4: 265000 | M4: 395000 | N4: 2600 | O4: Medium | P4: 8000 | Q4: Occupied | R4: 2500 | X4: 2731 Reno St deep dive; Fairmount 700-800sf row comps median $390k
A5: 1318974-2 | B5: 2 Base but vacant at deed | C5: 19130 | D5: 24700 | E5: 275615 | F5: 1st | G5: 700 | H5: 520 | I5: 1920 | J5: 1 | K5: 285300 | L5: 265000 | M5: 395000 | N5: 2600 | O5: Medium | P5: 8000 | Q5: Vacant | R5: 2500 | X5: 2731 Reno St deep dive
A6: 1318974-3 | B6: 3 Light cosmetic: ARV 375k, Light, occupied | C6: 19130 | D6: 24700 | E6: 275615 | F6: 1st | G6: 700 | H6: 520 | I6: 1920 | J6: 1 | K6: 285300 | L6: 265000 | M6: 375000 | N6: 2600 | O6: Light | P6: 0 | Q6: Occupied | R6: 2500 | X6: 2731 Reno St deep dive
A7: 1318974-4 | B7: 4 Downside: ARV 365k, Heavy, occupied | C7: 19130 | D7: 24700 | E7: 275615 | F7: 1st | G7: 700 | H7: 520 | I7: 1920 | J7: 1 | K7: 285300 | L7: 240000 | M7: 365000 | N7: 2600 | O7: Heavy | P7: 0 | Q7: Occupied | R7: 2500 | X7: 2731 Reno St deep dive
A8: 1318974-5 | B8: 5 Upside: ARV 425k, Medium + half bath, occupied | C8: 19130 | D8: 24700 | E8: 275615 | F8: 1st | G8: 700 | H8: 520 | I8: 1920 | J8: 1 | K8: 285300 | L8: 265000 | M8: 425000 | N8: 2600 | O8: Medium | P8: 20000 | Q8: Occupied | R8: 2500 | X8: 2731 Reno St deep dive; like 813 N Newkirk $432.5k
A9: 1318974-6 | B9: 6 Slow ejectment proxy: ARV 395k, Medium, occupied, Heavy timeline | C9: 19130 | D9: 24700 | E9: 275615 | F9: 1st | G9: 700 | H9: 520 | I9: 1920 | J9: 1 | K9: 285300 | L9: 265000 | M9: 395000 | N9: 2600 | O9: Heavy | P9: 0 | Q9: Occupied | R9: 2500 | X9: Heavy scope used as a proxy for 2 extra months and +$25k (contested possession / surprises)

Sheet Underwriting
A1: Property | C1: Result | K1: Timeline | O1: Costs | R1: Flip | Z1: Hold | AK1: Wholesale | AL1: Teardown
A2: Auction ID | B2: Address | C2: Best exit | D2: Max bid that hits target | E2: Check vs opening bid | F2: All-in cash at max bid | G2: Profit / return at max bid | H2: Buy box | I2: Other exits | J2: Flags | K2: Occupied? (1 = yes) | L2: Rehab months | M2: Flip: sale to sold | N2: Hold: sale to rent start | O2: Rehab budget (blind) | P2: Carry / month | Q2: Fixed deal costs (fees, legal, possession, liens) | R2: Flip: selling costs | S2: Flip: costs other than bid (pre-sale) | T2: Flip: profit before bid | U2: Flip: most the bid may cost (incl. premium, unpaid claims) | V2: Flip: max bid | W2: Flip: peak cash at max bid | X2: Flip: profit at max bid | Y2: Flip: annualized return at max bid | Z2: Hold: stabilized NOI / yr | AA2: Hold: costs other than bid | AB2: Hold: refi loan | AC2: Hold: cash flow after debt / yr | AD2: Hold: max bid at target yield on cost | AE2: Hold: max bid at target cash-on-cash | AF2: Hold: max bid (selected measure) | AG2: Hold: all-in cost at max bid | AH2: Hold: yield on cost at max bid | AI2: Hold: cash left in after refi | AJ2: Hold: cash-on-cash after refi | AK2: Wholesale: max bid (assign to a flipper, keep the fee) | AL2: Teardown: sale revenue | AM2: Teardown: costs other than bid | AN2: Teardown: max bid
A3: =IF(Deals!A3="","",Deals!A3) -> 1318974-0 | B3: =IF(A3="","",Deals!B3) -> 0 Bench screen (ARV 354k, Heavy, occupied) | C3: =IF(A3="","",IF(MAX(V3,AF3)<=0,"Pass",IF(V3>=AF3,"Flip","Value-add hold"))) -> Flip | D3: =IF(A3="","",MAX(V3,AF3)) -> 116429.49 | E3: =IF(A3="","",IF(D3<=0,"Pass",IF(N(Deals!D3)<=1,"$1 = awaiting minimum bid; re-check the morning of Nov 3",IF(D3<Deals!D3,"Max bid below opening bid: pass","Room of "&TEXT(D3-Deals!D3,"$#,##0")&" over opening bid")))) -> Room of $91,729 over opening bid | F3: =IF(A3="","",IF(C3="Flip",W3,IF(C3="Value-add hold",AG3,0))) -> 237864.4 | G3: =IF(A3="","",IF(C3="Flip",TEXT(X3,"$#,##0")&" profit, "&TEXT(Y3,"0%")&"/yr over "&TEXT(M3,"0")&" mo",IF(C3="Value-add hold",TEXT(AH3,"0.0%")&" yield on cost; "&IF(ISNUMBER(AJ3),TEXT(AJ3,"0.0%")&" cash-on-cash after refi","all cash out at refi"),""))) -> $83,253 profit, 15%/yr over 28 mo | H3: =IF(A3="","",IF(C3="Flip",IF(W3<=FlipCeiling,"In $300k flip box","Over flip ceiling: needs to be exceptional"),IF(C3="Value-add hold","Value-add",""))) -> In $300k flip box | I3: =IF(A3="","",TRIM(IF(AK3>D3,"Wholesale assignment supports "&TEXT(AK3,"$#,##0")&". ","")&IF(AND(ISNUMBER(AN3),N(AN3)>D3),"Teardown/new units supports "&TEXT(AN3,"$#,##0")&".",""))) -> Wholesale assignment supports $131,358. | J3: =IF(A3="","",TRIM(IF(Deals!F3="2nd","Plaintiff is 2nd: add senior mortgage to surviving liens. ",IF(Deals!F3<>"1st","Lien position unconfirmed. ",""))&IF(N(Deals!M3)=0,"No ARV yet. ","")&IF(N(Deals!G3)=0,"No building sf: rehab is allowance only. ","")&IF(AND(N(Deals!S3)>0,D3>0,D3*(1-RTTPurchase)-SheriffCostsFromBid<N(Deals!S3)),"City claims not fully paid at max bid; unpaid part is counted as cost. ","")&IF(K3=1,"Occupancy assumed: +"&TEXT(EjectMonths,"0")&" mo and possession cost. ",""))) -> Occupancy assumed: +8 mo and possession cost. | K3: =IF(A3="","",IF(OR(Deals!Q3="Occupied",AND(Deals!Q3<>"Vacant",UnknownAsOccupied="Y")),1,0)) -> 1 | L3: =IF(A3="","",IFERROR(INDEX(ScopeMonths,MATCH(Deals!O3,ScopeNames,0)),INDEX(ScopeMonths,3))) -> 5 | M3: =IF(A3="","",DeedMonths+K3*EjectMonths+L3+SellMonths) -> 28 | N3: =IF(A3="","",DeedMonths+K3*EjectMonths+L3+LeaseUpMonths) -> 27 | O3: =IF(A3="","",N(Deals!G3)*IFERROR(INDEX(ScopePSF,MATCH(Deals!O3,ScopeNames,0)),INDEX(ScopePSF,3))*(1+Contingency)+BlindAllowance+N(Deals!P3)) -> 81400 | P3: =IF(A3="","",IF(N(Deals!K3)>0,Deals!K3,N(Deals!M3))*TaxRate/12+VacantInsMo+SecuringMo+UtilitiesMo+N(Deals!T3)) -> 757.80245 | Q3: =IF(A3="","",SheriffFees+PurchaseTitle+CompelDeedLegal+K3*PossessionCost+N(Deals!R3)+N(Deals!T3)*HOAArrearsMonths) -> 17070 | R3: =IF(A3="","",N(Deals!M3)*(BrokerPct+SellerRTT+SellClosingPct+ConcessionsPct)) -> 32883.06 | S3: =IF(A3="","",Q3+O3+P3*M3) -> 119688.47 | T3: =IF(A3="","",N(Deals!M3)-R3-S3) -> 201428.47 | U3: =IF(A3="","",MIN(T3-FlipTarget,(T3-FlipMinAnnROI*M3/12*S3)/(1+FlipMinAnnROI*M3/12))) -> 118175.93 | V3: =IF(A3="","",IF(N(Deals!S3)=0,MAX(0,(U3)/(1+BuyerPremium)),IF((U3)>=(N(Deals!S3)+SheriffCostsFromBid)/(1-RTTPurchase)*(1+BuyerPremium),(U3)/(1+BuyerPremium),MAX(0,((U3)-N(Deals!S3)-SheriffCostsFromBid)/(BuyerPremium+RTTPurchase))))) -> 116429.49 | W3: =IF(A3="","",((V3)*(1+BuyerPremium)+IF(N(Deals!S3)=0,0,MIN(N(Deals!S3),MAX(0,N(Deals!S3)+SheriffCostsFromBid-(V3)*(1-RTTPurchase)))))+S3) -> 237864.4 | X3: =IF(A3="","",T3-((V3)*(1+BuyerPremium)+IF(N(Deals!S3)=0,0,MIN(N(Deals!S3),MAX(0,N(Deals!S3)+SheriffCostsFromBid-(V3)*(1-RTTPurchase)))))) -> 83252.54 | Y3: =IF(A3="","",IFERROR(X3/W3/(M3/12),0)) -> 0.15 | Z3: =IF(A3="","",N(Deals!N3)*12*(1-Vacancy)*(1-MgmtPct-MaintPct-CapexPct)-N(Deals!M3)*TaxRate-MAX(1,N(Deals!J3))*(InsPerUnit+WaterPerUnit)-N(Deals!T3)*12) -> 16357.508 | AA3: =IF(A3="","",Q3+O3+P3*N3) -> 118930.67 | AB3: =IF(A3="","",MAX(0,MIN(RefiLTV*N(Deals!M3),Z3/(RefiDSCR*12*PMT(RefiRate/12,RefiTerm*12,-1))))) -> 166516.79 | AC3: =IF(A3="","",Z3-AB3*12*PMT(RefiRate/12,RefiTerm*12,-1)) -> 2726.2513 | AD3: =IF(A3="","",IF(N(Deals!S3)=0,MAX(0,(Z3/HoldTarget-AA3)/(1+BuyerPremium)),IF((Z3/HoldTarget-AA3)>=(N(Deals!S3)+SheriffCostsFromBid)/(1-RTTPurchase)*(1+BuyerPremium),(Z3/HoldTarget-AA3)/(1+BuyerPremium),MAX(0,((Z3/HoldTarget-AA3)-N(Deals!S3)-SheriffCostsFromBid)/(BuyerPremium+RTTPurchase))))) -> 17125.025 | AE3: =IF(A3="","",IF(AC3<=0,0,IF(N(Deals!S3)=0,MAX(0,(AC3/HoldTarget+AB3*(1-RefiCostPct)-AA3)/(1+BuyerPremium)),IF((AC3/HoldTarget+AB3*(1-RefiCostPct)-AA3)>=(N(Deals!S3)+SheriffCostsFromBid)/(1-RTTPurchase)*(1+BuyerPremium),(AC3/HoldTarget+AB3*(1-RefiCostPct)-AA3)/(1+BuyerPremium),MAX(0,((AC3/HoldTarget+AB3*(1-RefiCostPct)-AA3)-N(Deals!S3)-SheriffCostsFromBid)/(BuyerPremium+RTTPurchase)))))) -> 64344.22 | AF3: =IF(A3="","",IF(HoldMeasure="Cash-on-cash",AE3,AD3)) -> 17125.025 | AG3: =IF(A3="","",((AF3)*(1+BuyerPremium)+IF(N(Deals!S3)=0,0,MIN(N(Deals!S3),MAX(0,N(Deals!S3)+SheriffCostsFromBid-(AF3)*(1-RTTPurchase)))))+AA3) -> 136312.57 | AH3: =IF(A3="","",IFERROR(Z3/AG3,0)) -> 0.12 | AI3: =IF(A3="","",AG3-AB3*(1-RefiCostPct)) -> -25208.721 | AJ3: =IF(A3="","",IF(AI3<=0,"All cash out",AC3/AI3)) -> All cash out | AK3: =IF(A3="","",IF(N(Deals!S3)=0,MAX(0,(T3-BuyerMarginPct*N(Deals!M3)-WholesaleMinFee)/(1+BuyerPremium)),IF((T3-BuyerMarginPct*N(Deals!M3)-WholesaleMinFee)>=(N(Deals!S3)+SheriffCostsFromBid)/(1-RTTPurchase)*(1+BuyerPremium),(T3-BuyerMarginPct*N(Deals!M3)-WholesaleMinFee)/(1+BuyerPremium),MAX(0,((T3-BuyerMarginPct*N(Deals!M3)-WholesaleMinFee)-N(Deals!S3)-SheriffCostsFromBid)/(BuyerPremium+RTTPurchase))))) -> 131358.1 | AL3: =IF(OR(A3="",N(Deals!U3)=0),"",Deals!U3*N(Deals!W3)) | AM3: =IF(AL3="","",DemoCost+N(Deals!V3)*BuildCostPSF*(1+SoftCostPct)+P3*(DeedMonths+K3*EjectMonths+BuildMonths+SellMonths)+Q3+AL3*(BrokerPct+SellerRTT+SellClosingPct+ConcessionsPct)) | AN3: =IF(AL3="","",IF(N(Deals!S3)=0,MAX(0,(AL3-AM3-MAX(FlipTarget,DevMarginPct*AL3))/(1+BuyerPremium)),IF((AL3-AM3-MAX(FlipTarget,DevMarginPct*AL3))>=(N(Deals!S3)+SheriffCostsFromBid)/(1-RTTPurchase)*(1+BuyerPremium),(AL3-AM3-MAX(FlipTarget,DevMarginPct*AL3))/(1+BuyerPremium),MAX(0,((AL3-AM3-MAX(FlipTarget,DevMarginPct*AL3))-N(Deals!S3)-SheriffCostsFromBid)/(BuyerPremium+RTTPurchase)))))
A4: =IF(Deals!A4="","",Deals!A4) -> 1318974-1 | B4: =IF(A4="","",Deals!B4) -> 1 Base: ARV 395k, Medium (+$8k roof/front), occupied | C4: =IF(A4="","",IF(MAX(V4,AF4)<=0,"Pass",IF(V4>=AF4,"Flip","Value-add hold"))) -> Flip | D4: =IF(A4="","",MAX(V4,AF4)) -> 166944.44 | E4: =IF(A4="","",IF(D4<=0,"Pass",IF(N(Deals!D4)<=1,"$1 = awaiting minimum bid; re-check the morning of Nov 3",IF(D4<Deals!D4,"Max bid below opening bid: pass","Room of "&TEXT(D4-Deals!D4,"$#,##0")&" over opening bid")))) -> Room of $142,244 over opening bid | F4: =IF(A4="","",IF(C4="Flip",W4,IF(C4="Value-add hold",AG4,0))) -> 270421.47 | G4: =IF(A4="","",IF(C4="Flip",TEXT(X4,"$#,##0")&" profit, "&TEXT(Y4,"0%")&"/yr over "&TEXT(M4,"0")&" mo",IF(C4="Value-add hold",TEXT(AH4,"0.0%")&" yield on cost; "&IF(ISNUMBER(AJ4),TEXT(AJ4,"0.0%")&" cash-on-cash after refi","all cash out at refi"),""))) -> $87,887 profit, 15%/yr over 26 mo | H4: =IF(A4="","",IF(C4="Flip",IF(W4<=FlipCeiling,"In $300k flip box","Over flip ceiling: needs to be exceptional"),IF(C4="Value-add hold","Value-add",""))) -> In $300k flip box | I4: =IF(A4="","",TRIM(IF(AK4>D4,"Wholesale assignment supports "&TEXT(AK4,"$#,##0")&". ","")&IF(AND(ISNUMBER(AN4),N(AN4)>D4),"Teardown/new units supports "&TEXT(AN4,"$#,##0")&".",""))) -> Wholesale assignment supports $180,380. | J4: =IF(A4="","",TRIM(IF(Deals!F4="2nd","Plaintiff is 2nd: add senior mortgage to surviving liens. ",IF(Deals!F4<>"1st","Lien position unconfirmed. ",""))&IF(N(Deals!M4)=0,"No ARV yet. ","")&IF(N(Deals!G4)=0,"No building sf: rehab is allowance only. ","")&IF(AND(N(Deals!S4)>0,D4>0,D4*(1-RTTPurchase)-SheriffCostsFromBid<N(Deals!S4)),"City claims not fully paid at max bid; unpaid part is counted as cost. ","")&IF(K4=1,"Occupancy assumed: +"&TEXT(EjectMonths,"0")&" mo and possession cost. ",""))) -> Occupancy assumed: +8 mo and possession cost. | K4: =IF(A4="","",IF(OR(Deals!Q4="Occupied",AND(Deals!Q4<>"Vacant",UnknownAsOccupied="Y")),1,0)) -> 1 | L4: =IF(A4="","",IFERROR(INDEX(ScopeMonths,MATCH(Deals!O4,ScopeNames,0)),INDEX(ScopeMonths,3))) -> 3 | M4: =IF(A4="","",DeedMonths+K4*EjectMonths+L4+SellMonths) -> 26 | N4: =IF(A4="","",DeedMonths+K4*EjectMonths+L4+LeaseUpMonths) -> 25 | O4: =IF(A4="","",N(Deals!G4)*IFERROR(INDEX(ScopePSF,MATCH(Deals!O4,ScopeNames,0)),INDEX(ScopePSF,3))*(1+Contingency)+BlindAllowance+N(Deals!P4)) -> 64200 | P4: =IF(A4="","",IF(N(Deals!K4)>0,Deals!K4,N(Deals!M4))*TaxRate/12+VacantInsMo+SecuringMo+UtilitiesMo+N(Deals!T4)) -> 757.80245 | Q4: =IF(A4="","",SheriffFees+PurchaseTitle+CompelDeedLegal+K4*PossessionCost+N(Deals!R4)+N(Deals!T4)*HOAArrearsMonths) -> 17070 | R4: =IF(A4="","",N(Deals!M4)*(BrokerPct+SellerRTT+SellClosingPct+ConcessionsPct)) -> 36691.55 | S4: =IF(A4="","",Q4+O4+P4*M4) -> 100972.86 | T4: =IF(A4="","",N(Deals!M4)-R4-S4) -> 257335.59 | U4: =IF(A4="","",MIN(T4-FlipTarget,(T4-FlipMinAnnROI*M4/12*S4)/(1+FlipMinAnnROI*M4/12))) -> 169448.61 | V4: =IF(A4="","",IF(N(Deals!S4)=0,MAX(0,(U4)/(1+BuyerPremium)),IF((U4)>=(N(Deals!S4)+SheriffCostsFromBid)/(1-RTTPurchase)*(1+BuyerPremium),(U4)/(1+BuyerPremium),MAX(0,((U4)-N(Deals!S4)-SheriffCostsFromBid)/(BuyerPremium+RTTPurchase))))) -> 166944.44 | W4: =IF(A4="","",((V4)*(1+BuyerPremium)+IF(N(Deals!S4)=0,0,MIN(N(Deals!S4),MAX(0,N(Deals!S4)+SheriffCostsFromBid-(V4)*(1-RTTPurchase)))))+S4) -> 270421.47 | X4: =IF(A4="","",T4-((V4)*(1+BuyerPremium)+IF(N(Deals!S4)=0,0,MIN(N(Deals!S4),MAX(0,N(Deals!S4)+SheriffCostsFromBid-(V4)*(1-RTTPurchase)))))) -> 87886.978 | Y4: =IF(A4="","",IFERROR(X4/W4/(M4/12),0)) -> 0.15 | Z4: =IF(A4="","",N(Deals!N4)*12*(1-Vacancy)*(1-MgmtPct-MaintPct-CapexPct)-N(Deals!M4)*TaxRate-MAX(1,N(Deals!J4))*(InsPerUnit+WaterPerUnit)-N(Deals!T4)*12) -> 15783.59 | AA4: =IF(A4="","",Q4+O4+P4*N4) -> 100215.06 | AB4: =IF(A4="","",MAX(0,MIN(RefiLTV*N(Deals!M4),Z4/(RefiDSCR*12*PMT(RefiRate/12,RefiTerm*12,-1))))) -> 160674.4 | AC4: =IF(A4="","",Z4-AB4*12*PMT(RefiRate/12,RefiTerm*12,-1)) -> 2630.5983 | AD4: =IF(A4="","",IF(N(Deals!S4)=0,MAX(0,(Z4/HoldTarget-AA4)/(1+BuyerPremium)),IF((Z4/HoldTarget-AA4)>=(N(Deals!S4)+SheriffCostsFromBid)/(1-RTTPurchase)*(1+BuyerPremium),(Z4/HoldTarget-AA4)/(1+BuyerPremium),MAX(0,((Z4/HoldTarget-AA4)-N(Deals!S4)-SheriffCostsFromBid)/(BuyerPremium+RTTPurchase))))) -> 30852.074 | AE4: =IF(A4="","",IF(AC4<=0,0,IF(N(Deals!S4)=0,MAX(0,(AC4/HoldTarget+AB4*(1-RefiCostPct)-AA4)/(1+BuyerPremium)),IF((AC4/HoldTarget+AB4*(1-RefiCostPct)-AA4)>=(N(Deals!S4)+SheriffCostsFromBid)/(1-RTTPurchase)*(1+BuyerPremium),(AC4/HoldTarget+AB4*(1-RefiCostPct)-AA4)/(1+BuyerPremium),MAX(0,((AC4/HoldTarget+AB4*(1-RefiCostPct)-AA4)-N(Deals!S4)-SheriffCostsFromBid)/(BuyerPremium+RTTPurchase)))))) -> 76414.541 | AF4: =IF(A4="","",IF(HoldMeasure="Cash-on-cash",AE4,AD4)) -> 30852.074 | AG4: =IF(A4="","",((AF4)*(1+BuyerPremium)+IF(N(Deals!S4)=0,0,MIN(N(Deals!S4),MAX(0,N(Deals!S4)+SheriffCostsFromBid-(AF4)*(1-RTTPurchase)))))+AA4) -> 131529.92 | AH4: =IF(A4="","",IFERROR(Z4/AG4,0)) -> 0.12 | AI4: =IF(A4="","",AG4-AB4*(1-RefiCostPct)) -> -24324.25 | AJ4: =IF(A4="","",IF(AI4<=0,"All cash out",AC4/AI4)) -> All cash out | AK4: =IF(A4="","",IF(N(Deals!S4)=0,MAX(0,(T4-BuyerMarginPct*N(Deals!M4)-WholesaleMinFee)/(1+BuyerPremium)),IF((T4-BuyerMarginPct*N(Deals!M4)-WholesaleMinFee)>=(N(Deals!S4)+SheriffCostsFromBid)/(1-RTTPurchase)*(1+BuyerPremium),(T4-BuyerMarginPct*N(Deals!M4)-WholesaleMinFee)/(1+BuyerPremium),MAX(0,((T4-BuyerMarginPct*N(Deals!M4)-WholesaleMinFee)-N(Deals!S4)-SheriffCostsFromBid)/(BuyerPremium+RTTPurchase))))) -> 180379.89 | AL4: =IF(OR(A4="",N(Deals!U4)=0),"",Deals!U4*N(Deals!W4)) | AM4: =IF(AL4="","",DemoCost+N(Deals!V4)*BuildCostPSF*(1+SoftCostPct)+P4*(DeedMonths+K4*EjectMonths+BuildMonths+SellMonths)+Q4+AL4*(BrokerPct+SellerRTT+SellClosingPct+ConcessionsPct)) | AN4: =IF(AL4="","",IF(N(Deals!S4)=0,MAX(0,(AL4-AM4-MAX(FlipTarget,DevMarginPct*AL4))/(1+BuyerPremium)),IF((AL4-AM4-MAX(FlipTarget,DevMarginPct*AL4))>=(N(Deals!S4)+SheriffCostsFromBid)/(1-RTTPurchase)*(1+BuyerPremium),(AL4-AM4-MAX(FlipTarget,DevMarginPct*AL4))/(1+BuyerPremium),MAX(0,((AL4-AM4-MAX(FlipTarget,DevMarginPct*AL4))-N(Deals!S4)-SheriffCostsFromBid)/(BuyerPremium+RTTPurchase)))))
A5: =IF(Deals!A5="","",Deals!A5) -> 1318974-2 | B5: =IF(A5="","",Deals!B5) -> 2 Base but vacant at deed | C5: =IF(A5="","",IF(MAX(V5,AF5)<=0,"Pass",IF(V5>=AF5,"Flip","Value-add hold"))) -> Flip | D5: =IF(A5="","",MAX(V5,AF5)) -> 204518.47 | E5: =IF(A5="","",IF(D5<=0,"Pass",IF(N(Deals!D5)<=1,"$1 = awaiting minimum bid; re-check the morning of Nov 3",IF(D5<Deals!D5,"Max bid below opening bid: pass","Room of "&TEXT(D5-Deals!D5,"$#,##0")&" over opening bid")))) -> Room of $179,818 over opening bid | F5: =IF(A5="","",IF(C5="Flip",W5,IF(C5="Value-add hold",AG5,0))) -> 292496.69 | G5: =IF(A5="","",IF(C5="Flip",TEXT(X5,"$#,##0")&" profit, "&TEXT(Y5,"0%")&"/yr over "&TEXT(M5,"0")&" mo",IF(C5="Value-add hold",TEXT(AH5,"0.0%")&" yield on cost; "&IF(ISNUMBER(AJ5),TEXT(AJ5,"0.0%")&" cash-on-cash after refi","all cash out at refi"),""))) -> $65,812 profit, 15%/yr over 18 mo | H5: =IF(A5="","",IF(C5="Flip",IF(W5<=FlipCeiling,"In $300k flip box","Over flip ceiling: needs to be exceptional"),IF(C5="Value-add hold","Value-add",""))) -> In $300k flip box | I5: =IF(A5="","",TRIM(IF(AK5>D5,"Wholesale assignment supports "&TEXT(AK5,"$#,##0")&". ","")&IF(AND(ISNUMBER(AN5),N(AN5)>D5),"Teardown/new units supports "&TEXT(AN5,"$#,##0")&".",""))) | J5: =IF(A5="","",TRIM(IF(Deals!F5="2nd","Plaintiff is 2nd: add senior mortgage to surviving liens. ",IF(Deals!F5<>"1st","Lien position unconfirmed. ",""))&IF(N(Deals!M5)=0,"No ARV yet. ","")&IF(N(Deals!G5)=0,"No building sf: rehab is allowance only. ","")&IF(AND(N(Deals!S5)>0,D5>0,D5*(1-RTTPurchase)-SheriffCostsFromBid<N(Deals!S5)),"City claims not fully paid at max bid; unpaid part is counted as cost. ","")&IF(K5=1,"Occupancy assumed: +"&TEXT(EjectMonths,"0")&" mo and possession cost. ",""))) | K5: =IF(A5="","",IF(OR(Deals!Q5="Occupied",AND(Deals!Q5<>"Vacant",UnknownAsOccupied="Y")),1,0)) -> 0 | L5: =IF(A5="","",IFERROR(INDEX(ScopeMonths,MATCH(Deals!O5,ScopeNames,0)),INDEX(ScopeMonths,3))) -> 3 | M5: =IF(A5="","",DeedMonths+K5*EjectMonths+L5+SellMonths) -> 18 | N5: =IF(A5="","",DeedMonths+K5*EjectMonths+L5+LeaseUpMonths) -> 17 | O5: =IF(A5="","",N(Deals!G5)*IFERROR(INDEX(ScopePSF,MATCH(Deals!O5,ScopeNames,0)),INDEX(ScopePSF,3))*(1+Contingency)+BlindAllowance+N(Deals!P5)) -> 64200 | P5: =IF(A5="","",IF(N(Deals!K5)>0,Deals!K5,N(Deals!M5))*TaxRate/12+VacantInsMo+SecuringMo+UtilitiesMo+N(Deals!T5)) -> 757.80245 | Q5: =IF(A5="","",SheriffFees+PurchaseTitle+CompelDeedLegal+K5*PossessionCost+N(Deals!R5)+N(Deals!T5)*HOAArrearsMonths) -> 7070 | R5: =IF(A5="","",N(Deals!M5)*(BrokerPct+SellerRTT+SellClosingPct+ConcessionsPct)) -> 36691.55 | S5: =IF(A5="","",Q5+O5+P5*M5) -> 84910.444 | T5: =IF(A5="","",N(Deals!M5)-R5-S5) -> 273398.01 | U5: =IF(A5="","",MIN(T5-FlipTarget,(T5-FlipMinAnnROI*M5/12*S5)/(1+FlipMinAnnROI*M5/12))) -> 207586.25 | V5: =IF(A5="","",IF(N(Deals!S5)=0,MAX(0,(U5)/(1+BuyerPremium)),IF((U5)>=(N(Deals!S5)+SheriffCostsFromBid)/(1-RTTPurchase)*(1+BuyerPremium),(U5)/(1+BuyerPremium),MAX(0,((U5)-N(Deals!S5)-SheriffCostsFromBid)/(BuyerPremium+RTTPurchase))))) -> 204518.47 | W5: =IF(A5="","",((V5)*(1+BuyerPremium)+IF(N(Deals!S5)=0,0,MIN(N(Deals!S5),MAX(0,N(Deals!S5)+SheriffCostsFromBid-(V5)*(1-RTTPurchase)))))+S5) -> 292496.69 | X5: =IF(A5="","",T5-((V5)*(1+BuyerPremium)+IF(N(Deals!S5)=0,0,MIN(N(Deals!S5),MAX(0,N(Deals!S5)+SheriffCostsFromBid-(V5)*(1-RTTPurchase)))))) -> 65811.756 | Y5: =IF(A5="","",IFERROR(X5/W5/(M5/12),0)) -> 0.15 | Z5: =IF(A5="","",N(Deals!N5)*12*(1-Vacancy)*(1-MgmtPct-MaintPct-CapexPct)-N(Deals!M5)*TaxRate-MAX(1,N(Deals!J5))*(InsPerUnit+WaterPerUnit)-N(Deals!T5)*12) -> 15783.59 | AA5: =IF(A5="","",Q5+O5+P5*N5) -> 84152.642 | AB5: =IF(A5="","",MAX(0,MIN(RefiLTV*N(Deals!M5),Z5/(RefiDSCR*12*PMT(RefiRate/12,RefiTerm*12,-1))))) -> 160674.4 | AC5: =IF(A5="","",Z5-AB5*12*PMT(RefiRate/12,RefiTerm*12,-1)) -> 2630.5983 | AD5: =IF(A5="","",IF(N(Deals!S5)=0,MAX(0,(Z5/HoldTarget-AA5)/(1+BuyerPremium)),IF((Z5/HoldTarget-AA5)>=(N(Deals!S5)+SheriffCostsFromBid)/(1-RTTPurchase)*(1+BuyerPremium),(Z5/HoldTarget-AA5)/(1+BuyerPremium),MAX(0,((Z5/HoldTarget-AA5)-N(Deals!S5)-SheriffCostsFromBid)/(BuyerPremium+RTTPurchase))))) -> 46677.118 | AE5: =IF(A5="","",IF(AC5<=0,0,IF(N(Deals!S5)=0,MAX(0,(AC5/HoldTarget+AB5*(1-RefiCostPct)-AA5)/(1+BuyerPremium)),IF((AC5/HoldTarget+AB5*(1-RefiCostPct)-AA5)>=(N(Deals!S5)+SheriffCostsFromBid)/(1-RTTPurchase)*(1+BuyerPremium),(AC5/HoldTarget+AB5*(1-RefiCostPct)-AA5)/(1+BuyerPremium),MAX(0,((AC5/HoldTarget+AB5*(1-RefiCostPct)-AA5)-N(Deals!S5)-SheriffCostsFromBid)/(BuyerPremium+RTTPurchase)))))) -> 92239.585 | AF5: =IF(A5="","",IF(HoldMeasure="Cash-on-cash",AE5,AD5)) -> 46677.118 | AG5: =IF(A5="","",((AF5)*(1+BuyerPremium)+IF(N(Deals!S5)=0,0,MIN(N(Deals!S5),MAX(0,N(Deals!S5)+SheriffCostsFromBid-(AF5)*(1-RTTPurchase)))))+AA5) -> 131529.92 | AH5: =IF(A5="","",IFERROR(Z5/AG5,0)) -> 0.12 | AI5: =IF(A5="","",AG5-AB5*(1-RefiCostPct)) -> -24324.25 | AJ5: =IF(A5="","",IF(AI5<=0,"All cash out",AC5/AI5)) -> All cash out | AK5: =IF(A5="","",IF(N(Deals!S5)=0,MAX(0,(T5-BuyerMarginPct*N(Deals!M5)-WholesaleMinFee)/(1+BuyerPremium)),IF((T5-BuyerMarginPct*N(Deals!M5)-WholesaleMinFee)>=(N(Deals!S5)+SheriffCostsFromBid)/(1-RTTPurchase)*(1+BuyerPremium),(T5-BuyerMarginPct*N(Deals!M5)-WholesaleMinFee)/(1+BuyerPremium),MAX(0,((T5-BuyerMarginPct*N(Deals!M5)-WholesaleMinFee)-N(Deals!S5)-SheriffCostsFromBid)/(BuyerPremium+RTTPurchase))))) -> 196204.93 | AL5: =IF(OR(A5="",N(Deals!U5)=0),"",Deals!U5*N(Deals!W5)) | AM5: =IF(AL5="","",DemoCost+N(Deals!V5)*BuildCostPSF*(1+SoftCostPct)+P5*(DeedMonths+K5*EjectMonths+BuildMonths+SellMonths)+Q5+AL5*(BrokerPct+SellerRTT+SellClosingPct+ConcessionsPct)) | AN5: =IF(AL5="","",IF(N(Deals!S5)=0,MAX(0,(AL5-AM5-MAX(FlipTarget,DevMarginPct*AL5))/(1+BuyerPremium)),IF((AL5-AM5-MAX(FlipTarget,DevMarginPct*AL5))>=(N(Deals!S5)+SheriffCostsFromBid)/(1-RTTPurchase)*(1+BuyerPremium),(AL5-AM5-MAX(FlipTarget,DevMarginPct*AL5))/(1+BuyerPremium),MAX(0,((AL5-AM5-MAX(FlipTarget,DevMarginPct*AL5))-N(Deals!S5)-SheriffCostsFromBid)/(BuyerPremium+RTTPurchase)))))
A6: =IF(Deals!A6="","",Deals!A6) -> 1318974-3 | B6: =IF(A6="","",Deals!B6) -> 3 Light cosmetic: ARV 375k, Light, occupied | C6: =IF(A6="","",IF(MAX(V6,AF6)<=0,"Pass",IF(V6>=AF6,"Flip","Value-add hold"))) -> Flip | D6: =IF(A6="","",MAX(V6,AF6)) -> 185181.5 | E6: =IF(A6="","",IF(D6<=0,"Pass",IF(N(Deals!D6)<=1,"$1 = awaiting minimum bid; re-check the morning of Nov 3",IF(D6<Deals!D6,"Max bid below opening bid: pass","Room of "&TEXT(D6-Deals!D6,"$#,##0")&" over opening bid")))) -> Room of $160,482 over opening bid | F6: =IF(A6="","",IF(C6="Flip",W6,IF(C6="Value-add hold",AG6,0))) -> 259174.29 | G6: =IF(A6="","",IF(C6="Flip",TEXT(X6,"$#,##0")&" profit, "&TEXT(Y6,"0%")&"/yr over "&TEXT(M6,"0")&" mo",IF(C6="Value-add hold",TEXT(AH6,"0.0%")&" yield on cost; "&IF(ISNUMBER(AJ6),TEXT(AJ6,"0.0%")&" cash-on-cash after refi","all cash out at refi"),""))) -> $80,992 profit, 15%/yr over 25 mo | H6: =IF(A6="","",IF(C6="Flip",IF(W6<=FlipCeiling,"In $300k flip box","Over flip ceiling: needs to be exceptional"),IF(C6="Value-add hold","Value-add",""))) -> In $300k flip box | I6: =IF(A6="","",TRIM(IF(AK6>D6,"Wholesale assignment supports "&TEXT(AK6,"$#,##0")&". ","")&IF(AND(ISNUMBER(AN6),N(AN6)>D6),"Teardown/new units supports "&TEXT(AN6,"$#,##0")&".",""))) -> Wholesale assignment supports $194,779. | J6: =IF(A6="","",TRIM(IF(Deals!F6="2nd","Plaintiff is 2nd: add senior mortgage to surviving liens. ",IF(Deals!F6<>"1st","Lien position unconfirmed. ",""))&IF(N(Deals!M6)=0,"No ARV yet. ","")&IF(N(Deals!G6)=0,"No building sf: rehab is allowance only. ","")&IF(AND(N(Deals!S6)>0,D6>0,D6*(1-RTTPurchase)-SheriffCostsFromBid<N(Deals!S6)),"City claims not fully paid at max bid; unpaid part is counted as cost. ","")&IF(K6=1,"Occupancy assumed: +"&TEXT(EjectMonths,"0")&" mo and possession cost. ",""))) -> Occupancy assumed: +8 mo and possession cost. | K6: =IF(A6="","",IF(OR(Deals!Q6="Occupied",AND(Deals!Q6<>"Vacant",UnknownAsOccupied="Y")),1,0)) -> 1 | L6: =IF(A6="","",IFERROR(INDEX(ScopeMonths,MATCH(Deals!O6,ScopeNames,0)),INDEX(ScopeMonths,3))) -> 2 | M6: =IF(A6="","",DeedMonths+K6*EjectMonths+L6+SellMonths) -> 25 | N6: =IF(A6="","",DeedMonths+K6*EjectMonths+L6+LeaseUpMonths) -> 24 | O6: =IF(A6="","",N(Deals!G6)*IFERROR(INDEX(ScopePSF,MATCH(Deals!O6,ScopeNames,0)),INDEX(ScopePSF,3))*(1+Contingency)+BlindAllowance+N(Deals!P6)) -> 35200 | P6: =IF(A6="","",IF(N(Deals!K6)>0,Deals!K6,N(Deals!M6))*TaxRate/12+VacantInsMo+SecuringMo+UtilitiesMo+N(Deals!T6)) -> 757.80245 | Q6: =IF(A6="","",SheriffFees+PurchaseTitle+CompelDeedLegal+K6*PossessionCost+N(Deals!R6)+N(Deals!T6)*HOAArrearsMonths) -> 17070 | R6: =IF(A6="","",N(Deals!M6)*(BrokerPct+SellerRTT+SellClosingPct+ConcessionsPct)) -> 34833.75 | S6: =IF(A6="","",Q6+O6+P6*M6) -> 71215.061 | T6: =IF(A6="","",N(Deals!M6)-R6-S6) -> 268951.19 | U6: =IF(A6="","",MIN(T6-FlipTarget,(T6-FlipMinAnnROI*M6/12*S6)/(1+FlipMinAnnROI*M6/12))) -> 187959.22 | V6: =IF(A6="","",IF(N(Deals!S6)=0,MAX(0,(U6)/(1+BuyerPremium)),IF((U6)>=(N(Deals!S6)+SheriffCostsFromBid)/(1-RTTPurchase)*(1+BuyerPremium),(U6)/(1+BuyerPremium),MAX(0,((U6)-N(Deals!S6)-SheriffCostsFromBid)/(BuyerPremium+RTTPurchase))))) -> 185181.5 | W6: =IF(A6="","",((V6)*(1+BuyerPremium)+IF(N(Deals!S6)=0,0,MIN(N(Deals!S6),MAX(0,N(Deals!S6)+SheriffCostsFromBid-(V6)*(1-RTTPurchase)))))+S6) -> 259174.29 | X6: =IF(A6="","",T6-((V6)*(1+BuyerPremium)+IF(N(Deals!S6)=0,0,MIN(N(Deals!S6),MAX(0,N(Deals!S6)+SheriffCostsFromBid-(V6)*(1-RTTPurchase)))))) -> 80991.964 | Y6: =IF(A6="","",IFERROR(X6/W6/(M6/12),0)) -> 0.15 | Z6: =IF(A6="","",N(Deals!N6)*12*(1-Vacancy)*(1-MgmtPct-MaintPct-CapexPct)-N(Deals!M6)*TaxRate-MAX(1,N(Deals!J6))*(InsPerUnit+WaterPerUnit)-N(Deals!T6)*12) -> 16063.55 | AA6: =IF(A6="","",Q6+O6+P6*N6) -> 70457.259 | AB6: =IF(A6="","",MAX(0,MIN(RefiLTV*N(Deals!M6),Z6/(RefiDSCR*12*PMT(RefiRate/12,RefiTerm*12,-1))))) -> 163524.35 | AC6: =IF(A6="","",Z6-AB6*12*PMT(RefiRate/12,RefiTerm*12,-1)) -> 2677.2583 | AD6: =IF(A6="","",IF(N(Deals!S6)=0,MAX(0,(Z6/HoldTarget-AA6)/(1+BuyerPremium)),IF((Z6/HoldTarget-AA6)>=(N(Deals!S6)+SheriffCostsFromBid)/(1-RTTPurchase)*(1+BuyerPremium),(Z6/HoldTarget-AA6)/(1+BuyerPremium),MAX(0,((Z6/HoldTarget-AA6)-N(Deals!S6)-SheriffCostsFromBid)/(BuyerPremium+RTTPurchase))))) -> 62468.628 | AE6: =IF(A6="","",IF(AC6<=0,0,IF(N(Deals!S6)=0,MAX(0,(AC6/HoldTarget+AB6*(1-RefiCostPct)-AA6)/(1+BuyerPremium)),IF((AC6/HoldTarget+AB6*(1-RefiCostPct)-AA6)>=(N(Deals!S6)+SheriffCostsFromBid)/(1-RTTPurchase)*(1+BuyerPremium),(AC6/HoldTarget+AB6*(1-RefiCostPct)-AA6)/(1+BuyerPremium),MAX(0,((AC6/HoldTarget+AB6*(1-RefiCostPct)-AA6)-N(Deals!S6)-SheriffCostsFromBid)/(BuyerPremium+RTTPurchase)))))) -> 108839.25 | AF6: =IF(A6="","",IF(HoldMeasure="Cash-on-cash",AE6,AD6)) -> 62468.628 | AG6: =IF(A6="","",((AF6)*(1+BuyerPremium)+IF(N(Deals!S6)=0,0,MIN(N(Deals!S6),MAX(0,N(Deals!S6)+SheriffCostsFromBid-(AF6)*(1-RTTPurchase)))))+AA6) -> 133862.92 | AH6: =IF(A6="","",IFERROR(Z6/AG6,0)) -> 0.12 | AI6: =IF(A6="","",AG6-AB6*(1-RefiCostPct)) -> -24755.7 | AJ6: =IF(A6="","",IF(AI6<=0,"All cash out",AC6/AI6)) -> All cash out | AK6: =IF(A6="","",IF(N(Deals!S6)=0,MAX(0,(T6-BuyerMarginPct*N(Deals!M6)-WholesaleMinFee)/(1+BuyerPremium)),IF((T6-BuyerMarginPct*N(Deals!M6)-WholesaleMinFee)>=(N(Deals!S6)+SheriffCostsFromBid)/(1-RTTPurchase)*(1+BuyerPremium),(T6-BuyerMarginPct*N(Deals!M6)-WholesaleMinFee)/(1+BuyerPremium),MAX(0,((T6-BuyerMarginPct*N(Deals!M6)-WholesaleMinFee)-N(Deals!S6)-SheriffCostsFromBid)/(BuyerPremium+RTTPurchase))))) -> 194779.5 | AL6: =IF(OR(A6="",N(Deals!U6)=0),"",Deals!U6*N(Deals!W6)) | AM6: =IF(AL6="","",DemoCost+N(Deals!V6)*BuildCostPSF*(1+SoftCostPct)+P6*(DeedMonths+K6*EjectMonths+BuildMonths+SellMonths)+Q6+AL6*(BrokerPct+SellerRTT+SellClosingPct+ConcessionsPct)) | AN6: =IF(AL6="","",IF(N(Deals!S6)=0,MAX(0,(AL6-AM6-MAX(FlipTarget,DevMarginPct*AL6))/(1+BuyerPremium)),IF((AL6-AM6-MAX(FlipTarget,DevMarginPct*AL6))>=(N(Deals!S6)+SheriffCostsFromBid)/(1-RTTPurchase)*(1+BuyerPremium),(AL6-AM6-MAX(FlipTarget,DevMarginPct*AL6))/(1+BuyerPremium),MAX(0,((AL6-AM6-MAX(FlipTarget,DevMarginPct*AL6))-N(Deals!S6)-SheriffCostsFromBid)/(BuyerPremium+RTTPurchase)))))
A7: =IF(Deals!A7="","",Deals!A7) -> 1318974-4 | B7: =IF(A7="","",Deals!B7) -> 4 Downside: ARV 365k, Heavy, occupied | C7: =IF(A7="","",IF(MAX(V7,AF7)<=0,"Pass",IF(V7>=AF7,"Flip","Value-add hold"))) -> Flip | D7: =IF(A7="","",MAX(V7,AF7)) -> 123711.53 | E7: =IF(A7="","",IF(D7<=0,"Pass",IF(N(Deals!D7)<=1,"$1 = awaiting minimum bid; re-check the morning of Nov 3",IF(D7<Deals!D7,"Max bid below opening bid: pass","Room of "&TEXT(D7-Deals!D7,"$#,##0")&" over opening bid")))) -> Room of $99,012 over opening bid | F7: =IF(A7="","",IF(C7="Flip",W7,IF(C7="Value-add hold",AG7,0))) -> 245255.67 | G7: =IF(A7="","",IF(C7="Flip",TEXT(X7,"$#,##0")&" profit, "&TEXT(Y7,"0%")&"/yr over "&TEXT(M7,"0")&" mo",IF(C7="Value-add hold",TEXT(AH7,"0.0%")&" yield on cost; "&IF(ISNUMBER(AJ7),TEXT(AJ7,"0.0%")&" cash-on-cash after refi","all cash out at refi"),""))) -> $85,839 profit, 15%/yr over 28 mo | H7: =IF(A7="","",IF(C7="Flip",IF(W7<=FlipCeiling,"In $300k flip box","Over flip ceiling: needs to be exceptional"),IF(C7="Value-add hold","Value-add",""))) -> In $300k flip box | I7: =IF(A7="","",TRIM(IF(AK7>D7,"Wholesale assignment supports "&TEXT(AK7,"$#,##0")&". ","")&IF(AND(ISNUMBER(AN7),N(AN7)>D7),"Teardown/new units supports "&TEXT(AN7,"$#,##0")&".",""))) -> Wholesale assignment supports $139,563. | J7: =IF(A7="","",TRIM(IF(Deals!F7="2nd","Plaintiff is 2nd: add senior mortgage to surviving liens. ",IF(Deals!F7<>"1st","Lien position unconfirmed. ",""))&IF(N(Deals!M7)=0,"No ARV yet. ","")&IF(N(Deals!G7)=0,"No building sf: rehab is allowance only. ","")&IF(AND(N(Deals!S7)>0,D7>0,D7*(1-RTTPurchase)-SheriffCostsFromBid<N(Deals!S7)),"City claims not fully paid at max bid; unpaid part is counted as cost. ","")&IF(K7=1,"Occupancy assumed: +"&TEXT(EjectMonths,"0")&" mo and possession cost. ",""))) -> Occupancy assumed: +8 mo and possession cost. | K7: =IF(A7="","",IF(OR(Deals!Q7="Occupied",AND(Deals!Q7<>"Vacant",UnknownAsOccupied="Y")),1,0)) -> 1 | L7: =IF(A7="","",IFERROR(INDEX(ScopeMonths,MATCH(Deals!O7,ScopeNames,0)),INDEX(ScopeMonths,3))) -> 5 | M7: =IF(A7="","",DeedMonths+K7*EjectMonths+L7+SellMonths) -> 28 | N7: =IF(A7="","",DeedMonths+K7*EjectMonths+L7+LeaseUpMonths) -> 27 | O7: =IF(A7="","",N(Deals!G7)*IFERROR(INDEX(ScopePSF,MATCH(Deals!O7,ScopeNames,0)),INDEX(ScopePSF,3))*(1+Contingency)+BlindAllowance+N(Deals!P7)) -> 81400 | P7: =IF(A7="","",IF(N(Deals!K7)>0,Deals!K7,N(Deals!M7))*TaxRate/12+VacantInsMo+SecuringMo+UtilitiesMo+N(Deals!T7)) -> 757.80245 | Q7: =IF(A7="","",SheriffFees+PurchaseTitle+CompelDeedLegal+K7*PossessionCost+N(Deals!R7)+N(Deals!T7)*HOAArrearsMonths) -> 17070 | R7: =IF(A7="","",N(Deals!M7)*(BrokerPct+SellerRTT+SellClosingPct+ConcessionsPct)) -> 33904.85 | S7: =IF(A7="","",Q7+O7+P7*M7) -> 119688.47 | T7: =IF(A7="","",N(Deals!M7)-R7-S7) -> 211406.68 | U7: =IF(A7="","",MIN(T7-FlipTarget,(T7-FlipMinAnnROI*M7/12*S7)/(1+FlipMinAnnROI*M7/12))) -> 125567.2 | V7: =IF(A7="","",IF(N(Deals!S7)=0,MAX(0,(U7)/(1+BuyerPremium)),IF((U7)>=(N(Deals!S7)+SheriffCostsFromBid)/(1-RTTPurchase)*(1+BuyerPremium),(U7)/(1+BuyerPremium),MAX(0,((U7)-N(Deals!S7)-SheriffCostsFromBid)/(BuyerPremium+RTTPurchase))))) -> 123711.53 | W7: =IF(A7="","",((V7)*(1+BuyerPremium)+IF(N(Deals!S7)=0,0,MIN(N(Deals!S7),MAX(0,N(Deals!S7)+SheriffCostsFromBid-(V7)*(1-RTTPurchase)))))+S7) -> 245255.67 | X7: =IF(A7="","",T7-((V7)*(1+BuyerPremium)+IF(N(Deals!S7)=0,0,MIN(N(Deals!S7),MAX(0,N(Deals!S7)+SheriffCostsFromBid-(V7)*(1-RTTPurchase)))))) -> 85839.483 | Y7: =IF(A7="","",IFERROR(X7/W7/(M7/12),0)) -> 0.15 | Z7: =IF(A7="","",N(Deals!N7)*12*(1-Vacancy)*(1-MgmtPct-MaintPct-CapexPct)-N(Deals!M7)*TaxRate-MAX(1,N(Deals!J7))*(InsPerUnit+WaterPerUnit)-N(Deals!T7)*12) -> 16203.53 | AA7: =IF(A7="","",Q7+O7+P7*N7) -> 118930.67 | AB7: =IF(A7="","",MAX(0,MIN(RefiLTV*N(Deals!M7),Z7/(RefiDSCR*12*PMT(RefiRate/12,RefiTerm*12,-1))))) -> 164949.32 | AC7: =IF(A7="","",Z7-AB7*12*PMT(RefiRate/12,RefiTerm*12,-1)) -> 2700.5883 | AD7: =IF(A7="","",IF(N(Deals!S7)=0,MAX(0,(Z7/HoldTarget-AA7)/(1+BuyerPremium)),IF((Z7/HoldTarget-AA7)>=(N(Deals!S7)+SheriffCostsFromBid)/(1-RTTPurchase)*(1+BuyerPremium),(Z7/HoldTarget-AA7)/(1+BuyerPremium),MAX(0,((Z7/HoldTarget-AA7)-N(Deals!S7)-SheriffCostsFromBid)/(BuyerPremium+RTTPurchase))))) -> 15860.838 | AE7: =IF(A7="","",IF(AC7<=0,0,IF(N(Deals!S7)=0,MAX(0,(AC7/HoldTarget+AB7*(1-RefiCostPct)-AA7)/(1+BuyerPremium)),IF((AC7/HoldTarget+AB7*(1-RefiCostPct)-AA7)>=(N(Deals!S7)+SheriffCostsFromBid)/(1-RTTPurchase)*(1+BuyerPremium),(AC7/HoldTarget+AB7*(1-RefiCostPct)-AA7)/(1+BuyerPremium),MAX(0,((AC7/HoldTarget+AB7*(1-RefiCostPct)-AA7)-N(Deals!S7)-SheriffCostsFromBid)/(BuyerPremium+RTTPurchase)))))) -> 62635.544 | AF7: =IF(A7="","",IF(HoldMeasure="Cash-on-cash",AE7,AD7)) -> 15860.838 | AG7: =IF(A7="","",((AF7)*(1+BuyerPremium)+IF(N(Deals!S7)=0,0,MIN(N(Deals!S7),MAX(0,N(Deals!S7)+SheriffCostsFromBid-(AF7)*(1-RTTPurchase)))))+AA7) -> 135029.42 | AH7: =IF(A7="","",IFERROR(Z7/AG7,0)) -> 0.12 | AI7: =IF(A7="","",AG7-AB7*(1-RefiCostPct)) -> -24971.424 | AJ7: =IF(A7="","",IF(AI7<=0,"All cash out",AC7/AI7)) -> All cash out | AK7: =IF(A7="","",IF(N(Deals!S7)=0,MAX(0,(T7-BuyerMarginPct*N(Deals!M7)-WholesaleMinFee)/(1+BuyerPremium)),IF((T7-BuyerMarginPct*N(Deals!M7)-WholesaleMinFee)>=(N(Deals!S7)+SheriffCostsFromBid)/(1-RTTPurchase)*(1+BuyerPremium),(T7-BuyerMarginPct*N(Deals!M7)-WholesaleMinFee)/(1+BuyerPremium),MAX(0,((T7-BuyerMarginPct*N(Deals!M7)-WholesaleMinFee)-N(Deals!S7)-SheriffCostsFromBid)/(BuyerPremium+RTTPurchase))))) -> 139563.23 | AL7: =IF(OR(A7="",N(Deals!U7)=0),"",Deals!U7*N(Deals!W7)) | AM7: =IF(AL7="","",DemoCost+N(Deals!V7)*BuildCostPSF*(1+SoftCostPct)+P7*(DeedMonths+K7*EjectMonths+BuildMonths+SellMonths)+Q7+AL7*(BrokerPct+SellerRTT+SellClosingPct+ConcessionsPct)) | AN7: =IF(AL7="","",IF(N(Deals!S7)=0,MAX(0,(AL7-AM7-MAX(FlipTarget,DevMarginPct*AL7))/(1+BuyerPremium)),IF((AL7-AM7-MAX(FlipTarget,DevMarginPct*AL7))>=(N(Deals!S7)+SheriffCostsFromBid)/(1-RTTPurchase)*(1+BuyerPremium),(AL7-AM7-MAX(FlipTarget,DevMarginPct*AL7))/(1+BuyerPremium),MAX(0,((AL7-AM7-MAX(FlipTarget,DevMarginPct*AL7))-N(Deals!S7)-SheriffCostsFromBid)/(BuyerPremium+RTTPurchase)))))
A8: =IF(Deals!A8="","",Deals!A8) -> 1318974-5 | B8: =IF(A8="","",Deals!B8) -> 5 Upside: ARV 425k, Medium + half bath, occupied | C8: =IF(A8="","",IF(MAX(V8,AF8)<=0,"Pass",IF(V8>=AF8,"Flip","Value-add hold"))) -> Flip | D8: =IF(A8="","",MAX(V8,AF8)) -> 175356.6 | E8: =IF(A8="","",IF(D8<=0,"Pass",IF(N(Deals!D8)<=1,"$1 = awaiting minimum bid; re-check the morning of Nov 3",IF(D8<Deals!D8,"Max bid below opening bid: pass","Room of "&TEXT(D8-Deals!D8,"$#,##0")&" over opening bid")))) -> Room of $150,657 over opening bid | F8: =IF(A8="","",IF(C8="Flip",W8,IF(C8="Value-add hold",AG8,0))) -> 290959.81 | G8: =IF(A8="","",IF(C8="Flip",TEXT(X8,"$#,##0")&" profit, "&TEXT(Y8,"0%")&"/yr over "&TEXT(M8,"0")&" mo",IF(C8="Value-add hold",TEXT(AH8,"0.0%")&" yield on cost; "&IF(ISNUMBER(AJ8),TEXT(AJ8,"0.0%")&" cash-on-cash after refi","all cash out at refi"),""))) -> $94,562 profit, 15%/yr over 26 mo | H8: =IF(A8="","",IF(C8="Flip",IF(W8<=FlipCeiling,"In $300k flip box","Over flip ceiling: needs to be exceptional"),IF(C8="Value-add hold","Value-add",""))) -> In $300k flip box | I8: =IF(A8="","",TRIM(IF(AK8>D8,"Wholesale assignment supports "&TEXT(AK8,"$#,##0")&". ","")&IF(AND(ISNUMBER(AN8),N(AN8)>D8),"Teardown/new units supports "&TEXT(AN8,"$#,##0")&".",""))) -> Wholesale assignment supports $190,935. | J8: =IF(A8="","",TRIM(IF(Deals!F8="2nd","Plaintiff is 2nd: add senior mortgage to surviving liens. ",IF(Deals!F8<>"1st","Lien position unconfirmed. ",""))&IF(N(Deals!M8)=0,"No ARV yet. ","")&IF(N(Deals!G8)=0,"No building sf: rehab is allowance only. ","")&IF(AND(N(Deals!S8)>0,D8>0,D8*(1-RTTPurchase)-SheriffCostsFromBid<N(Deals!S8)),"City claims not fully paid at max bid; unpaid part is counted as cost. ","")&IF(K8=1,"Occupancy assumed: +"&TEXT(EjectMonths,"0")&" mo and possession cost. ",""))) -> Occupancy assumed: +8 mo and possession cost. | K8: =IF(A8="","",IF(OR(Deals!Q8="Occupied",AND(Deals!Q8<>"Vacant",UnknownAsOccupied="Y")),1,0)) -> 1 | L8: =IF(A8="","",IFERROR(INDEX(ScopeMonths,MATCH(Deals!O8,ScopeNames,0)),INDEX(ScopeMonths,3))) -> 3 | M8: =IF(A8="","",DeedMonths+K8*EjectMonths+L8+SellMonths) -> 26 | N8: =IF(A8="","",DeedMonths+K8*EjectMonths+L8+LeaseUpMonths) -> 25 | O8: =IF(A8="","",N(Deals!G8)*IFERROR(INDEX(ScopePSF,MATCH(Deals!O8,ScopeNames,0)),INDEX(ScopePSF,3))*(1+Contingency)+BlindAllowance+N(Deals!P8)) -> 76200 | P8: =IF(A8="","",IF(N(Deals!K8)>0,Deals!K8,N(Deals!M8))*TaxRate/12+VacantInsMo+SecuringMo+UtilitiesMo+N(Deals!T8)) -> 757.80245 | Q8: =IF(A8="","",SheriffFees+PurchaseTitle+CompelDeedLegal+K8*PossessionCost+N(Deals!R8)+N(Deals!T8)*HOAArrearsMonths) -> 17070 | R8: =IF(A8="","",N(Deals!M8)*(BrokerPct+SellerRTT+SellClosingPct+ConcessionsPct)) -> 39478.25 | S8: =IF(A8="","",Q8+O8+P8*M8) -> 112972.86 | T8: =IF(A8="","",N(Deals!M8)-R8-S8) -> 272548.89 | U8: =IF(A8="","",MIN(T8-FlipTarget,(T8-FlipMinAnnROI*M8/12*S8)/(1+FlipMinAnnROI*M8/12))) -> 177986.95 | V8: =IF(A8="","",IF(N(Deals!S8)=0,MAX(0,(U8)/(1+BuyerPremium)),IF((U8)>=(N(Deals!S8)+SheriffCostsFromBid)/(1-RTTPurchase)*(1+BuyerPremium),(U8)/(1+BuyerPremium),MAX(0,((U8)-N(Deals!S8)-SheriffCostsFromBid)/(BuyerPremium+RTTPurchase))))) -> 175356.6 | W8: =IF(A8="","",((V8)*(1+BuyerPremium)+IF(N(Deals!S8)=0,0,MIN(N(Deals!S8),MAX(0,N(Deals!S8)+SheriffCostsFromBid-(V8)*(1-RTTPurchase)))))+S8) -> 290959.81 | X8: =IF(A8="","",T8-((V8)*(1+BuyerPremium)+IF(N(Deals!S8)=0,0,MIN(N(Deals!S8),MAX(0,N(Deals!S8)+SheriffCostsFromBid-(V8)*(1-RTTPurchase)))))) -> 94561.939 | Y8: =IF(A8="","",IFERROR(X8/W8/(M8/12),0)) -> 0.15 | Z8: =IF(A8="","",N(Deals!N8)*12*(1-Vacancy)*(1-MgmtPct-MaintPct-CapexPct)-N(Deals!M8)*TaxRate-MAX(1,N(Deals!J8))*(InsPerUnit+WaterPerUnit)-N(Deals!T8)*12) -> 15363.65 | AA8: =IF(A8="","",Q8+O8+P8*N8) -> 112215.06 | AB8: =IF(A8="","",MAX(0,MIN(RefiLTV*N(Deals!M8),Z8/(RefiDSCR*12*PMT(RefiRate/12,RefiTerm*12,-1))))) -> 156399.48 | AC8: =IF(A8="","",Z8-AB8*12*PMT(RefiRate/12,RefiTerm*12,-1)) -> 2560.6083 | AD8: =IF(A8="","",IF(N(Deals!S8)=0,MAX(0,(Z8/HoldTarget-AA8)/(1+BuyerPremium)),IF((Z8/HoldTarget-AA8)>=(N(Deals!S8)+SheriffCostsFromBid)/(1-RTTPurchase)*(1+BuyerPremium),(Z8/HoldTarget-AA8)/(1+BuyerPremium),MAX(0,((Z8/HoldTarget-AA8)-N(Deals!S8)-SheriffCostsFromBid)/(BuyerPremium+RTTPurchase))))) -> 15581.631 | AE8: =IF(A8="","",IF(AC8<=0,0,IF(N(Deals!S8)=0,MAX(0,(AC8/HoldTarget+AB8*(1-RefiCostPct)-AA8)/(1+BuyerPremium)),IF((AC8/HoldTarget+AB8*(1-RefiCostPct)-AA8)>=(N(Deals!S8)+SheriffCostsFromBid)/(1-RTTPurchase)*(1+BuyerPremium),(AC8/HoldTarget+AB8*(1-RefiCostPct)-AA8)/(1+BuyerPremium),MAX(0,((AC8/HoldTarget+AB8*(1-RefiCostPct)-AA8)-N(Deals!S8)-SheriffCostsFromBid)/(BuyerPremium+RTTPurchase)))))) -> 59931.857 | AF8: =IF(A8="","",IF(HoldMeasure="Cash-on-cash",AE8,AD8)) -> 15581.631 | AG8: =IF(A8="","",((AF8)*(1+BuyerPremium)+IF(N(Deals!S8)=0,0,MIN(N(Deals!S8),MAX(0,N(Deals!S8)+SheriffCostsFromBid-(AF8)*(1-RTTPurchase)))))+AA8) -> 128030.42 | AH8: =IF(A8="","",IFERROR(Z8/AG8,0)) -> 0.12 | AI8: =IF(A8="","",AG8-AB8*(1-RefiCostPct)) -> -23677.077 | AJ8: =IF(A8="","",IF(AI8<=0,"All cash out",AC8/AI8)) -> All cash out | AK8: =IF(A8="","",IF(N(Deals!S8)=0,MAX(0,(T8-BuyerMarginPct*N(Deals!M8)-WholesaleMinFee)/(1+BuyerPremium)),IF((T8-BuyerMarginPct*N(Deals!M8)-WholesaleMinFee)>=(N(Deals!S8)+SheriffCostsFromBid)/(1-RTTPurchase)*(1+BuyerPremium),(T8-BuyerMarginPct*N(Deals!M8)-WholesaleMinFee)/(1+BuyerPremium),MAX(0,((T8-BuyerMarginPct*N(Deals!M8)-WholesaleMinFee)-N(Deals!S8)-SheriffCostsFromBid)/(BuyerPremium+RTTPurchase))))) -> 190934.86 | AL8: =IF(OR(A8="",N(Deals!U8)=0),"",Deals!U8*N(Deals!W8)) | AM8: =IF(AL8="","",DemoCost+N(Deals!V8)*BuildCostPSF*(1+SoftCostPct)+P8*(DeedMonths+K8*EjectMonths+BuildMonths+SellMonths)+Q8+AL8*(BrokerPct+SellerRTT+SellClosingPct+ConcessionsPct)) | AN8: =IF(AL8="","",IF(N(Deals!S8)=0,MAX(0,(AL8-AM8-MAX(FlipTarget,DevMarginPct*AL8))/(1+BuyerPremium)),IF((AL8-AM8-MAX(FlipTarget,DevMarginPct*AL8))>=(N(Deals!S8)+SheriffCostsFromBid)/(1-RTTPurchase)*(1+BuyerPremium),(AL8-AM8-MAX(FlipTarget,DevMarginPct*AL8))/(1+BuyerPremium),MAX(0,((AL8-AM8-MAX(FlipTarget,DevMarginPct*AL8))-N(Deals!S8)-SheriffCostsFromBid)/(BuyerPremium+RTTPurchase)))))
A9: =IF(Deals!A9="","",Deals!A9) -> 1318974-6 | B9: =IF(A9="","",Deals!B9) -> 6 Slow ejectment proxy: ARV 395k, Medium, occupied, Heavy timeline | C9: =IF(A9="","",IF(MAX(V9,AF9)<=0,"Pass",IF(V9>=AF9,"Flip","Value-add hold"))) -> Flip | D9: =IF(A9="","",MAX(V9,AF9)) -> 143571.62 | E9: =IF(A9="","",IF(D9<=0,"Pass",IF(N(Deals!D9)<=1,"$1 = awaiting minimum bid; re-check the morning of Nov 3",IF(D9<Deals!D9,"Max bid below opening bid: pass","Room of "&TEXT(D9-Deals!D9,"$#,##0")&" over opening bid")))) -> Room of $118,872 over opening bid | F9: =IF(A9="","",IF(C9="Flip",W9,IF(C9="Value-add hold",AG9,0))) -> 265413.67 | G9: =IF(A9="","",IF(C9="Flip",TEXT(X9,"$#,##0")&" profit, "&TEXT(Y9,"0%")&"/yr over "&TEXT(M9,"0")&" mo",IF(C9="Value-add hold",TEXT(AH9,"0.0%")&" yield on cost; "&IF(ISNUMBER(AJ9),TEXT(AJ9,"0.0%")&" cash-on-cash after refi","all cash out at refi"),""))) -> $92,895 profit, 15%/yr over 28 mo | H9: =IF(A9="","",IF(C9="Flip",IF(W9<=FlipCeiling,"In $300k flip box","Over flip ceiling: needs to be exceptional"),IF(C9="Value-add hold","Value-add",""))) -> In $300k flip box | I9: =IF(A9="","",TRIM(IF(AK9>D9,"Wholesale assignment supports "&TEXT(AK9,"$#,##0")&". ","")&IF(AND(ISNUMBER(AN9),N(AN9)>D9),"Teardown/new units supports "&TEXT(AN9,"$#,##0")&".",""))) -> Wholesale assignment supports $161,941. | J9: =IF(A9="","",TRIM(IF(Deals!F9="2nd","Plaintiff is 2nd: add senior mortgage to surviving liens. ",IF(Deals!F9<>"1st","Lien position unconfirmed. ",""))&IF(N(Deals!M9)=0,"No ARV yet. ","")&IF(N(Deals!G9)=0,"No building sf: rehab is allowance only. ","")&IF(AND(N(Deals!S9)>0,D9>0,D9*(1-RTTPurchase)-SheriffCostsFromBid<N(Deals!S9)),"City claims not fully paid at max bid; unpaid part is counted as cost. ","")&IF(K9=1,"Occupancy assumed: +"&TEXT(EjectMonths,"0")&" mo and possession cost. ",""))) -> Occupancy assumed: +8 mo and possession cost. | K9: =IF(A9="","",IF(OR(Deals!Q9="Occupied",AND(Deals!Q9<>"Vacant",UnknownAsOccupied="Y")),1,0)) -> 1 | L9: =IF(A9="","",IFERROR(INDEX(ScopeMonths,MATCH(Deals!O9,ScopeNames,0)),INDEX(ScopeMonths,3))) -> 5 | M9: =IF(A9="","",DeedMonths+K9*EjectMonths+L9+SellMonths) -> 28 | N9: =IF(A9="","",DeedMonths+K9*EjectMonths+L9+LeaseUpMonths) -> 27 | O9: =IF(A9="","",N(Deals!G9)*IFERROR(INDEX(ScopePSF,MATCH(Deals!O9,ScopeNames,0)),INDEX(ScopePSF,3))*(1+Contingency)+BlindAllowance+N(Deals!P9)) -> 81400 | P9: =IF(A9="","",IF(N(Deals!K9)>0,Deals!K9,N(Deals!M9))*TaxRate/12+VacantInsMo+SecuringMo+UtilitiesMo+N(Deals!T9)) -> 757.80245 | Q9: =IF(A9="","",SheriffFees+PurchaseTitle+CompelDeedLegal+K9*PossessionCost+N(Deals!R9)+N(Deals!T9)*HOAArrearsMonths) -> 17070 | R9: =IF(A9="","",N(Deals!M9)*(BrokerPct+SellerRTT+SellClosingPct+ConcessionsPct)) -> 36691.55 | S9: =IF(A9="","",Q9+O9+P9*M9) -> 119688.47 | T9: =IF(A9="","",N(Deals!M9)-R9-S9) -> 238619.98 | U9: =IF(A9="","",MIN(T9-FlipTarget,(T9-FlipMinAnnROI*M9/12*S9)/(1+FlipMinAnnROI*M9/12))) -> 145725.2 | V9: =IF(A9="","",IF(N(Deals!S9)=0,MAX(0,(U9)/(1+BuyerPremium)),IF((U9)>=(N(Deals!S9)+SheriffCostsFromBid)/(1-RTTPurchase)*(1+BuyerPremium),(U9)/(1+BuyerPremium),MAX(0,((U9)-N(Deals!S9)-SheriffCostsFromBid)/(BuyerPremium+RTTPurchase))))) -> 143571.62 | W9: =IF(A9="","",((V9)*(1+BuyerPremium)+IF(N(Deals!S9)=0,0,MIN(N(Deals!S9),MAX(0,N(Deals!S9)+SheriffCostsFromBid-(V9)*(1-RTTPurchase)))))+S9) -> 265413.67 | X9: =IF(A9="","",T9-((V9)*(1+BuyerPremium)+IF(N(Deals!S9)=0,0,MIN(N(Deals!S9),MAX(0,N(Deals!S9)+SheriffCostsFromBid-(V9)*(1-RTTPurchase)))))) -> 92894.783 | Y9: =IF(A9="","",IFERROR(X9/W9/(M9/12),0)) -> 0.15 | Z9: =IF(A9="","",N(Deals!N9)*12*(1-Vacancy)*(1-MgmtPct-MaintPct-CapexPct)-N(Deals!M9)*TaxRate-MAX(1,N(Deals!J9))*(InsPerUnit+WaterPerUnit)-N(Deals!T9)*12) -> 15783.59 | AA9: =IF(A9="","",Q9+O9+P9*N9) -> 118930.67 | AB9: =IF(A9="","",MAX(0,MIN(RefiLTV*N(Deals!M9),Z9/(RefiDSCR*12*PMT(RefiRate/12,RefiTerm*12,-1))))) -> 160674.4 | AC9: =IF(A9="","",Z9-AB9*12*PMT(RefiRate/12,RefiTerm*12,-1)) -> 2630.5983 | AD9: =IF(A9="","",IF(N(Deals!S9)=0,MAX(0,(Z9/HoldTarget-AA9)/(1+BuyerPremium)),IF((Z9/HoldTarget-AA9)>=(N(Deals!S9)+SheriffCostsFromBid)/(1-RTTPurchase)*(1+BuyerPremium),(Z9/HoldTarget-AA9)/(1+BuyerPremium),MAX(0,((Z9/HoldTarget-AA9)-N(Deals!S9)-SheriffCostsFromBid)/(BuyerPremium+RTTPurchase))))) -> 12413.055 | AE9: =IF(A9="","",IF(AC9<=0,0,IF(N(Deals!S9)=0,MAX(0,(AC9/HoldTarget+AB9*(1-RefiCostPct)-AA9)/(1+BuyerPremium)),IF((AC9/HoldTarget+AB9*(1-RefiCostPct)-AA9)>=(N(Deals!S9)+SheriffCostsFromBid)/(1-RTTPurchase)*(1+BuyerPremium),(AC9/HoldTarget+AB9*(1-RefiCostPct)-AA9)/(1+BuyerPremium),MAX(0,((AC9/HoldTarget+AB9*(1-RefiCostPct)-AA9)-N(Deals!S9)-SheriffCostsFromBid)/(BuyerPremium+RTTPurchase)))))) -> 57975.521 | AF9: =IF(A9="","",IF(HoldMeasure="Cash-on-cash",AE9,AD9)) -> 12413.055 | AG9: =IF(A9="","",((AF9)*(1+BuyerPremium)+IF(N(Deals!S9)=0,0,MIN(N(Deals!S9),MAX(0,N(Deals!S9)+SheriffCostsFromBid-(AF9)*(1-RTTPurchase)))))+AA9) -> 131529.92 | AH9: =IF(A9="","",IFERROR(Z9/AG9,0)) -> 0.12 | AI9: =IF(A9="","",AG9-AB9*(1-RefiCostPct)) -> -24324.25 | AJ9: =IF(A9="","",IF(AI9<=0,"All cash out",AC9/AI9)) -> All cash out | AK9: =IF(A9="","",IF(N(Deals!S9)=0,MAX(0,(T9-BuyerMarginPct*N(Deals!M9)-WholesaleMinFee)/(1+BuyerPremium)),IF((T9-BuyerMarginPct*N(Deals!M9)-WholesaleMinFee)>=(N(Deals!S9)+SheriffCostsFromBid)/(1-RTTPurchase)*(1+BuyerPremium),(T9-BuyerMarginPct*N(Deals!M9)-WholesaleMinFee)/(1+BuyerPremium),MAX(0,((T9-BuyerMarginPct*N(Deals!M9)-WholesaleMinFee)-N(Deals!S9)-SheriffCostsFromBid)/(BuyerPremium+RTTPurchase))))) -> 161940.87 | AL9: =IF(OR(A9="",N(Deals!U9)=0),"",Deals!U9*N(Deals!W9)) | AM9: =IF(AL9="","",DemoCost+N(Deals!V9)*BuildCostPSF*(1+SoftCostPct)+P9*(DeedMonths+K9*EjectMonths+BuildMonths+SellMonths)+Q9+AL9*(BrokerPct+SellerRTT+SellClosingPct+ConcessionsPct)) | AN9: =IF(AL9="","",IF(N(Deals!S9)=0,MAX(0,(AL9-AM9-MAX(FlipTarget,DevMarginPct*AL9))/(1+BuyerPremium)),IF((AL9-AM9-MAX(FlipTarget,DevMarginPct*AL9))>=(N(Deals!S9)+SheriffCostsFromBid)/(1-RTTPurchase)*(1+BuyerPremium),(AL9-AM9-MAX(FlipTarget,DevMarginPct*AL9))/(1+BuyerPremium),MAX(0,((AL9-AM9-MAX(FlipTarget,DevMarginPct*AL9))-N(Deals!S9)-SheriffCostsFromBid)/(BuyerPremium+RTTPurchase)))))
A10: =IF(Deals!A10="","",Deals!A10) | B10: =IF(A10="","",Deals!B10) | C10: =IF(A10="","",IF(MAX(V10,AF10)<=0,"Pass",IF(V10>=AF10,"Flip","Value-add hold"))) | D10: =IF(A10="","",MAX(V10,AF10)) | E10: =IF(A10="","",IF(D10<=0,"Pass",IF(N(Deals!D10)<=1,"$1 = awaiting minimum bid; re-check the morning of Nov 3",IF(D10<Deals!D10,"Max bid below opening bid: pass","Room of "&TEXT(D10-Deals!D10,"$#,##0")&" over opening bid")))) | F10: =IF(A10="","",IF(C10="Flip",W10,IF(C10="Value-add hold",AG10,0))) | G10: =IF(A10="","",IF(C10="Flip",TEXT(X10,"$#,##0")&" profit, "&TEXT(Y10,"0%")&"/yr over "&TEXT(M10,"0")&" mo",IF(C10="Value-add hold",TEXT(AH10,"0.0%")&" yield on cost; "&IF(ISNUMBER(AJ10),TEXT(AJ10,"0.0%")&" cash-on-cash after refi","all cash out at refi"),""))) | H10: =IF(A10="","",IF(C10="Flip",IF(W10<=FlipCeiling,"In $300k flip box","Over flip ceiling: needs to be exceptional"),IF(C10="Value-add hold","Value-add",""))) | I10: =IF(A10="","",TRIM(IF(AK10>D10,"Wholesale assignment supports "&TEXT(AK10,"$#,##0")&". ","")&IF(AND(ISNUMBER(AN10),N(AN10)>D10),"Teardown/new units supports "&TEXT(AN10,"$#,##0")&".",""))) | J10: =IF(A10="","",TRIM(IF(Deals!F10="2nd","Plaintiff is 2nd: add senior mortgage to surviving liens. ",IF(Deals!F10<>"1st","Lien position unconfirmed. ",""))&IF(N(Deals!M10)=0,"No ARV yet. ","")&IF(N(Deals!G10)=0,"No building sf: rehab is allowance only. ","")&IF(AND(N(Deals!S10)>0,D10>0,D10*(1-RTTPurchase)-SheriffCostsFromBid<N(Deals!S10)),"City claims not fully paid at max bid; unpaid part is counted as cost. ","")&IF(K10=1,"Occupancy assumed: +"&TEXT(EjectMonths,"0")&" mo and possession cost. ",""))) | K10: =IF(A10="","",IF(OR(Deals!Q10="Occupied",AND(Deals!Q10<>"Vacant",UnknownAsOccupied="Y")),1,0)) | L10: =IF(A10="","",IFERROR(INDEX(ScopeMonths,MATCH(Deals!O10,ScopeNames,0)),INDEX(ScopeMonths,3))) | M10: =IF(A10="","",DeedMonths+K10*EjectMonths+L10+SellMonths) | N10: =IF(A10="","",DeedMonths+K10*EjectMonths+L10+LeaseUpMonths) | O10: =IF(A10="","",N(Deals!G10)*IFERROR(INDEX(ScopePSF,MATCH(Deals!O10,ScopeNames,0)),INDEX(ScopePSF,3))*(1+Contingency)+BlindAllowance+N(Deals!P10)) | P10: =IF(A10="","",IF(N(Deals!K10)>0,Deals!K10,N(Deals!M10))*TaxRate/12+VacantInsMo+SecuringMo+UtilitiesMo+N(Deals!T10)) | Q10: =IF(A10="","",SheriffFees+PurchaseTitle+CompelDeedLegal+K10*PossessionCost+N(Deals!R10)+N(Deals!T10)*HOAArrearsMonths) | R10: =IF(A10="","",N(Deals!M10)*(BrokerPct+SellerRTT+SellClosingPct+ConcessionsPct)) | S10: =IF(A10="","",Q10+O10+P10*M10) | T10: =IF(A10="","",N(Deals!M10)-R10-S10) | U10: =IF(A10="","",MIN(T10-FlipTarget,(T10-FlipMinAnnROI*M10/12*S10)/(1+FlipMinAnnROI*M10/12))) | V10: =IF(A10="","",IF(N(Deals!S10)=0,MAX(0,(U10)/(1+BuyerPremium)),IF((U10)>=(N(Deals!S10)+SheriffCostsFromBid)/(1-RTTPurchase)*(1+BuyerPremium),(U10)/(1+BuyerPremium),MAX(0,((U10)-N(Deals!S10)-SheriffCostsFromBid)/(BuyerPremium+RTTPurchase))))) | W10: =IF(A10="","",((V10)*(1+BuyerPremium)+IF(N(Deals!S10)=0,0,MIN(N(Deals!S10),MAX(0,N(Deals!S10)+SheriffCostsFromBid-(V10)*(1-RTTPurchase)))))+S10) | X10: =IF(A10="","",T10-((V10)*(1+BuyerPremium)+IF(N(Deals!S10)=0,0,MIN(N(Deals!S10),MAX(0,N(Deals!S10)+SheriffCostsFromBid-(V10)*(1-RTTPurchase)))))) | Y10: =IF(A10="","",IFERROR(X10/W10/(M10/12),0)) | Z10: =IF(A10="","",N(Deals!N10)*12*(1-Vacancy)*(1-MgmtPct-MaintPct-CapexPct)-N(Deals!M10)*TaxRate-MAX(1,N(Deals!J10))*(InsPerUnit+WaterPerUnit)-N(Deals!T10)*12) | AA10: =IF(A10="","",Q10+O10+P10*N10) | AB10: =IF(A10="","",MAX(0,MIN(RefiLTV*N(Deals!M10),Z10/(RefiDSCR*12*PMT(RefiRate/12,RefiTerm*12,-1))))) | AC10: =IF(A10="","",Z10-AB10*12*PMT(RefiRate/12,RefiTerm*12,-1)) | AD10: =IF(A10="","",IF(N(Deals!S10)=0,MAX(0,(Z10/HoldTarget-AA10)/(1+BuyerPremium)),IF((Z10/HoldTarget-AA10)>=(N(Deals!S10)+SheriffCostsFromBid)/(1-RTTPurchase)*(1+BuyerPremium),(Z10/HoldTarget-AA10)/(1+BuyerPremium),MAX(0,((Z10/HoldTarget-AA10)-N(Deals!S10)-SheriffCostsFromBid)/(BuyerPremium+RTTPurchase))))) | AE10: =IF(A10="","",IF(AC10<=0,0,IF(N(Deals!S10)=0,MAX(0,(AC10/HoldTarget+AB10*(1-RefiCostPct)-AA10)/(1+BuyerPremium)),IF((AC10/HoldTarget+AB10*(1-RefiCostPct)-AA10)>=(N(Deals!S10)+SheriffCostsFromBid)/(1-RTTPurchase)*(1+BuyerPremium),(AC10/HoldTarget+AB10*(1-RefiCostPct)-AA10)/(1+BuyerPremium),MAX(0,((AC10/HoldTarget+AB10*(1-RefiCostPct)-AA10)-N(Deals!S10)-SheriffCostsFromBid)/(BuyerPremium+RTTPurchase)))))) | AF10: =IF(A10="","",IF(HoldMeasure="Cash-on-cash",AE10,AD10)) | AG10: =IF(A10="","",((AF10)*(1+BuyerPremium)+IF(N(Deals!S10)=0,0,MIN(N(Deals!S10),MAX(0,N(Deals!S10)+SheriffCostsFromBid-(AF10)*(1-RTTPurchase)))))+AA10) | AH10: =IF(A10="","",IFERROR(Z10/AG10,0)) | AI10: =IF(A10="","",AG10-AB10*(1-RefiCostPct)) | AJ10: =IF(A10="","",IF(AI10<=0,"All cash out",AC10/AI10)) | AK10: =IF(A10="","",IF(N(Deals!S10)=0,MAX(0,(T10-BuyerMarginPct*N(Deals!M10)-WholesaleMinFee)/(1+BuyerPremium)),IF((T10-BuyerMarginPct*N(Deals!M10)-WholesaleMinFee)>=(N(Deals!S10)+SheriffCostsFromBid)/(1-RTTPurchase)*(1+BuyerPremium),(T10-BuyerMarginPct*N(Deals!M10)-WholesaleMinFee)/(1+BuyerPremium),MAX(0,((T10-BuyerMarginPct*N(Deals!M10)-WholesaleMinFee)-N(Deals!S10)-SheriffCostsFromBid)/(BuyerPremium+RTTPurchase))))) | AL10: =IF(OR(A10="",N(Deals!U10)=0),"",Deals!U10*N(Deals!W10)) | AM10: =IF(AL10="","",DemoCost+N(Deals!V10)*BuildCostPSF*(1+SoftCostPct)+P10*(DeedMonths+K10*EjectMonths+BuildMonths+SellMonths)+Q10+AL10*(BrokerPct+SellerRTT+SellClosingPct+ConcessionsPct)) | AN10: =IF(AL10="","",IF(N(Deals!S10)=0,MAX(0,(AL10-AM10-MAX(FlipTarget,DevMarginPct*AL10))/(1+BuyerPremium)),IF((AL10-AM10-MAX(FlipTarget,DevMarginPct*AL10))>=(N(Deals!S10)+SheriffCostsFromBid)/(1-RTTPurchase)*(1+BuyerPremium),(AL10-AM10-MAX(FlipTarget,DevMarginPct*AL10))/(1+BuyerPremium),MAX(0,((AL10-AM10-MAX(FlipTarget,DevMarginPct*AL10))-N(Deals!S10)-SheriffCostsFromBid)/(BuyerPremium+RTTPurchase)))))
A11: =IF(Deals!A11="","",Deals!A11) | B11: =IF(A11="","",Deals!B11) | C11: =IF(A11="","",IF(MAX(V11,AF11)<=0,"Pass",IF(V11>=AF11,"Flip","Value-add hold"))) | D11: =IF(A11="","",MAX(V11,AF11)) | E11: =IF(A11="","",IF(D11<=0,"Pass",IF(N(Deals!D11)<=1,"$1 = awaiting minimum bid; re-check the morning of Nov 3",IF(D11<Deals!D11,"Max bid below opening bid: pass","Room of "&TEXT(D11-Deals!D11,"$#,##0")&" over opening bid")))) | F11: =IF(A11="","",IF(C11="Flip",W11,IF(C11="Value-add hold",AG11,0))) | G11: =IF(A11="","",IF(C11="Flip",TEXT(X11,"$#,##0")&" profit, "&TEXT(Y11,"0%")&"/yr over "&TEXT(M11,"0")&" mo",IF(C11="Value-add hold",TEXT(AH11,"0.0%")&" yield on cost; "&IF(ISNUMBER(AJ11),TEXT(AJ11,"0.0%")&" cash-on-cash after refi","all cash out at refi"),""))) | H11: =IF(A11="","",IF(C11="Flip",IF(W11<=FlipCeiling,"In $300k flip box","Over flip ceiling: needs to be exceptional"),IF(C11="Value-add hold","Value-add",""))) | I11: =IF(A11="","",TRIM(IF(AK11>D11,"Wholesale assignment supports "&TEXT(AK11,"$#,##0")&". ","")&IF(AND(ISNUMBER(AN11),N(AN11)>D11),"Teardown/new units supports "&TEXT(AN11,"$#,##0")&".",""))) | J11: =IF(A11="","",TRIM(IF(Deals!F11="2nd","Plaintiff is 2nd: add senior mortgage to surviving liens. ",IF(Deals!F11<>"1st","Lien position unconfirmed. ",""))&IF(N(Deals!M11)=0,"No ARV yet. ","")&IF(N(Deals!G11)=0,"No building sf: rehab is allowance only. ","")&IF(AND(N(Deals!S11)>0,D11>0,D11*(1-RTTPurchase)-SheriffCostsFromBid<N(Deals!S11)),"City claims not fully paid at max bid; unpaid part is counted as cost. ","")&IF(K11=1,"Occupancy assumed: +"&TEXT(EjectMonths,"0")&" mo and possession cost. ",""))) | K11: =IF(A11="","",IF(OR(Deals!Q11="Occupied",AND(Deals!Q11<>"Vacant",UnknownAsOccupied="Y")),1,0)) | L11: =IF(A11="","",IFERROR(INDEX(ScopeMonths,MATCH(Deals!O11,ScopeNames,0)),INDEX(ScopeMonths,3))) | M11: =IF(A11="","",DeedMonths+K11*EjectMonths+L11+SellMonths) | N11: =IF(A11="","",DeedMonths+K11*EjectMonths+L11+LeaseUpMonths) | O11: =IF(A11="","",N(Deals!G11)*IFERROR(INDEX(ScopePSF,MATCH(Deals!O11,ScopeNames,0)),INDEX(ScopePSF,3))*(1+Contingency)+BlindAllowance+N(Deals!P11)) | P11: =IF(A11="","",IF(N(Deals!K11)>0,Deals!K11,N(Deals!M11))*TaxRate/12+VacantInsMo+SecuringMo+UtilitiesMo+N(Deals!T11)) | Q11: =IF(A11="","",SheriffFees+PurchaseTitle+CompelDeedLegal+K11*PossessionCost+N(Deals!R11)+N(Deals!T11)*HOAArrearsMonths) | R11: =IF(A11="","",N(Deals!M11)*(BrokerPct+SellerRTT+SellClosingPct+ConcessionsPct)) | S11: =IF(A11="","",Q11+O11+P11*M11) | T11: =IF(A11="","",N(Deals!M11)-R11-S11) | U11: =IF(A11="","",MIN(T11-FlipTarget,(T11-FlipMinAnnROI*M11/12*S11)/(1+FlipMinAnnROI*M11/12))) | V11: =IF(A11="","",IF(N(Deals!S11)=0,MAX(0,(U11)/(1+BuyerPremium)),IF((U11)>=(N(Deals!S11)+SheriffCostsFromBid)/(1-RTTPurchase)*(1+BuyerPremium),(U11)/(1+BuyerPremium),MAX(0,((U11)-N(Deals!S11)-SheriffCostsFromBid)/(BuyerPremium+RTTPurchase))))) | W11: =IF(A11="","",((V11)*(1+BuyerPremium)+IF(N(Deals!S11)=0,0,MIN(N(Deals!S11),MAX(0,N(Deals!S11)+SheriffCostsFromBid-(V11)*(1-RTTPurchase)))))+S11) | X11: =IF(A11="","",T11-((V11)*(1+BuyerPremium)+IF(N(Deals!S11)=0,0,MIN(N(Deals!S11),MAX(0,N(Deals!S11)+SheriffCostsFromBid-(V11)*(1-RTTPurchase)))))) | Y11: =IF(A11="","",IFERROR(X11/W11/(M11/12),0)) | Z11: =IF(A11="","",N(Deals!N11)*12*(1-Vacancy)*(1-MgmtPct-MaintPct-CapexPct)-N(Deals!M11)*TaxRate-MAX(1,N(Deals!J11))*(InsPerUnit+WaterPerUnit)-N(Deals!T11)*12) | AA11: =IF(A11="","",Q11+O11+P11*N11) | AB11: =IF(A11="","",MAX(0,MIN(RefiLTV*N(Deals!M11),Z11/(RefiDSCR*12*PMT(RefiRate/12,RefiTerm*12,-1))))) | AC11: =IF(A11="","",Z11-AB11*12*PMT(RefiRate/12,RefiTerm*12,-1)) | AD11: =IF(A11="","",IF(N(Deals!S11)=0,MAX(0,(Z11/HoldTarget-AA11)/(1+BuyerPremium)),IF((Z11/HoldTarget-AA11)>=(N(Deals!S11)+SheriffCostsFromBid)/(1-RTTPurchase)*(1+BuyerPremium),(Z11/HoldTarget-AA11)/(1+BuyerPremium),MAX(0,((Z11/HoldTarget-AA11)-N(Deals!S11)-SheriffCostsFromBid)/(BuyerPremium+RTTPurchase))))) | AE11: =IF(A11="","",IF(AC11<=0,0,IF(N(Deals!S11)=0,MAX(0,(AC11/HoldTarget+AB11*(1-RefiCostPct)-AA11)/(1+BuyerPremium)),IF((AC11/HoldTarget+AB11*(1-RefiCostPct)-AA11)>=(N(Deals!S11)+SheriffCostsFromBid)/(1-RTTPurchase)*(1+BuyerPremium),(AC11/HoldTarget+AB11*(1-RefiCostPct)-AA11)/(1+BuyerPremium),MAX(0,((AC11/HoldTarget+AB11*(1-RefiCostPct)-AA11)-N(Deals!S11)-SheriffCostsFromBid)/(BuyerPremium+RTTPurchase)))))) | AF11: =IF(A11="","",IF(HoldMeasure="Cash-on-cash",AE11,AD11)) | AG11: =IF(A11="","",((AF11)*(1+BuyerPremium)+IF(N(Deals!S11)=0,0,MIN(N(Deals!S11),MAX(0,N(Deals!S11)+SheriffCostsFromBid-(AF11)*(1-RTTPurchase)))))+AA11) | AH11: =IF(A11="","",IFERROR(Z11/AG11,0)) | AI11: =IF(A11="","",AG11-AB11*(1-RefiCostPct)) | AJ11: =IF(A11="","",IF(AI11<=0,"All cash out",AC11/AI11)) | AK11: =IF(A11="","",IF(N(Deals!S11)=0,MAX(0,(T11-BuyerMarginPct*N(Deals!M11)-WholesaleMinFee)/(1+BuyerPremium)),IF((T11-BuyerMarginPct*N(Deals!M11)-WholesaleMinFee)>=(N(Deals!S11)+SheriffCostsFromBid)/(1-RTTPurchase)*(1+BuyerPremium),(T11-BuyerMarginPct*N(Deals!M11)-WholesaleMinFee)/(1+BuyerPremium),MAX(0,((T11-BuyerMarginPct*N(Deals!M11)-WholesaleMinFee)-N(Deals!S11)-SheriffCostsFromBid)/(BuyerPremium+RTTPurchase))))) | AL11: =IF(OR(A11="",N(Deals!U11)=0),"",Deals!U11*N(Deals!W11)) | AM11: =IF(AL11="","",DemoCost+N(Deals!V11)*BuildCostPSF*(1+SoftCostPct)+P11*(DeedMonths+K11*EjectMonths+BuildMonths+SellMonths)+Q11+AL11*(BrokerPct+SellerRTT+SellClosingPct+ConcessionsPct)) | AN11: =IF(AL11="","",IF(N(Deals!S11)=0,MAX(0,(AL11-AM11-MAX(FlipTarget,DevMarginPct*AL11))/(1+BuyerPremium)),IF((AL11-AM11-MAX(FlipTarget,DevMarginPct*AL11))>=(N(Deals!S11)+SheriffCostsFromBid)/(1-RTTPurchase)*(1+BuyerPremium),(AL11-AM11-MAX(FlipTarget,DevMarginPct*AL11))/(1+BuyerPremium),MAX(0,((AL11-AM11-MAX(FlipTarget,DevMarginPct*AL11))-N(Deals!S11)-SheriffCostsFromBid)/(BuyerPremium+RTTPurchase)))))
A12: =IF(Deals!A12="","",Deals!A12) | B12: =IF(A12="","",Deals!B12) | C12: =IF(A12="","",IF(MAX(V12,AF12)<=0,"Pass",IF(V12>=AF12,"Flip","Value-add hold"))) | D12: =IF(A12="","",MAX(V12,AF12)) | E12: =IF(A12="","",IF(D12<=0,"Pass",IF(N(Deals!D12)<=1,"$1 = awaiting minimum bid; re-check the morning of Nov 3",IF(D12<Deals!D12,"Max bid below opening bid: pass","Room of "&TEXT(D12-Deals!D12,"$#,##0")&" over opening bid")))) | F12: =IF(A12="","",IF(C12="Flip",W12,IF(C12="Value-add hold",AG12,0))) | G12: =IF(A12="","",IF(C12="Flip",TEXT(X12,"$#,##0")&" profit, "&TEXT(Y12,"0%")&"/yr over "&TEXT(M12,"0")&" mo",IF(C12="Value-add hold",TEXT(AH12,"0.0%")&" yield on cost; "&IF(ISNUMBER(AJ12),TEXT(AJ12,"0.0%")&" cash-on-cash after refi","all cash out at refi"),""))) | H12: =IF(A12="","",IF(C12="Flip",IF(W12<=FlipCeiling,"In $300k flip box","Over flip ceiling: needs to be exceptional"),IF(C12="Value-add hold","Value-add",""))) | I12: =IF(A12="","",TRIM(IF(AK12>D12,"Wholesale assignment supports "&TEXT(AK12,"$#,##0")&". ","")&IF(AND(ISNUMBER(AN12),N(AN12)>D12),"Teardown/new units supports "&TEXT(AN12,"$#,##0")&".",""))) | J12: =IF(A12="","",TRIM(IF(Deals!F12="2nd","Plaintiff is 2nd: add senior mortgage to surviving liens. ",IF(Deals!F12<>"1st","Lien position unconfirmed. ",""))&IF(N(Deals!M12)=0,"No ARV yet. ","")&IF(N(Deals!G12)=0,"No building sf: rehab is allowance only. ","")&IF(AND(N(Deals!S12)>0,D12>0,D12*(1-RTTPurchase)-SheriffCostsFromBid<N(Deals!S12)),"City claims not fully paid at max bid; unpaid part is counted as cost. ","")&IF(K12=1,"Occupancy assumed: +"&TEXT(EjectMonths,"0")&" mo and possession cost. ",""))) | K12: =IF(A12="","",IF(OR(Deals!Q12="Occupied",AND(Deals!Q12<>"Vacant",UnknownAsOccupied="Y")),1,0)) | L12: =IF(A12="","",IFERROR(INDEX(ScopeMonths,MATCH(Deals!O12,ScopeNames,0)),INDEX(ScopeMonths,3))) | M12: =IF(A12="","",DeedMonths+K12*EjectMonths+L12+SellMonths) | N12: =IF(A12="","",DeedMonths+K12*EjectMonths+L12+LeaseUpMonths) | O12: =IF(A12="","",N(Deals!G12)*IFERROR(INDEX(ScopePSF,MATCH(Deals!O12,ScopeNames,0)),INDEX(ScopePSF,3))*(1+Contingency)+BlindAllowance+N(Deals!P12)) | P12: =IF(A12="","",IF(N(Deals!K12)>0,Deals!K12,N(Deals!M12))*TaxRate/12+VacantInsMo+SecuringMo+UtilitiesMo+N(Deals!T12)) | Q12: =IF(A12="","",SheriffFees+PurchaseTitle+CompelDeedLegal+K12*PossessionCost+N(Deals!R12)+N(Deals!T12)*HOAArrearsMonths) | R12: =IF(A12="","",N(Deals!M12)*(BrokerPct+SellerRTT+SellClosingPct+ConcessionsPct)) | S12: =IF(A12="","",Q12+O12+P12*M12) | T12: =IF(A12="","",N(Deals!M12)-R12-S12) | U12: =IF(A12="","",MIN(T12-FlipTarget,(T12-FlipMinAnnROI*M12/12*S12)/(1+FlipMinAnnROI*M12/12))) | V12: =IF(A12="","",IF(N(Deals!S12)=0,MAX(0,(U12)/(1+BuyerPremium)),IF((U12)>=(N(Deals!S12)+SheriffCostsFromBid)/(1-RTTPurchase)*(1+BuyerPremium),(U12)/(1+BuyerPremium),MAX(0,((U12)-N(Deals!S12)-SheriffCostsFromBid)/(BuyerPremium+RTTPurchase))))) | W12: =IF(A12="","",((V12)*(1+BuyerPremium)+IF(N(Deals!S12)=0,0,MIN(N(Deals!S12),MAX(0,N(Deals!S12)+SheriffCostsFromBid-(V12)*(1-RTTPurchase)))))+S12) | X12: =IF(A12="","",T12-((V12)*(1+BuyerPremium)+IF(N(Deals!S12)=0,0,MIN(N(Deals!S12),MAX(0,N(Deals!S12)+SheriffCostsFromBid-(V12)*(1-RTTPurchase)))))) | Y12: =IF(A12="","",IFERROR(X12/W12/(M12/12),0)) | Z12: =IF(A12="","",N(Deals!N12)*12*(1-Vacancy)*(1-MgmtPct-MaintPct-CapexPct)-N(Deals!M12)*TaxRate-MAX(1,N(Deals!J12))*(InsPerUnit+WaterPerUnit)-N(Deals!T12)*12) | AA12: =IF(A12="","",Q12+O12+P12*N12) | AB12: =IF(A12="","",MAX(0,MIN(RefiLTV*N(Deals!M12),Z12/(RefiDSCR*12*PMT(RefiRate/12,RefiTerm*12,-1))))) | AC12: =IF(A12="","",Z12-AB12*12*PMT(RefiRate/12,RefiTerm*12,-1)) | AD12: =IF(A12="","",IF(N(Deals!S12)=0,MAX(0,(Z12/HoldTarget-AA12)/(1+BuyerPremium)),IF((Z12/HoldTarget-AA12)>=(N(Deals!S12)+SheriffCostsFromBid)/(1-RTTPurchase)*(1+BuyerPremium),(Z12/HoldTarget-AA12)/(1+BuyerPremium),MAX(0,((Z12/HoldTarget-AA12)-N(Deals!S12)-SheriffCostsFromBid)/(BuyerPremium+RTTPurchase))))) | AE12: =IF(A12="","",IF(AC12<=0,0,IF(N(Deals!S12)=0,MAX(0,(AC12/HoldTarget+AB12*(1-RefiCostPct)-AA12)/(1+BuyerPremium)),IF((AC12/HoldTarget+AB12*(1-RefiCostPct)-AA12)>=(N(Deals!S12)+SheriffCostsFromBid)/(1-RTTPurchase)*(1+BuyerPremium),(AC12/HoldTarget+AB12*(1-RefiCostPct)-AA12)/(1+BuyerPremium),MAX(0,((AC12/HoldTarget+AB12*(1-RefiCostPct)-AA12)-N(Deals!S12)-SheriffCostsFromBid)/(BuyerPremium+RTTPurchase)))))) | AF12: =IF(A12="","",IF(HoldMeasure="Cash-on-cash",AE12,AD12)) | AG12: =IF(A12="","",((AF12)*(1+BuyerPremium)+IF(N(Deals!S12)=0,0,MIN(N(Deals!S12),MAX(0,N(Deals!S12)+SheriffCostsFromBid-(AF12)*(1-RTTPurchase)))))+AA12) | AH12: =IF(A12="","",IFERROR(Z12/AG12,0)) | AI12: =IF(A12="","",AG12-AB12*(1-RefiCostPct)) | AJ12: =IF(A12="","",IF(AI12<=0,"All cash out",AC12/AI12)) | AK12: =IF(A12="","",IF(N(Deals!S12)=0,MAX(0,(T12-BuyerMarginPct*N(Deals!M12)-WholesaleMinFee)/(1+BuyerPremium)),IF((T12-BuyerMarginPct*N(Deals!M12)-WholesaleMinFee)>=(N(Deals!S12)+SheriffCostsFromBid)/(1-RTTPurchase)*(1+BuyerPremium),(T12-BuyerMarginPct*N(Deals!M12)-WholesaleMinFee)/(1+BuyerPremium),MAX(0,((T12-BuyerMarginPct*N(Deals!M12)-WholesaleMinFee)-N(Deals!S12)-SheriffCostsFromBid)/(BuyerPremium+RTTPurchase))))) | AL12: =IF(OR(A12="",N(Deals!U12)=0),"",Deals!U12*N(Deals!W12)) | AM12: =IF(AL12="","",DemoCost+N(Deals!V12)*BuildCostPSF*(1+SoftCostPct)+P12*(DeedMonths+K12*EjectMonths+BuildMonths+SellMonths)+Q12+AL12*(BrokerPct+SellerRTT+SellClosingPct+ConcessionsPct)) | AN12: =IF(AL12="","",IF(N(Deals!S12)=0,MAX(0,(AL12-AM12-MAX(FlipTarget,DevMarginPct*AL12))/(1+BuyerPremium)),IF((AL12-AM12-MAX(FlipTarget,DevMarginPct*AL12))>=(N(Deals!S12)+SheriffCostsFromBid)/(1-RTTPurchase)*(1+BuyerPremium),(AL12-AM12-MAX(FlipTarget,DevMarginPct*AL12))/(1+BuyerPremium),MAX(0,((AL12-AM12-MAX(FlipTarget,DevMarginPct*AL12))-N(Deals!S12)-SheriffCostsFromBid)/(BuyerPremium+RTTPurchase)))))
A13: =IF(Deals!A13="","",Deals!A13) | B13: =IF(A13="","",Deals!B13) | C13: =IF(A13="","",IF(MAX(V13,AF13)<=0,"Pass",IF(V13>=AF13,"Flip","Value-add hold"))) | D13: =IF(A13="","",MAX(V13,AF13)) | E13: =IF(A13="","",IF(D13<=0,"Pass",IF(N(Deals!D13)<=1,"$1 = awaiting minimum bid; re-check the morning of Nov 3",IF(D13<Deals!D13,"Max bid below opening bid: pass","Room of "&TEXT(D13-Deals!D13,"$#,##0")&" over opening bid")))) | F13: =IF(A13="","",IF(C13="Flip",W13,IF(C13="Value-add hold",AG13,0))) | G13: =IF(A13="","",IF(C13="Flip",TEXT(X13,"$#,##0")&" profit, "&TEXT(Y13,"0%")&"/yr over "&TEXT(M13,"0")&" mo",IF(C13="Value-add hold",TEXT(AH13,"0.0%")&" yield on cost; "&IF(ISNUMBER(AJ13),TEXT(AJ13,"0.0%")&" cash-on-cash after refi","all cash out at refi"),""))) | H13: =IF(A13="","",IF(C13="Flip",IF(W13<=FlipCeiling,"In $300k flip box","Over flip ceiling: needs to be exceptional"),IF(C13="Value-add hold","Value-add",""))) | I13: =IF(A13="","",TRIM(IF(AK13>D13,"Wholesale assignment supports "&TEXT(AK13,"$#,##0")&". ","")&IF(AND(ISNUMBER(AN13),N(AN13)>D13),"Teardown/new units supports "&TEXT(AN13,"$#,##0")&".",""))) | J13: =IF(A13="","",TRIM(IF(Deals!F13="2nd","Plaintiff is 2nd: add senior mortgage to surviving liens. ",IF(Deals!F13<>"1st","Lien position unconfirmed. ",""))&IF(N(Deals!M13)=0,"No ARV yet. ","")&IF(N(Deals!G13)=0,"No building sf: rehab is allowance only. ","")&IF(AND(N(Deals!S13)>0,D13>0,D13*(1-RTTPurchase)-SheriffCostsFromBid<N(Deals!S13)),"City claims not fully paid at max bid; unpaid part is counted as cost. ","")&IF(K13=1,"Occupancy assumed: +"&TEXT(EjectMonths,"0")&" mo and possession cost. ",""))) | K13: =IF(A13="","",IF(OR(Deals!Q13="Occupied",AND(Deals!Q13<>"Vacant",UnknownAsOccupied="Y")),1,0)) | L13: =IF(A13="","",IFERROR(INDEX(ScopeMonths,MATCH(Deals!O13,ScopeNames,0)),INDEX(ScopeMonths,3))) | M13: =IF(A13="","",DeedMonths+K13*EjectMonths+L13+SellMonths) | N13: =IF(A13="","",DeedMonths+K13*EjectMonths+L13+LeaseUpMonths) | O13: =IF(A13="","",N(Deals!G13)*IFERROR(INDEX(ScopePSF,MATCH(Deals!O13,ScopeNames,0)),INDEX(ScopePSF,3))*(1+Contingency)+BlindAllowance+N(Deals!P13)) | P13: =IF(A13="","",IF(N(Deals!K13)>0,Deals!K13,N(Deals!M13))*TaxRate/12+VacantInsMo+SecuringMo+UtilitiesMo+N(Deals!T13)) | Q13: =IF(A13="","",SheriffFees+PurchaseTitle+CompelDeedLegal+K13*PossessionCost+N(Deals!R13)+N(Deals!T13)*HOAArrearsMonths) | R13: =IF(A13="","",N(Deals!M13)*(BrokerPct+SellerRTT+SellClosingPct+ConcessionsPct)) | S13: =IF(A13="","",Q13+O13+P13*M13) | T13: =IF(A13="","",N(Deals!M13)-R13-S13) | U13: =IF(A13="","",MIN(T13-FlipTarget,(T13-FlipMinAnnROI*M13/12*S13)/(1+FlipMinAnnROI*M13/12))) | V13: =IF(A13="","",IF(N(Deals!S13)=0,MAX(0,(U13)/(1+BuyerPremium)),IF((U13)>=(N(Deals!S13)+SheriffCostsFromBid)/(1-RTTPurchase)*(1+BuyerPremium),(U13)/(1+BuyerPremium),MAX(0,((U13)-N(Deals!S13)-SheriffCostsFromBid)/(BuyerPremium+RTTPurchase))))) | W13: =IF(A13="","",((V13)*(1+BuyerPremium)+IF(N(Deals!S13)=0,0,MIN(N(Deals!S13),MAX(0,N(Deals!S13)+SheriffCostsFromBid-(V13)*(1-RTTPurchase)))))+S13) | X13: =IF(A13="","",T13-((V13)*(1+BuyerPremium)+IF(N(Deals!S13)=0,0,MIN(N(Deals!S13),MAX(0,N(Deals!S13)+SheriffCostsFromBid-(V13)*(1-RTTPurchase)))))) | Y13: =IF(A13="","",IFERROR(X13/W13/(M13/12),0)) | Z13: =IF(A13="","",N(Deals!N13)*12*(1-Vacancy)*(1-MgmtPct-MaintPct-CapexPct)-N(Deals!M13)*TaxRate-MAX(1,N(Deals!J13))*(InsPerUnit+WaterPerUnit)-N(Deals!T13)*12) | AA13: =IF(A13="","",Q13+O13+P13*N13) | AB13: =IF(A13="","",MAX(0,MIN(RefiLTV*N(Deals!M13),Z13/(RefiDSCR*12*PMT(RefiRate/12,RefiTerm*12,-1))))) | AC13: =IF(A13="","",Z13-AB13*12*PMT(RefiRate/12,RefiTerm*12,-1)) | AD13: =IF(A13="","",IF(N(Deals!S13)=0,MAX(0,(Z13/HoldTarget-AA13)/(1+BuyerPremium)),IF((Z13/HoldTarget-AA13)>=(N(Deals!S13)+SheriffCostsFromBid)/(1-RTTPurchase)*(1+BuyerPremium),(Z13/HoldTarget-AA13)/(1+BuyerPremium),MAX(0,((Z13/HoldTarget-AA13)-N(Deals!S13)-SheriffCostsFromBid)/(BuyerPremium+RTTPurchase))))) | AE13: =IF(A13="","",IF(AC13<=0,0,IF(N(Deals!S13)=0,MAX(0,(AC13/HoldTarget+AB13*(1-RefiCostPct)-AA13)/(1+BuyerPremium)),IF((AC13/HoldTarget+AB13*(1-RefiCostPct)-AA13)>=(N(Deals!S13)+SheriffCostsFromBid)/(1-RTTPurchase)*(1+BuyerPremium),(AC13/HoldTarget+AB13*(1-RefiCostPct)-AA13)/(1+BuyerPremium),MAX(0,((AC13/HoldTarget+AB13*(1-RefiCostPct)-AA13)-N(Deals!S13)-SheriffCostsFromBid)/(BuyerPremium+RTTPurchase)))))) | AF13: =IF(A13="","",IF(HoldMeasure="Cash-on-cash",AE13,AD13)) | AG13: =IF(A13="","",((AF13)*(1+BuyerPremium)+IF(N(Deals!S13)=0,0,MIN(N(Deals!S13),MAX(0,N(Deals!S13)+SheriffCostsFromBid-(AF13)*(1-RTTPurchase)))))+AA13) | AH13: =IF(A13="","",IFERROR(Z13/AG13,0)) | AI13: =IF(A13="","",AG13-AB13*(1-RefiCostPct)) | AJ13: =IF(A13="","",IF(AI13<=0,"All cash out",AC13/AI13)) | AK13: =IF(A13="","",IF(N(Deals!S13)=0,MAX(0,(T13-BuyerMarginPct*N(Deals!M13)-WholesaleMinFee)/(1+BuyerPremium)),IF((T13-BuyerMarginPct*N(Deals!M13)-WholesaleMinFee)>=(N(Deals!S13)+SheriffCostsFromBid)/(1-RTTPurchase)*(1+BuyerPremium),(T13-BuyerMarginPct*N(Deals!M13)-WholesaleMinFee)/(1+BuyerPremium),MAX(0,((T13-BuyerMarginPct*N(Deals!M13)-WholesaleMinFee)-N(Deals!S13)-SheriffCostsFromBid)/(BuyerPremium+RTTPurchase))))) | AL13: =IF(OR(A13="",N(Deals!U13)=0),"",Deals!U13*N(Deals!W13)) | AM13: =IF(AL13="","",DemoCost+N(Deals!V13)*BuildCostPSF*(1+SoftCostPct)+P13*(DeedMonths+K13*EjectMonths+BuildMonths+SellMonths)+Q13+AL13*(BrokerPct+SellerRTT+SellClosingPct+ConcessionsPct)) | AN13: =IF(AL13="","",IF(N(Deals!S13)=0,MAX(0,(AL13-AM13-MAX(FlipTarget,DevMarginPct*AL13))/(1+BuyerPremium)),IF((AL13-AM13-MAX(FlipTarget,DevMarginPct*AL13))>=(N(Deals!S13)+SheriffCostsFromBid)/(1-RTTPurchase)*(1+BuyerPremium),(AL13-AM13-MAX(FlipTarget,DevMarginPct*AL13))/(1+BuyerPremium),MAX(0,((AL13-AM13-MAX(FlipTarget,DevMarginPct*AL13))-N(Deals!S13)-SheriffCostsFromBid)/(BuyerPremium+RTTPurchase)))))
A14: =IF(Deals!A14="","",Deals!A14) | B14: =IF(A14="","",Deals!B14) | C14: =IF(A14="","",IF(MAX(V14,AF14)<=0,"Pass",IF(V14>=AF14,"Flip","Value-add hold"))) | D14: =IF(A14="","",MAX(V14,AF14)) | E14: =IF(A14="","",IF(D14<=0,"Pass",IF(N(Deals!D14)<=1,"$1 = awaiting minimum bid; re-check the morning of Nov 3",IF(D14<Deals!D14,"Max bid below opening bid: pass","Room of "&TEXT(D14-Deals!D14,"$#,##0")&" over opening bid")))) | F14: =IF(A14="","",IF(C14="Flip",W14,IF(C14="Value-add hold",AG14,0))) | G14: =IF(A14="","",IF(C14="Flip",TEXT(X14,"$#,##0")&" profit, "&TEXT(Y14,"0%")&"/yr over "&TEXT(M14,"0")&" mo",IF(C14="Value-add hold",TEXT(AH14,"0.0%")&" yield on cost; "&IF(ISNUMBER(AJ14),TEXT(AJ14,"0.0%")&" cash-on-cash after refi","all cash out at refi"),""))) | H14: =IF(A14="","",IF(C14="Flip",IF(W14<=FlipCeiling,"In $300k flip box","Over flip ceiling: needs to be exceptional"),IF(C14="Value-add hold","Value-add",""))) | I14: =IF(A14="","",TRIM(IF(AK14>D14,"Wholesale assignment supports "&TEXT(AK14,"$#,##0")&". ","")&IF(AND(ISNUMBER(AN14),N(AN14)>D14),"Teardown/new units supports "&TEXT(AN14,"$#,##0")&".",""))) | J14: =IF(A14="","",TRIM(IF(Deals!F14="2nd","Plaintiff is 2nd: add senior mortgage to surviving liens. ",IF(Deals!F14<>"1st","Lien position unconfirmed. ",""))&IF(N(Deals!M14)=0,"No ARV yet. ","")&IF(N(Deals!G14)=0,"No building sf: rehab is allowance only. ","")&IF(AND(N(Deals!S14)>0,D14>0,D14*(1-RTTPurchase)-SheriffCostsFromBid<N(Deals!S14)),"City claims not fully paid at max bid; unpaid part is counted as cost. ","")&IF(K14=1,"Occupancy assumed: +"&TEXT(EjectMonths,"0")&" mo and possession cost. ",""))) | K14: =IF(A14="","",IF(OR(Deals!Q14="Occupied",AND(Deals!Q14<>"Vacant",UnknownAsOccupied="Y")),1,0)) | L14: =IF(A14="","",IFERROR(INDEX(ScopeMonths,MATCH(Deals!O14,ScopeNames,0)),INDEX(ScopeMonths,3))) | M14: =IF(A14="","",DeedMonths+K14*EjectMonths+L14+SellMonths) | N14: =IF(A14="","",DeedMonths+K14*EjectMonths+L14+LeaseUpMonths) | O14: =IF(A14="","",N(Deals!G14)*IFERROR(INDEX(ScopePSF,MATCH(Deals!O14,ScopeNames,0)),INDEX(ScopePSF,3))*(1+Contingency)+BlindAllowance+N(Deals!P14)) | P14: =IF(A14="","",IF(N(Deals!K14)>0,Deals!K14,N(Deals!M14))*TaxRate/12+VacantInsMo+SecuringMo+UtilitiesMo+N(Deals!T14)) | Q14: =IF(A14="","",SheriffFees+PurchaseTitle+CompelDeedLegal+K14*PossessionCost+N(Deals!R14)+N(Deals!T14)*HOAArrearsMonths) | R14: =IF(A14="","",N(Deals!M14)*(BrokerPct+SellerRTT+SellClosingPct+ConcessionsPct)) | S14: =IF(A14="","",Q14+O14+P14*M14) | T14: =IF(A14="","",N(Deals!M14)-R14-S14) | U14: =IF(A14="","",MIN(T14-FlipTarget,(T14-FlipMinAnnROI*M14/12*S14)/(1+FlipMinAnnROI*M14/12))) | V14: =IF(A14="","",IF(N(Deals!S14)=0,MAX(0,(U14)/(1+BuyerPremium)),IF((U14)>=(N(Deals!S14)+SheriffCostsFromBid)/(1-RTTPurchase)*(1+BuyerPremium),(U14)/(1+BuyerPremium),MAX(0,((U14)-N(Deals!S14)-SheriffCostsFromBid)/(BuyerPremium+RTTPurchase))))) | W14: =IF(A14="","",((V14)*(1+BuyerPremium)+IF(N(Deals!S14)=0,0,MIN(N(Deals!S14),MAX(0,N(Deals!S14)+SheriffCostsFromBid-(V14)*(1-RTTPurchase)))))+S14) | X14: =IF(A14="","",T14-((V14)*(1+BuyerPremium)+IF(N(Deals!S14)=0,0,MIN(N(Deals!S14),MAX(0,N(Deals!S14)+SheriffCostsFromBid-(V14)*(1-RTTPurchase)))))) | Y14: =IF(A14="","",IFERROR(X14/W14/(M14/12),0)) | Z14: =IF(A14="","",N(Deals!N14)*12*(1-Vacancy)*(1-MgmtPct-MaintPct-CapexPct)-N(Deals!M14)*TaxRate-MAX(1,N(Deals!J14))*(InsPerUnit+WaterPerUnit)-N(Deals!T14)*12) | AA14: =IF(A14="","",Q14+O14+P14*N14) | AB14: =IF(A14="","",MAX(0,MIN(RefiLTV*N(Deals!M14),Z14/(RefiDSCR*12*PMT(RefiRate/12,RefiTerm*12,-1))))) | AC14: =IF(A14="","",Z14-AB14*12*PMT(RefiRate/12,RefiTerm*12,-1)) | AD14: =IF(A14="","",IF(N(Deals!S14)=0,MAX(0,(Z14/HoldTarget-AA14)/(1+BuyerPremium)),IF((Z14/HoldTarget-AA14)>=(N(Deals!S14)+SheriffCostsFromBid)/(1-RTTPurchase)*(1+BuyerPremium),(Z14/HoldTarget-AA14)/(1+BuyerPremium),MAX(0,((Z14/HoldTarget-AA14)-N(Deals!S14)-SheriffCostsFromBid)/(BuyerPremium+RTTPurchase))))) | AE14: =IF(A14="","",IF(AC14<=0,0,IF(N(Deals!S14)=0,MAX(0,(AC14/HoldTarget+AB14*(1-RefiCostPct)-AA14)/(1+BuyerPremium)),IF((AC14/HoldTarget+AB14*(1-RefiCostPct)-AA14)>=(N(Deals!S14)+SheriffCostsFromBid)/(1-RTTPurchase)*(1+BuyerPremium),(AC14/HoldTarget+AB14*(1-RefiCostPct)-AA14)/(1+BuyerPremium),MAX(0,((AC14/HoldTarget+AB14*(1-RefiCostPct)-AA14)-N(Deals!S14)-SheriffCostsFromBid)/(BuyerPremium+RTTPurchase)))))) | AF14: =IF(A14="","",IF(HoldMeasure="Cash-on-cash",AE14,AD14)) | AG14: =IF(A14="","",((AF14)*(1+BuyerPremium)+IF(N(Deals!S14)=0,0,MIN(N(Deals!S14),MAX(0,N(Deals!S14)+SheriffCostsFromBid-(AF14)*(1-RTTPurchase)))))+AA14) | AH14: =IF(A14="","",IFERROR(Z14/AG14,0)) | AI14: =IF(A14="","",AG14-AB14*(1-RefiCostPct)) | AJ14: =IF(A14="","",IF(AI14<=0,"All cash out",AC14/AI14)) | AK14: =IF(A14="","",IF(N(Deals!S14)=0,MAX(0,(T14-BuyerMarginPct*N(Deals!M14)-WholesaleMinFee)/(1+BuyerPremium)),IF((T14-BuyerMarginPct*N(Deals!M14)-WholesaleMinFee)>=(N(Deals!S14)+SheriffCostsFromBid)/(1-RTTPurchase)*(1+BuyerPremium),(T14-BuyerMarginPct*N(Deals!M14)-WholesaleMinFee)/(1+BuyerPremium),MAX(0,((T14-BuyerMarginPct*N(Deals!M14)-WholesaleMinFee)-N(Deals!S14)-SheriffCostsFromBid)/(BuyerPremium+RTTPurchase))))) | AL14: =IF(OR(A14="",N(Deals!U14)=0),"",Deals!U14*N(Deals!W14)) | AM14: =IF(AL14="","",DemoCost+N(Deals!V14)*BuildCostPSF*(1+SoftCostPct)+P14*(DeedMonths+K14*EjectMonths+BuildMonths+SellMonths)+Q14+AL14*(BrokerPct+SellerRTT+SellClosingPct+ConcessionsPct)) | AN14: =IF(AL14="","",IF(N(Deals!S14)=0,MAX(0,(AL14-AM14-MAX(FlipTarget,DevMarginPct*AL14))/(1+BuyerPremium)),IF((AL14-AM14-MAX(FlipTarget,DevMarginPct*AL14))>=(N(Deals!S14)+SheriffCostsFromBid)/(1-RTTPurchase)*(1+BuyerPremium),(AL14-AM14-MAX(FlipTarget,DevMarginPct*AL14))/(1+BuyerPremium),MAX(0,((AL14-AM14-MAX(FlipTarget,DevMarginPct*AL14))-N(Deals!S14)-SheriffCostsFromBid)/(BuyerPremium+RTTPurchase)))))
... A42: =IF(Deals!A42="","",Deals!A42) | B42: =IF(A42="","",Deals!B42) | C42: =IF(A42="","",IF(MAX(V42,AF42)<=0,"Pass",IF(V42>=AF42,"Flip","Value-add hold"))) | D42: =IF(A42="","",MAX(V42,AF42)) | E42: =IF(A42="","",IF(D42<=0,"Pass",IF(N(Deals!D42)<=1,"$1 = awaiting minimum bid; re-check the morning of Nov 3",IF(D42<Deals!D42,"Max bid below opening bid: pass","Room of "&TEXT(D42-Deals!D42,"$#,##0")&" over opening bid")))) | F42: =IF(A42="","",IF(C42="Flip",W42,IF(C42="Value-add hold",AG42,0))) | G42: =IF(A42="","",IF(C42="Flip",TEXT(X42,"$#,##0")&" profit, "&TEXT(Y42,"0%")&"/yr over "&TEXT(M42,"0")&" mo",IF(C42="Value-add hold",TEXT(AH42,"0.0%")&" yield on cost; "&IF(ISNUMBER(AJ42),TEXT(AJ42,"0.0%")&" cash-on-cash after refi","all cash out at refi"),""))) | H42: =IF(A42="","",IF(C42="Flip",IF(W42<=FlipCeiling,"In $300k flip box","Over flip ceiling: needs to be exceptional"),IF(C42="Value-add hold","Value-add",""))) | I42: =IF(A42="","",TRIM(IF(AK42>D42,"Wholesale assignment supports "&TEXT(AK42,"$#,##0")&". ","")&IF(AND(ISNUMBER(AN42),N(AN42)>D42),"Teardown/new units supports "&TEXT(AN42,"$#,##0")&".",""))) | J42: =IF(A42="","",TRIM(IF(Deals!F42="2nd","Plaintiff is 2nd: add senior mortgage to surviving liens. ",IF(Deals!F42<>"1st","Lien position unconfirmed. ",""))&IF(N(Deals!M42)=0,"No ARV yet. ","")&IF(N(Deals!G42)=0,"No building sf: rehab is allowance only. ","")&IF(AND(N(Deals!S42)>0,D42>0,D42*(1-RTTPurchase)-SheriffCostsFromBid<N(Deals!S42)),"City claims not fully paid at max bid; unpaid part is counted as cost. ","")&IF(K42=1,"Occupancy assumed: +"&TEXT(EjectMonths,"0")&" mo and possession cost. ",""))) | K42: =IF(A42="","",IF(OR(Deals!Q42="Occupied",AND(Deals!Q42<>"Vacant",UnknownAsOccupied="Y")),1,0)) | L42: =IF(A42="","",IFERROR(INDEX(ScopeMonths,MATCH(Deals!O42,ScopeNames,0)),INDEX(ScopeMonths,3))) | M42: =IF(A42="","",DeedMonths+K42*EjectMonths+L42+SellMonths) | N42: =IF(A42="","",DeedMonths+K42*EjectMonths+L42+LeaseUpMonths) | O42: =IF(A42="","",N(Deals!G42)*IFERROR(INDEX(ScopePSF,MATCH(Deals!O42,ScopeNames,0)),INDEX(ScopePSF,3))*(1+Contingency)+BlindAllowance+N(Deals!P42)) | P42: =IF(A42="","",IF(N(Deals!K42)>0,Deals!K42,N(Deals!M42))*TaxRate/12+VacantInsMo+SecuringMo+UtilitiesMo+N(Deals!T42)) | Q42: =IF(A42="","",SheriffFees+PurchaseTitle+CompelDeedLegal+K42*PossessionCost+N(Deals!R42)+N(Deals!T42)*HOAArrearsMonths) | R42: =IF(A42="","",N(Deals!M42)*(BrokerPct+SellerRTT+SellClosingPct+ConcessionsPct)) | S42: =IF(A42="","",Q42+O42+P42*M42) | T42: =IF(A42="","",N(Deals!M42)-R42-S42) | U42: =IF(A42="","",MIN(T42-FlipTarget,(T42-FlipMinAnnROI*M42/12*S42)/(1+FlipMinAnnROI*M42/12))) | V42: =IF(A42="","",IF(N(Deals!S42)=0,MAX(0,(U42)/(1+BuyerPremium)),IF((U42)>=(N(Deals!S42)+SheriffCostsFromBid)/(1-RTTPurchase)*(1+BuyerPremium),(U42)/(1+BuyerPremium),MAX(0,((U42)-N(Deals!S42)-SheriffCostsFromBid)/(BuyerPremium+RTTPurchase))))) | W42: =IF(A42="","",((V42)*(1+BuyerPremium)+IF(N(Deals!S42)=0,0,MIN(N(Deals!S42),MAX(0,N(Deals!S42)+SheriffCostsFromBid-(V42)*(1-RTTPurchase)))))+S42) | X42: =IF(A42="","",T42-((V42)*(1+BuyerPremium)+IF(N(Deals!S42)=0,0,MIN(N(Deals!S42),MAX(0,N(Deals!S42)+SheriffCostsFromBid-(V42)*(1-RTTPurchase)))))) | Y42: =IF(A42="","",IFERROR(X42/W42/(M42/12),0)) | Z42: =IF(A42="","",N(Deals!N42)*12*(1-Vacancy)*(1-MgmtPct-MaintPct-CapexPct)-N(Deals!M42)*TaxRate-MAX(1,N(Deals!J42))*(InsPerUnit+WaterPerUnit)-N(Deals!T42)*12) | AA42: =IF(A42="","",Q42+O42+P42*N42) | AB42: =IF(A42="","",MAX(0,MIN(RefiLTV*N(Deals!M42),Z42/(RefiDSCR*12*PMT(RefiRate/12,RefiTerm*12,-1))))) | AC42: =IF(A42="","",Z42-AB42*12*PMT(RefiRate/12,RefiTerm*12,-1)) | AD42: =IF(A42="","",IF(N(Deals!S42)=0,MAX(0,(Z42/HoldTarget-AA42)/(1+BuyerPremium)),IF((Z42/HoldTarget-AA42)>=(N(Deals!S42)+SheriffCostsFromBid)/(1-RTTPurchase)*(1+BuyerPremium),(Z42/HoldTarget-AA42)/(1+BuyerPremium),MAX(0,((Z42/HoldTarget-AA42)-N(Deals!S42)-SheriffCostsFromBid)/(BuyerPremium+RTTPurchase))))) | AE42: =IF(A42="","",IF(AC42<=0,0,IF(N(Deals!S42)=0,MAX(0,(AC42/HoldTarget+AB42*(1-RefiCostPct)-AA42)/(1+BuyerPremium)),IF((AC42/HoldTarget+AB42*(1-RefiCostPct)-AA42)>=(N(Deals!S42)+SheriffCostsFromBid)/(1-RTTPurchase)*(1+BuyerPremium),(AC42/HoldTarget+AB42*(1-RefiCostPct)-AA42)/(1+BuyerPremium),MAX(0,((AC42/HoldTarget+AB42*(1-RefiCostPct)-AA42)-N(Deals!S42)-SheriffCostsFromBid)/(BuyerPremium+RTTPurchase)))))) | AF42: =IF(A42="","",IF(HoldMeasure="Cash-on-cash",AE42,AD42)) | AG42: =IF(A42="","",((AF42)*(1+BuyerPremium)+IF(N(Deals!S42)=0,0,MIN(N(Deals!S42),MAX(0,N(Deals!S42)+SheriffCostsFromBid-(AF42)*(1-RTTPurchase)))))+AA42) | AH42: =IF(A42="","",IFERROR(Z42/AG42,0)) | AI42: =IF(A42="","",AG42-AB42*(1-RefiCostPct)) | AJ42: =IF(A42="","",IF(AI42<=0,"All cash out",AC42/AI42)) | AK42: =IF(A42="","",IF(N(Deals!S42)=0,MAX(0,(T42-BuyerMarginPct*N(Deals!M42)-WholesaleMinFee)/(1+BuyerPremium)),IF((T42-BuyerMarginPct*N(Deals!M42)-WholesaleMinFee)>=(N(Deals!S42)+SheriffCostsFromBid)/(1-RTTPurchase)*(1+BuyerPremium),(T42-BuyerMarginPct*N(Deals!M42)-WholesaleMinFee)/(1+BuyerPremium),MAX(0,((T42-BuyerMarginPct*N(Deals!M42)-WholesaleMinFee)-N(Deals!S42)-SheriffCostsFromBid)/(BuyerPremium+RTTPurchase))))) | AL42: =IF(OR(A42="",N(Deals!U42)=0),"",Deals!U42*N(Deals!W42)) | AM42: =IF(AL42="","",DemoCost+N(Deals!V42)*BuildCostPSF*(1+SoftCostPct)+P42*(DeedMonths+K42*EjectMonths+BuildMonths+SellMonths)+Q42+AL42*(BrokerPct+SellerRTT+SellClosingPct+ConcessionsPct)) | AN42: =IF(AL42="","",IF(N(Deals!S42)=0,MAX(0,(AL42-AM42-MAX(FlipTarget,DevMarginPct*AL42))/(1+BuyerPremium)),IF((AL42-AM42-MAX(FlipTarget,DevMarginPct*AL42))>=(N(Deals!S42)+SheriffCostsFromBid)/(1-RTTPurchase)*(1+BuyerPremium),(AL42-AM42-MAX(FlipTarget,DevMarginPct*AL42))/(1+BuyerPremium),MAX(0,((AL42-AM42-MAX(FlipTarget,DevMarginPct*AL42))-N(Deals!S42)-SheriffCostsFromBid)/(BuyerPremium+RTTPurchase)))))

Sheet Bid Ladder
A1: Profit and return at several bids. Change the % of ARV in row 2 (yellow) to move the ladder.
F2: At opening bid | J2: 0.2 | N2: 0.3 | R2: 0.4 | V2: 0.5 | Z2: 0.6 | AD2: 0.7 | AH2: At max bid
A3: Auction ID | B3: Address | C3: ARV | D3: Opening bid | E3: Max bid | F3: Bid | G3: Flip profit | H3: Flip ann. return | I3: Hold yield on cost | J3: Bid | K3: Flip profit | L3: Flip ann. return | M3: Hold yield on cost | N3: Bid | O3: Flip profit | P3: Flip ann. return | Q3: Hold yield on cost | R3: Bid | S3: Flip profit | T3: Flip ann. return | U3: Hold yield on cost | V3: Bid | W3: Flip profit | X3: Flip ann. return | Y3: Hold yield on cost | Z3: Bid | AA3: Flip profit | AB3: Flip ann. return | AC3: Hold yield on cost | AD3: Bid | AE3: Flip profit | AF3: Flip ann. return | AG3: Hold yield on cost | AH3: Bid | AI3: Flip profit | AJ3: Flip ann. return | AK3: Hold yield on cost
A4: =Underwriting!$A3 -> 1318974-0 | B4: =Underwriting!$B3 -> 0 Bench screen (ARV 354k, Heavy, occupied) | C4: =IF(Underwriting!$A3="","",N(Deals!M3)) -> 354000 | D4: =IF(Underwriting!$A3="","",N(Deals!D3)) -> 24700 | E4: =IF(Underwriting!$A3="","",Underwriting!$D3) -> 116429.49 | F4: =IF(Underwriting!$A3="","",$D4) -> 24700 | G4: =IF(Underwriting!$A3="","",Underwriting!$T3-((F4)*(1+BuyerPremium)+IF(N(Deals!S3)=0,0,MIN(N(Deals!S3),MAX(0,N(Deals!S3)+SheriffCostsFromBid-(F4)*(1-RTTPurchase)))))) -> 176357.97 | H4: =IF(Underwriting!$A3="","",IFERROR(G4/(((F4)*(1+BuyerPremium)+IF(N(Deals!S3)=0,0,MIN(N(Deals!S3),MAX(0,N(Deals!S3)+SheriffCostsFromBid-(F4)*(1-RTTPurchase)))))+Underwriting!$S3)/(Underwriting!$M3/12),0)) -> 0.52212301 | I4: =IF(Underwriting!$A3="","",IFERROR(Underwriting!$Z3/(((F4)*(1+BuyerPremium)+IF(N(Deals!S3)=0,0,MIN(N(Deals!S3),MAX(0,N(Deals!S3)+SheriffCostsFromBid-(F4)*(1-RTTPurchase)))))+Underwriting!$AA3),0)) -> 0.11359289 | J4: =IF(Underwriting!$A3="","",ROUND(J$2*$C4,-3)) -> 71000 | K4: =IF(Underwriting!$A3="","",Underwriting!$T3-((J4)*(1+BuyerPremium)+IF(N(Deals!S3)=0,0,MIN(N(Deals!S3),MAX(0,N(Deals!S3)+SheriffCostsFromBid-(J4)*(1-RTTPurchase)))))) -> 129363.47 | L4: =IF(Underwriting!$A3="","",IFERROR(K4/(((J4)*(1+BuyerPremium)+IF(N(Deals!S3)=0,0,MIN(N(Deals!S3),MAX(0,N(Deals!S3)+SheriffCostsFromBid-(J4)*(1-RTTPurchase)))))+Underwriting!$S3)/(Underwriting!$M3/12),0)) -> 0.289129 | M4: =IF(Underwriting!$A3="","",IFERROR(Underwriting!$Z3/(((J4)*(1+BuyerPremium)+IF(N(Deals!S3)=0,0,MIN(N(Deals!S3),MAX(0,N(Deals!S3)+SheriffCostsFromBid-(J4)*(1-RTTPurchase)))))+Underwriting!$AA3),0)) -> 0.085643346 | N4: =IF(Underwriting!$A3="","",ROUND(N$2*$C4,-3)) -> 106000 | O4: =IF(Underwriting!$A3="","",Underwriting!$T3-((N4)*(1+BuyerPremium)+IF(N(Deals!S3)=0,0,MIN(N(Deals!S3),MAX(0,N(Deals!S3)+SheriffCostsFromBid-(N4)*(1-RTTPurchase)))))) -> 93838.471 | P4: =IF(Underwriting!$A3="","",IFERROR(O4/(((N4)*(1+BuyerPremium)+IF(N(Deals!S3)=0,0,MIN(N(Deals!S3),MAX(0,N(Deals!S3)+SheriffCostsFromBid-(N4)*(1-RTTPurchase)))))+Underwriting!$S3)/(Underwriting!$M3/12),0)) -> 0.17694808 | Q4: =IF(Underwriting!$A3="","",IFERROR(Underwriting!$Z3/(((N4)*(1+BuyerPremium)+IF(N(Deals!S3)=0,0,MIN(N(Deals!S3),MAX(0,N(Deals!S3)+SheriffCostsFromBid-(N4)*(1-RTTPurchase)))))+Underwriting!$AA3),0)) -> 0.07221199 | R4: =IF(Underwriting!$A3="","",ROUND(R$2*$C4,-3)) -> 142000 | S4: =IF(Underwriting!$A3="","",Underwriting!$T3-((R4)*(1+BuyerPremium)+IF(N(Deals!S3)=0,0,MIN(N(Deals!S3),MAX(0,N(Deals!S3)+SheriffCostsFromBid-(R4)*(1-RTTPurchase)))))) -> 57298.471 | T4: =IF(Underwriting!$A3="","",IFERROR(S4/(((R4)*(1+BuyerPremium)+IF(N(Deals!S3)=0,0,MIN(N(Deals!S3),MAX(0,N(Deals!S3)+SheriffCostsFromBid-(R4)*(1-RTTPurchase)))))+Underwriting!$S3)/(Underwriting!$M3/12),0)) -> 0.093081003 | U4: =IF(Underwriting!$A3="","",IFERROR(Underwriting!$Z3/(((R4)*(1+BuyerPremium)+IF(N(Deals!S3)=0,0,MIN(N(Deals!S3),MAX(0,N(Deals!S3)+SheriffCostsFromBid-(R4)*(1-RTTPurchase)))))+Underwriting!$AA3),0)) -> 0.062181505 | V4: =IF(Underwriting!$A3="","",ROUND(V$2*$C4,-3)) -> 177000 | W4: =IF(Underwriting!$A3="","",Underwriting!$T3-((V4)*(1+BuyerPremium)+IF(N(Deals!S3)=0,0,MIN(N(Deals!S3),MAX(0,N(Deals!S3)+SheriffCostsFromBid-(V4)*(1-RTTPurchase)))))) -> 21773.471 | X4: =IF(Underwriting!$A3="","",IFERROR(W4/(((V4)*(1+BuyerPremium)+IF(N(Deals!S3)=0,0,MIN(N(Deals!S3),MAX(0,N(Deals!S3)+SheriffCostsFromBid-(V4)*(1-RTTPurchase)))))+Underwriting!$S3)/(Underwriting!$M3/12),0)) -> 0.03117318 | Y4: =IF(Underwriting!$A3="","",IFERROR(Underwriting!$Z3/(((V4)*(1+BuyerPremium)+IF(N(Deals!S3)=0,0,MIN(N(Deals!S3),MAX(0,N(Deals!S3)+SheriffCostsFromBid-(V4)*(1-RTTPurchase)))))+Underwriting!$AA3),0)) -> 0.0547833 | Z4: =IF(Underwriting!$A3="","",ROUND(Z$2*$C4,-3)) -> 212000 | AA4: =IF(Underwriting!$A3="","",Underwriting!$T3-((Z4)*(1+BuyerPremium)+IF(N(Deals!S3)=0,0,MIN(N(Deals!S3),MAX(0,N(Deals!S3)+SheriffCostsFromBid-(Z4)*(1-RTTPurchase)))))) -> -13751.529 | AB4: =IF(Underwriting!$A3="","",IFERROR(AA4/(((Z4)*(1+BuyerPremium)+IF(N(Deals!S3)=0,0,MIN(N(Deals!S3),MAX(0,N(Deals!S3)+SheriffCostsFromBid-(Z4)*(1-RTTPurchase)))))+Underwriting!$S3)/(Underwriting!$M3/12),0)) -> -0.017599484 | AC4: =IF(Underwriting!$A3="","",IFERROR(Underwriting!$Z3/(((Z4)*(1+BuyerPremium)+IF(N(Deals!S3)=0,0,MIN(N(Deals!S3),MAX(0,N(Deals!S3)+SheriffCostsFromBid-(Z4)*(1-RTTPurchase)))))+Underwriting!$AA3),0)) -> 0.048958353 | AD4: =IF(Underwriting!$A3="","",ROUND(AD$2*$C4,-3)) -> 248000 | AE4: =IF(Underwriting!$A3="","",Underwriting!$T3-((AD4)*(1+BuyerPremium)+IF(N(Deals!S3)=0,0,MIN(N(Deals!S3),MAX(0,N(Deals!S3)+SheriffCostsFromBid-(AD4)*(1-RTTPurchase)))))) -> -50291.529 | AF4: =IF(Underwriting!$A3="","",IFERROR(AE4/(((AD4)*(1+BuyerPremium)+IF(N(Deals!S3)=0,0,MIN(N(Deals!S3),MAX(0,N(Deals!S3)+SheriffCostsFromBid-(AD4)*(1-RTTPurchase)))))+Underwriting!$S3)/(Underwriting!$M3/12),0)) -> -0.058031828 | AG4: =IF(Underwriting!$A3="","",IFERROR(Underwriting!$Z3/(((AD4)*(1+BuyerPremium)+IF(N(Deals!S3)=0,0,MIN(N(Deals!S3),MAX(0,N(Deals!S3)+SheriffCostsFromBid-(AD4)*(1-RTTPurchase)))))+Underwriting!$AA3),0)) -> 0.044131873 | AH4: =IF(Underwriting!$A3="","",$E4) -> 116429.49 | AI4: =IF(Underwriting!$A3="","",Underwriting!$T3-((AH4)*(1+BuyerPremium)+IF(N(Deals!S3)=0,0,MIN(N(Deals!S3),MAX(0,N(Deals!S3)+SheriffCostsFromBid-(AH4)*(1-RTTPurchase)))))) -> 83252.54 | AJ4: =IF(Underwriting!$A3="","",IFERROR(AI4/(((AH4)*(1+BuyerPremium)+IF(N(Deals!S3)=0,0,MIN(N(Deals!S3),MAX(0,N(Deals!S3)+SheriffCostsFromBid-(AH4)*(1-RTTPurchase)))))+Underwriting!$S3)/(Underwriting!$M3/12),0)) -> 0.15 | AK4: =IF(Underwriting!$A3="","",IFERROR(Underwriting!$Z3/(((AH4)*(1+BuyerPremium)+IF(N(Deals!S3)=0,0,MIN(N(Deals!S3),MAX(0,N(Deals!S3)+SheriffCostsFromBid-(AH4)*(1-RTTPurchase)))))+Underwriting!$AA3),0)) -> 0.068987992
A5: =Underwriting!$A4 -> 1318974-1 | B5: =Underwriting!$B4 -> 1 Base: ARV 395k, Medium (+$8k roof/front), occupied | C5: =IF(Underwriting!$A4="","",N(Deals!M4)) -> 395000 | D5: =IF(Underwriting!$A4="","",N(Deals!D4)) -> 24700 | E5: =IF(Underwriting!$A4="","",Underwriting!$D4) -> 166944.44 | F5: =IF(Underwriting!$A4="","",$D5) -> 24700 | G5: =IF(Underwriting!$A4="","",Underwriting!$T4-((F5)*(1+BuyerPremium)+IF(N(Deals!S4)=0,0,MIN(N(Deals!S4),MAX(0,N(Deals!S4)+SheriffCostsFromBid-(F5)*(1-RTTPurchase)))))) -> 232265.09 | H5: =IF(Underwriting!$A4="","",IFERROR(G5/(((F5)*(1+BuyerPremium)+IF(N(Deals!S4)=0,0,MIN(N(Deals!S4),MAX(0,N(Deals!S4)+SheriffCostsFromBid-(F5)*(1-RTTPurchase)))))+Underwriting!$S4)/(Underwriting!$M4/12),0)) -> 0.85049516 | I5: =IF(Underwriting!$A4="","",IFERROR(Underwriting!$Z4/(((F5)*(1+BuyerPremium)+IF(N(Deals!S4)=0,0,MIN(N(Deals!S4),MAX(0,N(Deals!S4)+SheriffCostsFromBid-(F5)*(1-RTTPurchase)))))+Underwriting!$AA4),0)) -> 0.12598092 | J5: =IF(Underwriting!$A4="","",ROUND(J$2*$C5,-3)) -> 79000 | K5: =IF(Underwriting!$A4="","",Underwriting!$T4-((J5)*(1+BuyerPremium)+IF(N(Deals!S4)=0,0,MIN(N(Deals!S4),MAX(0,N(Deals!S4)+SheriffCostsFromBid-(J5)*(1-RTTPurchase)))))) -> 177150.59 | L5: =IF(Underwriting!$A4="","",IFERROR(K5/(((J5)*(1+BuyerPremium)+IF(N(Deals!S4)=0,0,MIN(N(Deals!S4),MAX(0,N(Deals!S4)+SheriffCostsFromBid-(J5)*(1-RTTPurchase)))))+Underwriting!$S4)/(Underwriting!$M4/12),0)) -> 0.45132906 | M5: =IF(Underwriting!$A4="","",IFERROR(Underwriting!$Z4/(((J5)*(1+BuyerPremium)+IF(N(Deals!S4)=0,0,MIN(N(Deals!S4),MAX(0,N(Deals!S4)+SheriffCostsFromBid-(J5)*(1-RTTPurchase)))))+Underwriting!$AA4),0)) -> 0.087492154 | N5: =IF(Underwriting!$A4="","",ROUND(N$2*$C5,-3)) -> 119000 | O5: =IF(Underwriting!$A4="","",Underwriting!$T4-((N5)*(1+BuyerPremium)+IF(N(Deals!S4)=0,0,MIN(N(Deals!S4),MAX(0,N(Deals!S4)+SheriffCostsFromBid-(N5)*(1-RTTPurchase)))))) -> 136550.59 | P5: =IF(Underwriting!$A4="","",IFERROR(O5/(((N5)*(1+BuyerPremium)+IF(N(Deals!S4)=0,0,MIN(N(Deals!S4),MAX(0,N(Deals!S4)+SheriffCostsFromBid-(N5)*(1-RTTPurchase)))))+Underwriting!$S4)/(Underwriting!$M4/12),0)) -> 0.28419893 | Q5: =IF(Underwriting!$A4="","",IFERROR(Underwriting!$Z4/(((N5)*(1+BuyerPremium)+IF(N(Deals!S4)=0,0,MIN(N(Deals!S4),MAX(0,N(Deals!S4)+SheriffCostsFromBid-(N5)*(1-RTTPurchase)))))+Underwriting!$AA4),0)) -> 0.071418939 | R5: =IF(Underwriting!$A4="","",ROUND(R$2*$C5,-3)) -> 158000 | S5: =IF(Underwriting!$A4="","",Underwriting!$T4-((R5)*(1+BuyerPremium)+IF(N(Deals!S4)=0,0,MIN(N(Deals!S4),MAX(0,N(Deals!S4)+SheriffCostsFromBid-(R5)*(1-RTTPurchase)))))) -> 96965.586 | T5: =IF(Underwriting!$A4="","",IFERROR(S5/(((R5)*(1+BuyerPremium)+IF(N(Deals!S4)=0,0,MIN(N(Deals!S4),MAX(0,N(Deals!S4)+SheriffCostsFromBid-(R5)*(1-RTTPurchase)))))+Underwriting!$S4)/(Underwriting!$M4/12),0)) -> 0.17124381 | U5: =IF(Underwriting!$A4="","",IFERROR(Underwriting!$Z4/(((R5)*(1+BuyerPremium)+IF(N(Deals!S4)=0,0,MIN(N(Deals!S4),MAX(0,N(Deals!S4)+SheriffCostsFromBid-(R5)*(1-RTTPurchase)))))+Underwriting!$AA4),0)) -> 0.060569819 | V5: =IF(Underwriting!$A4="","",ROUND(V$2*$C5,-3)) -> 198000 | W5: =IF(Underwriting!$A4="","",Underwriting!$T4-((V5)*(1+BuyerPremium)+IF(N(Deals!S4)=0,0,MIN(N(Deals!S4),MAX(0,N(Deals!S4)+SheriffCostsFromBid-(V5)*(1-RTTPurchase)))))) -> 56365.586 | X5: =IF(Underwriting!$A4="","",IFERROR(W5/(((V5)*(1+BuyerPremium)+IF(N(Deals!S4)=0,0,MIN(N(Deals!S4),MAX(0,N(Deals!S4)+SheriffCostsFromBid-(V5)*(1-RTTPurchase)))))+Underwriting!$S4)/(Underwriting!$M4/12),0)) -> 0.086158307 | Y5: =IF(Underwriting!$A4="","",IFERROR(Underwriting!$Z4/(((V5)*(1+BuyerPremium)+IF(N(Deals!S4)=0,0,MIN(N(Deals!S4),MAX(0,N(Deals!S4)+SheriffCostsFromBid-(V5)*(1-RTTPurchase)))))+Underwriting!$AA4),0)) -> 0.052404956 | Z5: =IF(Underwriting!$A4="","",ROUND(Z$2*$C5,-3)) -> 237000 | AA5: =IF(Underwriting!$A4="","",Underwriting!$T4-((Z5)*(1+BuyerPremium)+IF(N(Deals!S4)=0,0,MIN(N(Deals!S4),MAX(0,N(Deals!S4)+SheriffCostsFromBid-(Z5)*(1-RTTPurchase)))))) -> 16780.586 | AB5: =IF(Underwriting!$A4="","",IFERROR(AA5/(((Z5)*(1+BuyerPremium)+IF(N(Deals!S4)=0,0,MIN(N(Deals!S4),MAX(0,N(Deals!S4)+SheriffCostsFromBid-(Z5)*(1-RTTPurchase)))))+Underwriting!$S4)/(Underwriting!$M4/12),0)) -> 0.022677172 | AC5: =IF(Underwriting!$A4="","",IFERROR(Underwriting!$Z4/(((Z5)*(1+BuyerPremium)+IF(N(Deals!S4)=0,0,MIN(N(Deals!S4),MAX(0,N(Deals!S4)+SheriffCostsFromBid-(Z5)*(1-RTTPurchase)))))+Underwriting!$AA4),0)) -> 0.04631742 | AD5: =IF(Underwriting!$A4="","",ROUND(AD$2*$C5,-3)) -> 277000 | AE5: =IF(Underwriting!$A4="","",Underwriting!$T4-((AD5)*(1+BuyerPremium)+IF(N(Deals!S4)=0,0,MIN(N(Deals!S4),MAX(0,N(Deals!S4)+SheriffCostsFromBid-(AD5)*(1-RTTPurchase)))))) -> -23819.414 | AF5: =IF(Underwriting!$A4="","",IFERROR(AE5/(((AD5)*(1+BuyerPremium)+IF(N(Deals!S4)=0,0,MIN(N(Deals!S4),MAX(0,N(Deals!S4)+SheriffCostsFromBid-(AD5)*(1-RTTPurchase)))))+Underwriting!$S4)/(Underwriting!$M4/12),0)) -> -0.028769364 | AG5: =IF(Underwriting!$A4="","",IFERROR(Underwriting!$Z4/(((AD5)*(1+BuyerPremium)+IF(N(Deals!S4)=0,0,MIN(N(Deals!S4),MAX(0,N(Deals!S4)+SheriffCostsFromBid-(AD5)*(1-RTTPurchase)))))+Underwriting!$AA4),0)) -> 0.041386547 | AH5: =IF(Underwriting!$A4="","",$E5) -> 166944.44 | AI5: =IF(Underwriting!$A4="","",Underwriting!$T4-((AH5)*(1+BuyerPremium)+IF(N(Deals!S4)=0,0,MIN(N(Deals!S4),MAX(0,N(Deals!S4)+SheriffCostsFromBid-(AH5)*(1-RTTPurchase)))))) -> 87886.978 | AJ5: =IF(Underwriting!$A4="","",IFERROR(AI5/(((AH5)*(1+BuyerPremium)+IF(N(Deals!S4)=0,0,MIN(N(Deals!S4),MAX(0,N(Deals!S4)+SheriffCostsFromBid-(AH5)*(1-RTTPurchase)))))+Underwriting!$S4)/(Underwriting!$M4/12),0)) -> 0.15 | AK5: =IF(Underwriting!$A4="","",IFERROR(Underwriting!$Z4/(((AH5)*(1+BuyerPremium)+IF(N(Deals!S4)=0,0,MIN(N(Deals!S4),MAX(0,N(Deals!S4)+SheriffCostsFromBid-(AH5)*(1-RTTPurchase)))))+Underwriting!$AA4),0)) -> 0.058530651
A6: =Underwriting!$A5 -> 1318974-2 | B6: =Underwriting!$B5 -> 2 Base but vacant at deed | C6: =IF(Underwriting!$A5="","",N(Deals!M5)) -> 395000 | D6: =IF(Underwriting!$A5="","",N(Deals!D5)) -> 24700 | E6: =IF(Underwriting!$A5="","",Underwriting!$D5) -> 204518.47 | F6: =IF(Underwriting!$A5="","",$D6) -> 24700 | G6: =IF(Underwriting!$A5="","",Underwriting!$T5-((F6)*(1+BuyerPremium)+IF(N(Deals!S5)=0,0,MIN(N(Deals!S5),MAX(0,N(Deals!S5)+SheriffCostsFromBid-(F6)*(1-RTTPurchase)))))) -> 248327.51 | H6: =IF(Underwriting!$A5="","",IFERROR(G6/(((F6)*(1+BuyerPremium)+IF(N(Deals!S5)=0,0,MIN(N(Deals!S5),MAX(0,N(Deals!S5)+SheriffCostsFromBid-(F6)*(1-RTTPurchase)))))+Underwriting!$S5)/(Underwriting!$M5/12),0)) -> 1.505276 | I6: =IF(Underwriting!$A5="","",IFERROR(Underwriting!$Z5/(((F6)*(1+BuyerPremium)+IF(N(Deals!S5)=0,0,MIN(N(Deals!S5),MAX(0,N(Deals!S5)+SheriffCostsFromBid-(F6)*(1-RTTPurchase)))))+Underwriting!$AA5),0)) -> 0.14450775 | J6: =IF(Underwriting!$A5="","",ROUND(J$2*$C6,-3)) -> 79000 | K6: =IF(Underwriting!$A5="","",Underwriting!$T5-((J6)*(1+BuyerPremium)+IF(N(Deals!S5)=0,0,MIN(N(Deals!S5),MAX(0,N(Deals!S5)+SheriffCostsFromBid-(J6)*(1-RTTPurchase)))))) -> 193213.01 | L6: =IF(Underwriting!$A5="","",IFERROR(K6/(((J6)*(1+BuyerPremium)+IF(N(Deals!S5)=0,0,MIN(N(Deals!S5),MAX(0,N(Deals!S5)+SheriffCostsFromBid-(J6)*(1-RTTPurchase)))))+Underwriting!$S5)/(Underwriting!$M5/12),0)) -> 0.7802073 | M6: =IF(Underwriting!$A5="","",IFERROR(Underwriting!$Z5/(((J6)*(1+BuyerPremium)+IF(N(Deals!S5)=0,0,MIN(N(Deals!S5),MAX(0,N(Deals!S5)+SheriffCostsFromBid-(J6)*(1-RTTPurchase)))))+Underwriting!$AA5),0)) -> 0.096043669 | N6: =IF(Underwriting!$A5="","",ROUND(N$2*$C6,-3)) -> 119000 | O6: =IF(Underwriting!$A5="","",Underwriting!$T5-((N6)*(1+BuyerPremium)+IF(N(Deals!S5)=0,0,MIN(N(Deals!S5),MAX(0,N(Deals!S5)+SheriffCostsFromBid-(N6)*(1-RTTPurchase)))))) -> 152613.01 | P6: =IF(Underwriting!$A5="","",IFERROR(O6/(((N6)*(1+BuyerPremium)+IF(N(Deals!S5)=0,0,MIN(N(Deals!S5),MAX(0,N(Deals!S5)+SheriffCostsFromBid-(N6)*(1-RTTPurchase)))))+Underwriting!$S5)/(Underwriting!$M5/12),0)) -> 0.49462449 | Q6: =IF(Underwriting!$A5="","",IFERROR(Underwriting!$Z5/(((N6)*(1+BuyerPremium)+IF(N(Deals!S5)=0,0,MIN(N(Deals!S5),MAX(0,N(Deals!S5)+SheriffCostsFromBid-(N6)*(1-RTTPurchase)))))+Underwriting!$AA5),0)) -> 0.077016549 | R6: =IF(Underwriting!$A5="","",ROUND(R$2*$C6,-3)) -> 158000 | S6: =IF(Underwriting!$A5="","",Underwriting!$T5-((R6)*(1+BuyerPremium)+IF(N(Deals!S5)=0,0,MIN(N(Deals!S5),MAX(0,N(Deals!S5)+SheriffCostsFromBid-(R6)*(1-RTTPurchase)))))) -> 113028.01 | T6: =IF(Underwriting!$A5="","",IFERROR(S6/(((R6)*(1+BuyerPremium)+IF(N(Deals!S5)=0,0,MIN(N(Deals!S5),MAX(0,N(Deals!S5)+SheriffCostsFromBid-(R6)*(1-RTTPurchase)))))+Underwriting!$S5)/(Underwriting!$M5/12),0)) -> 0.30720755 | U6: =IF(Underwriting!$A5="","",IFERROR(Underwriting!$Z5/(((R6)*(1+BuyerPremium)+IF(N(Deals!S5)=0,0,MIN(N(Deals!S5),MAX(0,N(Deals!S5)+SheriffCostsFromBid-(R6)*(1-RTTPurchase)))))+Underwriting!$AA5),0)) -> 0.064548583 | V6: =IF(Underwriting!$A5="","",ROUND(V$2*$C6,-3)) -> 198000 | W6: =IF(Underwriting!$A5="","",Underwriting!$T5-((V6)*(1+BuyerPremium)+IF(N(Deals!S5)=0,0,MIN(N(Deals!S5),MAX(0,N(Deals!S5)+SheriffCostsFromBid-(V6)*(1-RTTPurchase)))))) -> 72428.006 | X6: =IF(Underwriting!$A5="","",IFERROR(W6/(((V6)*(1+BuyerPremium)+IF(N(Deals!S5)=0,0,MIN(N(Deals!S5),MAX(0,N(Deals!S5)+SheriffCostsFromBid-(V6)*(1-RTTPurchase)))))+Underwriting!$S5)/(Underwriting!$M5/12),0)) -> 0.16890046 | Y6: =IF(Underwriting!$A5="","",IFERROR(Underwriting!$Z5/(((V6)*(1+BuyerPremium)+IF(N(Deals!S5)=0,0,MIN(N(Deals!S5),MAX(0,N(Deals!S5)+SheriffCostsFromBid-(V6)*(1-RTTPurchase)))))+Underwriting!$AA5),0)) -> 0.055357196 | Z6: =IF(Underwriting!$A5="","",ROUND(Z$2*$C6,-3)) -> 237000 | AA6: =IF(Underwriting!$A5="","",Underwriting!$T5-((Z6)*(1+BuyerPremium)+IF(N(Deals!S5)=0,0,MIN(N(Deals!S5),MAX(0,N(Deals!S5)+SheriffCostsFromBid-(Z6)*(1-RTTPurchase)))))) -> 32843.006 | AB6: =IF(Underwriting!$A5="","",IFERROR(AA6/(((Z6)*(1+BuyerPremium)+IF(N(Deals!S5)=0,0,MIN(N(Deals!S5),MAX(0,N(Deals!S5)+SheriffCostsFromBid-(Z6)*(1-RTTPurchase)))))+Underwriting!$S5)/(Underwriting!$M5/12),0)) -> 0.067273923 | AC6: =IF(Underwriting!$A5="","",IFERROR(Underwriting!$Z5/(((Z6)*(1+BuyerPremium)+IF(N(Deals!S5)=0,0,MIN(N(Deals!S5),MAX(0,N(Deals!S5)+SheriffCostsFromBid-(Z6)*(1-RTTPurchase)))))+Underwriting!$AA5),0)) -> 0.048608619 | AD6: =IF(Underwriting!$A5="","",ROUND(AD$2*$C6,-3)) -> 277000 | AE6: =IF(Underwriting!$A5="","",Underwriting!$T5-((AD6)*(1+BuyerPremium)+IF(N(Deals!S5)=0,0,MIN(N(Deals!S5),MAX(0,N(Deals!S5)+SheriffCostsFromBid-(AD6)*(1-RTTPurchase)))))) -> -7756.9941 | AF6: =IF(Underwriting!$A5="","",IFERROR(AE6/(((AD6)*(1+BuyerPremium)+IF(N(Deals!S5)=0,0,MIN(N(Deals!S5),MAX(0,N(Deals!S5)+SheriffCostsFromBid-(AD6)*(1-RTTPurchase)))))+Underwriting!$S5)/(Underwriting!$M5/12),0)) -> -0.014126789 | AG6: =IF(Underwriting!$A5="","",IFERROR(Underwriting!$Z5/(((AD6)*(1+BuyerPremium)+IF(N(Deals!S5)=0,0,MIN(N(Deals!S5),MAX(0,N(Deals!S5)+SheriffCostsFromBid-(AD6)*(1-RTTPurchase)))))+Underwriting!$AA5),0)) -> 0.043206296 | AH6: =IF(Underwriting!$A5="","",$E6) -> 204518.47 | AI6: =IF(Underwriting!$A5="","",Underwriting!$T5-((AH6)*(1+BuyerPremium)+IF(N(Deals!S5)=0,0,MIN(N(Deals!S5),MAX(0,N(Deals!S5)+SheriffCostsFromBid-(AH6)*(1-RTTPurchase)))))) -> 65811.756 | AJ6: =IF(Underwriting!$A5="","",IFERROR(AI6/(((AH6)*(1+BuyerPremium)+IF(N(Deals!S5)=0,0,MIN(N(Deals!S5),MAX(0,N(Deals!S5)+SheriffCostsFromBid-(AH6)*(1-RTTPurchase)))))+Underwriting!$S5)/(Underwriting!$M5/12),0)) -> 0.15 | AK6: =IF(Underwriting!$A5="","",IFERROR(Underwriting!$Z5/(((AH6)*(1+BuyerPremium)+IF(N(Deals!S5)=0,0,MIN(N(Deals!S5),MAX(0,N(Deals!S5)+SheriffCostsFromBid-(AH6)*(1-RTTPurchase)))))+Underwriting!$AA5),0)) -> 0.054101769
A7: =Underwriting!$A6 -> 1318974-3 | B7: =Underwriting!$B6 -> 3 Light cosmetic: ARV 375k, Light, occupied | C7: =IF(Underwriting!$A6="","",N(Deals!M6)) -> 375000 | D7: =IF(Underwriting!$A6="","",N(Deals!D6)) -> 24700 | E7: =IF(Underwriting!$A6="","",Underwriting!$D6) -> 185181.5 | F7: =IF(Underwriting!$A6="","",$D7) -> 24700 | G7: =IF(Underwriting!$A6="","",Underwriting!$T6-((F7)*(1+BuyerPremium)+IF(N(Deals!S6)=0,0,MIN(N(Deals!S6),MAX(0,N(Deals!S6)+SheriffCostsFromBid-(F7)*(1-RTTPurchase)))))) -> 243880.69 | H7: =IF(Underwriting!$A6="","",IFERROR(G7/(((F7)*(1+BuyerPremium)+IF(N(Deals!S6)=0,0,MIN(N(Deals!S6),MAX(0,N(Deals!S6)+SheriffCostsFromBid-(F7)*(1-RTTPurchase)))))+Underwriting!$S6)/(Underwriting!$M6/12),0)) -> 1.215787 | I7: =IF(Underwriting!$A6="","",IFERROR(Underwriting!$Z6/(((F7)*(1+BuyerPremium)+IF(N(Deals!S6)=0,0,MIN(N(Deals!S6),MAX(0,N(Deals!S6)+SheriffCostsFromBid-(F7)*(1-RTTPurchase)))))+Underwriting!$AA6),0)) -> 0.16815583 | J7: =IF(Underwriting!$A6="","",ROUND(J$2*$C7,-3)) -> 75000 | K7: =IF(Underwriting!$A6="","",Underwriting!$T6-((J7)*(1+BuyerPremium)+IF(N(Deals!S6)=0,0,MIN(N(Deals!S6),MAX(0,N(Deals!S6)+SheriffCostsFromBid-(J7)*(1-RTTPurchase)))))) -> 192826.19 | L7: =IF(Underwriting!$A6="","",IFERROR(K7/(((J7)*(1+BuyerPremium)+IF(N(Deals!S6)=0,0,MIN(N(Deals!S6),MAX(0,N(Deals!S6)+SheriffCostsFromBid-(J7)*(1-RTTPurchase)))))+Underwriting!$S6)/(Underwriting!$M6/12),0)) -> 0.62818333 | M7: =IF(Underwriting!$A6="","",IFERROR(Underwriting!$Z6/(((J7)*(1+BuyerPremium)+IF(N(Deals!S6)=0,0,MIN(N(Deals!S6),MAX(0,N(Deals!S6)+SheriffCostsFromBid-(J7)*(1-RTTPurchase)))))+Underwriting!$AA6),0)) -> 0.10958727 | N7: =IF(Underwriting!$A6="","",ROUND(N$2*$C7,-3)) -> 113000 | O7: =IF(Underwriting!$A6="","",Underwriting!$T6-((N7)*(1+BuyerPremium)+IF(N(Deals!S6)=0,0,MIN(N(Deals!S6),MAX(0,N(Deals!S6)+SheriffCostsFromBid-(N7)*(1-RTTPurchase)))))) -> 154256.19 | P7: =IF(Underwriting!$A6="","",IFERROR(O7/(((N7)*(1+BuyerPremium)+IF(N(Deals!S6)=0,0,MIN(N(Deals!S6),MAX(0,N(Deals!S6)+SheriffCostsFromBid-(N7)*(1-RTTPurchase)))))+Underwriting!$S6)/(Underwriting!$M6/12),0)) -> 0.39827307 | Q7: =IF(Underwriting!$A6="","",IFERROR(Underwriting!$Z6/(((N7)*(1+BuyerPremium)+IF(N(Deals!S6)=0,0,MIN(N(Deals!S6),MAX(0,N(Deals!S6)+SheriffCostsFromBid-(N7)*(1-RTTPurchase)))))+Underwriting!$AA6),0)) -> 0.086758596 | R7: =IF(Underwriting!$A6="","",ROUND(R$2*$C7,-3)) -> 150000 | S7: =IF(Underwriting!$A6="","",Underwriting!$T6-((R7)*(1+BuyerPremium)+IF(N(Deals!S6)=0,0,MIN(N(Deals!S6),MAX(0,N(Deals!S6)+SheriffCostsFromBid-(R7)*(1-RTTPurchase)))))) -> 116701.19 | T7: =IF(Underwriting!$A6="","",IFERROR(S7/(((R7)*(1+BuyerPremium)+IF(N(Deals!S6)=0,0,MIN(N(Deals!S6),MAX(0,N(Deals!S6)+SheriffCostsFromBid-(R7)*(1-RTTPurchase)))))+Underwriting!$S6)/(Underwriting!$M6/12),0)) -> 0.25067261 | U7: =IF(Underwriting!$A6="","",IFERROR(Underwriting!$Z6/(((R7)*(1+BuyerPremium)+IF(N(Deals!S6)=0,0,MIN(N(Deals!S6),MAX(0,N(Deals!S6)+SheriffCostsFromBid-(R7)*(1-RTTPurchase)))))+Underwriting!$AA6),0)) -> 0.072128543 | V7: =IF(Underwriting!$A6="","",ROUND(V$2*$C7,-3)) -> 188000 | W7: =IF(Underwriting!$A6="","",Underwriting!$T6-((V7)*(1+BuyerPremium)+IF(N(Deals!S6)=0,0,MIN(N(Deals!S6),MAX(0,N(Deals!S6)+SheriffCostsFromBid-(V7)*(1-RTTPurchase)))))) -> 78131.189 | X7: =IF(Underwriting!$A6="","",IFERROR(W7/(((V7)*(1+BuyerPremium)+IF(N(Deals!S6)=0,0,MIN(N(Deals!S6),MAX(0,N(Deals!S6)+SheriffCostsFromBid-(V7)*(1-RTTPurchase)))))+Underwriting!$S6)/(Underwriting!$M6/12),0)) -> 0.14312196 | Y7: =IF(Underwriting!$A6="","",IFERROR(Underwriting!$Z6/(((V7)*(1+BuyerPremium)+IF(N(Deals!S6)=0,0,MIN(N(Deals!S6),MAX(0,N(Deals!S6)+SheriffCostsFromBid-(V7)*(1-RTTPurchase)))))+Underwriting!$AA6),0)) -> 0.061480858 | Z7: =IF(Underwriting!$A6="","",ROUND(Z$2*$C7,-3)) -> 225000 | AA7: =IF(Underwriting!$A6="","",Underwriting!$T6-((Z7)*(1+BuyerPremium)+IF(N(Deals!S6)=0,0,MIN(N(Deals!S6),MAX(0,N(Deals!S6)+SheriffCostsFromBid-(Z7)*(1-RTTPurchase)))))) -> 40576.189 | AB7: =IF(Underwriting!$A6="","",IFERROR(AA7/(((Z7)*(1+BuyerPremium)+IF(N(Deals!S6)=0,0,MIN(N(Deals!S6),MAX(0,N(Deals!S6)+SheriffCostsFromBid-(Z7)*(1-RTTPurchase)))))+Underwriting!$S6)/(Underwriting!$M6/12),0)) -> 0.065010737 | AC7: =IF(Underwriting!$A6="","",IFERROR(Underwriting!$Z6/(((Z7)*(1+BuyerPremium)+IF(N(Deals!S6)=0,0,MIN(N(Deals!S6),MAX(0,N(Deals!S6)+SheriffCostsFromBid-(Z7)*(1-RTTPurchase)))))+Underwriting!$AA6),0)) -> 0.053754404 | AD7: =IF(Underwriting!$A6="","",ROUND(AD$2*$C7,-3)) -> 263000 | AE7: =IF(Underwriting!$A6="","",Underwriting!$T6-((AD7)*(1+BuyerPremium)+IF(N(Deals!S6)=0,0,MIN(N(Deals!S6),MAX(0,N(Deals!S6)+SheriffCostsFromBid-(AD7)*(1-RTTPurchase)))))) -> 2006.1887 | AF7: =IF(Underwriting!$A6="","",IFERROR(AE7/(((AD7)*(1+BuyerPremium)+IF(N(Deals!S6)=0,0,MIN(N(Deals!S6),MAX(0,N(Deals!S6)+SheriffCostsFromBid-(AD7)*(1-RTTPurchase)))))+Underwriting!$S6)/(Underwriting!$M6/12),0)) -> 0.0028476769 | AG7: =IF(Underwriting!$A6="","",IFERROR(Underwriting!$Z6/(((AD7)*(1+BuyerPremium)+IF(N(Deals!S6)=0,0,MIN(N(Deals!S6),MAX(0,N(Deals!S6)+SheriffCostsFromBid-(AD7)*(1-RTTPurchase)))))+Underwriting!$AA6),0)) -> 0.047609492 | AH7: =IF(Underwriting!$A6="","",$E7) -> 185181.5 | AI7: =IF(Underwriting!$A6="","",Underwriting!$T6-((AH7)*(1+BuyerPremium)+IF(N(Deals!S6)=0,0,MIN(N(Deals!S6),MAX(0,N(Deals!S6)+SheriffCostsFromBid-(AH7)*(1-RTTPurchase)))))) -> 80991.964 | AJ7: =IF(Underwriting!$A6="","",IFERROR(AI7/(((AH7)*(1+BuyerPremium)+IF(N(Deals!S6)=0,0,MIN(N(Deals!S6),MAX(0,N(Deals!S6)+SheriffCostsFromBid-(AH7)*(1-RTTPurchase)))))+Underwriting!$S6)/(Underwriting!$M6/12),0)) -> 0.15 | AK7: =IF(Underwriting!$A6="","",IFERROR(Underwriting!$Z6/(((AH7)*(1+BuyerPremium)+IF(N(Deals!S6)=0,0,MIN(N(Deals!S6),MAX(0,N(Deals!S6)+SheriffCostsFromBid-(AH7)*(1-RTTPurchase)))))+Underwriting!$AA6),0)) -> 0.062161476
A8: =Underwriting!$A7 -> 1318974-4 | B8: =Underwriting!$B7 -> 4 Downside: ARV 365k, Heavy, occupied | C8: =IF(Underwriting!$A7="","",N(Deals!M7)) -> 365000 | D8: =IF(Underwriting!$A7="","",N(Deals!D7)) -> 24700 | E8: =IF(Underwriting!$A7="","",Underwriting!$D7) -> 123711.53 | F8: =IF(Underwriting!$A7="","",$D8) -> 24700 | G8: =IF(Underwriting!$A7="","",Underwriting!$T7-((F8)*(1+BuyerPremium)+IF(N(Deals!S7)=0,0,MIN(N(Deals!S7),MAX(0,N(Deals!S7)+SheriffCostsFromBid-(F8)*(1-RTTPurchase)))))) -> 186336.18 | H8: =IF(Underwriting!$A7="","",IFERROR(G8/(((F8)*(1+BuyerPremium)+IF(N(Deals!S7)=0,0,MIN(N(Deals!S7),MAX(0,N(Deals!S7)+SheriffCostsFromBid-(F8)*(1-RTTPurchase)))))+Underwriting!$S7)/(Underwriting!$M7/12),0)) -> 0.55166436 | I8: =IF(Underwriting!$A7="","",IFERROR(Underwriting!$Z7/(((F8)*(1+BuyerPremium)+IF(N(Deals!S7)=0,0,MIN(N(Deals!S7),MAX(0,N(Deals!S7)+SheriffCostsFromBid-(F8)*(1-RTTPurchase)))))+Underwriting!$AA7),0)) -> 0.1125236 | J8: =IF(Underwriting!$A7="","",ROUND(J$2*$C8,-3)) -> 73000 | K8: =IF(Underwriting!$A7="","",Underwriting!$T7-((J8)*(1+BuyerPremium)+IF(N(Deals!S7)=0,0,MIN(N(Deals!S7),MAX(0,N(Deals!S7)+SheriffCostsFromBid-(J8)*(1-RTTPurchase)))))) -> 137311.68 | L8: =IF(Underwriting!$A7="","",IFERROR(K8/(((J8)*(1+BuyerPremium)+IF(N(Deals!S7)=0,0,MIN(N(Deals!S7),MAX(0,N(Deals!S7)+SheriffCostsFromBid-(J8)*(1-RTTPurchase)))))+Underwriting!$S7)/(Underwriting!$M7/12),0)) -> 0.30367845 | M8: =IF(Underwriting!$A7="","",IFERROR(Underwriting!$Z7/(((J8)*(1+BuyerPremium)+IF(N(Deals!S7)=0,0,MIN(N(Deals!S7),MAX(0,N(Deals!S7)+SheriffCostsFromBid-(J8)*(1-RTTPurchase)))))+Underwriting!$AA7),0)) -> 0.083944951 | N8: =IF(Underwriting!$A7="","",ROUND(N$2*$C8,-3)) -> 110000 | O8: =IF(Underwriting!$A7="","",Underwriting!$T7-((N8)*(1+BuyerPremium)+IF(N(Deals!S7)=0,0,MIN(N(Deals!S7),MAX(0,N(Deals!S7)+SheriffCostsFromBid-(N8)*(1-RTTPurchase)))))) -> 99756.681 | P8: =IF(Underwriting!$A7="","",IFERROR(O8/(((N8)*(1+BuyerPremium)+IF(N(Deals!S7)=0,0,MIN(N(Deals!S7),MAX(0,N(Deals!S7)+SheriffCostsFromBid-(N8)*(1-RTTPurchase)))))+Underwriting!$S7)/(Underwriting!$M7/12),0)) -> 0.18480655 | Q8: =IF(Underwriting!$A7="","",IFERROR(Underwriting!$Z7/(((N8)*(1+BuyerPremium)+IF(N(Deals!S7)=0,0,MIN(N(Deals!S7),MAX(0,N(Deals!S7)+SheriffCostsFromBid-(N8)*(1-RTTPurchase)))))+Underwriting!$AA7),0)) -> 0.070272717 | R8: =IF(Underwriting!$A7="","",ROUND(R$2*$C8,-3)) -> 146000 | S8: =IF(Underwriting!$A7="","",Underwriting!$T7-((R8)*(1+BuyerPremium)+IF(N(Deals!S7)=0,0,MIN(N(Deals!S7),MAX(0,N(Deals!S7)+SheriffCostsFromBid-(R8)*(1-RTTPurchase)))))) -> 63216.681 | T8: =IF(Underwriting!$A7="","",IFERROR(S8/(((R8)*(1+BuyerPremium)+IF(N(Deals!S7)=0,0,MIN(N(Deals!S7),MAX(0,N(Deals!S7)+SheriffCostsFromBid-(R8)*(1-RTTPurchase)))))+Underwriting!$S7)/(Underwriting!$M7/12),0)) -> 0.10113864 | U8: =IF(Underwriting!$A7="","",IFERROR(Underwriting!$Z7/(((R8)*(1+BuyerPremium)+IF(N(Deals!S7)=0,0,MIN(N(Deals!S7),MAX(0,N(Deals!S7)+SheriffCostsFromBid-(R8)*(1-RTTPurchase)))))+Underwriting!$AA7),0)) -> 0.060659964 | V8: =IF(Underwriting!$A7="","",ROUND(V$2*$C8,-3)) -> 183000 | W8: =IF(Underwriting!$A7="","",Underwriting!$T7-((V8)*(1+BuyerPremium)+IF(N(Deals!S7)=0,0,MIN(N(Deals!S7),MAX(0,N(Deals!S7)+SheriffCostsFromBid-(V8)*(1-RTTPurchase)))))) -> 25661.681 | X8: =IF(Underwriting!$A7="","",IFERROR(W8/(((V8)*(1+BuyerPremium)+IF(N(Deals!S7)=0,0,MIN(N(Deals!S7),MAX(0,N(Deals!S7)+SheriffCostsFromBid-(V8)*(1-RTTPurchase)))))+Underwriting!$S7)/(Underwriting!$M7/12),0)) -> 0.036007395 | Y8: =IF(Underwriting!$A7="","",IFERROR(Underwriting!$Z7/(((V8)*(1+BuyerPremium)+IF(N(Deals!S7)=0,0,MIN(N(Deals!S7),MAX(0,N(Deals!S7)+SheriffCostsFromBid-(V8)*(1-RTTPurchase)))))+Underwriting!$AA7),0)) -> 0.053182882 | Z8: =IF(Underwriting!$A7="","",ROUND(Z$2*$C8,-3)) -> 219000 | AA8: =IF(Underwriting!$A7="","",Underwriting!$T7-((Z8)*(1+BuyerPremium)+IF(N(Deals!S7)=0,0,MIN(N(Deals!S7),MAX(0,N(Deals!S7)+SheriffCostsFromBid-(Z8)*(1-RTTPurchase)))))) -> -10878.319 | AB8: =IF(Underwriting!$A7="","",IFERROR(AA8/(((Z8)*(1+BuyerPremium)+IF(N(Deals!S7)=0,0,MIN(N(Deals!S7),MAX(0,N(Deals!S7)+SheriffCostsFromBid-(Z8)*(1-RTTPurchase)))))+Underwriting!$S7)/(Underwriting!$M7/12),0)) -> -0.013633036 | AC8: =IF(Underwriting!$A7="","",IFERROR(Underwriting!$Z7/(((Z8)*(1+BuyerPremium)+IF(N(Deals!S7)=0,0,MIN(N(Deals!S7),MAX(0,N(Deals!S7)+SheriffCostsFromBid-(Z8)*(1-RTTPurchase)))))+Underwriting!$AA7),0)) -> 0.04748765 | AD8: =IF(Underwriting!$A7="","",ROUND(AD$2*$C8,-3)) -> 256000 | AE8: =IF(Underwriting!$A7="","",Underwriting!$T7-((AD8)*(1+BuyerPremium)+IF(N(Deals!S7)=0,0,MIN(N(Deals!S7),MAX(0,N(Deals!S7)+SheriffCostsFromBid-(AD8)*(1-RTTPurchase)))))) -> -48433.319 | AF8: =IF(Underwriting!$A7="","",IFERROR(AE8/(((AD8)*(1+BuyerPremium)+IF(N(Deals!S7)=0,0,MIN(N(Deals!S7),MAX(0,N(Deals!S7)+SheriffCostsFromBid-(AD8)*(1-RTTPurchase)))))+Underwriting!$S7)/(Underwriting!$M7/12),0)) -> -0.054691909 | AG8: =IF(Underwriting!$A7="","",IFERROR(Underwriting!$Z7/(((AD8)*(1+BuyerPremium)+IF(N(Deals!S7)=0,0,MIN(N(Deals!S7),MAX(0,N(Deals!S7)+SheriffCostsFromBid-(AD8)*(1-RTTPurchase)))))+Underwriting!$AA7),0)) -> 0.042779263 | AH8: =IF(Underwriting!$A7="","",$E8) -> 123711.53 | AI8: =IF(Underwriting!$A7="","",Underwriting!$T7-((AH8)*(1+BuyerPremium)+IF(N(Deals!S7)=0,0,MIN(N(Deals!S7),MAX(0,N(Deals!S7)+SheriffCostsFromBid-(AH8)*(1-RTTPurchase)))))) -> 85839.483 | AJ8: =IF(Underwriting!$A7="","",IFERROR(AI8/(((AH8)*(1+BuyerPremium)+IF(N(Deals!S7)=0,0,MIN(N(Deals!S7),MAX(0,N(Deals!S7)+SheriffCostsFromBid-(AH8)*(1-RTTPurchase)))))+Underwriting!$S7)/(Underwriting!$M7/12),0)) -> 0.15 | AK8: =IF(Underwriting!$A7="","",IFERROR(Underwriting!$Z7/(((AH8)*(1+BuyerPremium)+IF(N(Deals!S7)=0,0,MIN(N(Deals!S7),MAX(0,N(Deals!S7)+SheriffCostsFromBid-(AH8)*(1-RTTPurchase)))))+Underwriting!$AA7),0)) -> 0.066272685
A9: =Underwriting!$A8 -> 1318974-5 | B9: =Underwriting!$B8 -> 5 Upside: ARV 425k, Medium + half bath, occupied | C9: =IF(Underwriting!$A8="","",N(Deals!M8)) -> 425000 | D9: =IF(Underwriting!$A8="","",N(Deals!D8)) -> 24700 | E9: =IF(Underwriting!$A8="","",Underwriting!$D8) -> 175356.6 | F9: =IF(Underwriting!$A8="","",$D9) -> 24700 | G9: =IF(Underwriting!$A8="","",Underwriting!$T8-((F9)*(1+BuyerPremium)+IF(N(Deals!S8)=0,0,MIN(N(Deals!S8),MAX(0,N(Deals!S8)+SheriffCostsFromBid-(F9)*(1-RTTPurchase)))))) -> 247478.39 | H9: =IF(Underwriting!$A8="","",IFERROR(G9/(((F9)*(1+BuyerPremium)+IF(N(Deals!S8)=0,0,MIN(N(Deals!S8),MAX(0,N(Deals!S8)+SheriffCostsFromBid-(F9)*(1-RTTPurchase)))))+Underwriting!$S8)/(Underwriting!$M8/12),0)) -> 0.82742691 | I9: =IF(Underwriting!$A8="","",IFERROR(Underwriting!$Z8/(((F9)*(1+BuyerPremium)+IF(N(Deals!S8)=0,0,MIN(N(Deals!S8),MAX(0,N(Deals!S8)+SheriffCostsFromBid-(F9)*(1-RTTPurchase)))))+Underwriting!$AA8),0)) -> 0.11191017 | J9: =IF(Underwriting!$A8="","",ROUND(J$2*$C9,-3)) -> 85000 | K9: =IF(Underwriting!$A8="","",Underwriting!$T8-((J9)*(1+BuyerPremium)+IF(N(Deals!S8)=0,0,MIN(N(Deals!S8),MAX(0,N(Deals!S8)+SheriffCostsFromBid-(J9)*(1-RTTPurchase)))))) -> 186273.89 | L9: =IF(Underwriting!$A8="","",IFERROR(K9/(((J9)*(1+BuyerPremium)+IF(N(Deals!S8)=0,0,MIN(N(Deals!S8),MAX(0,N(Deals!S8)+SheriffCostsFromBid-(J9)*(1-RTTPurchase)))))+Underwriting!$S8)/(Underwriting!$M8/12),0)) -> 0.43148549 | M9: =IF(Underwriting!$A8="","",IFERROR(Underwriting!$Z8/(((J9)*(1+BuyerPremium)+IF(N(Deals!S8)=0,0,MIN(N(Deals!S8),MAX(0,N(Deals!S8)+SheriffCostsFromBid-(J9)*(1-RTTPurchase)))))+Underwriting!$AA8),0)) -> 0.077402616 | N9: =IF(Underwriting!$A8="","",ROUND(N$2*$C9,-3)) -> 128000 | O9: =IF(Underwriting!$A8="","",Underwriting!$T8-((N9)*(1+BuyerPremium)+IF(N(Deals!S8)=0,0,MIN(N(Deals!S8),MAX(0,N(Deals!S8)+SheriffCostsFromBid-(N9)*(1-RTTPurchase)))))) -> 142628.89 | P9: =IF(Underwriting!$A8="","",IFERROR(O9/(((N9)*(1+BuyerPremium)+IF(N(Deals!S8)=0,0,MIN(N(Deals!S8),MAX(0,N(Deals!S8)+SheriffCostsFromBid-(N9)*(1-RTTPurchase)))))+Underwriting!$S8)/(Underwriting!$M8/12),0)) -> 0.27101956 | Q9: =IF(Underwriting!$A8="","",IFERROR(Underwriting!$Z8/(((N9)*(1+BuyerPremium)+IF(N(Deals!S8)=0,0,MIN(N(Deals!S8),MAX(0,N(Deals!S8)+SheriffCostsFromBid-(N9)*(1-RTTPurchase)))))+Underwriting!$AA8),0)) -> 0.063450745 | R9: =IF(Underwriting!$A8="","",ROUND(R$2*$C9,-3)) -> 170000 | S9: =IF(Underwriting!$A8="","",Underwriting!$T8-((R9)*(1+BuyerPremium)+IF(N(Deals!S8)=0,0,MIN(N(Deals!S8),MAX(0,N(Deals!S8)+SheriffCostsFromBid-(R9)*(1-RTTPurchase)))))) -> 99998.886 | T9: =IF(Underwriting!$A8="","",IFERROR(S9/(((R9)*(1+BuyerPremium)+IF(N(Deals!S8)=0,0,MIN(N(Deals!S8),MAX(0,N(Deals!S8)+SheriffCostsFromBid-(R9)*(1-RTTPurchase)))))+Underwriting!$S8)/(Underwriting!$M8/12),0)) -> 0.16164496 | U9: =IF(Underwriting!$A8="","",IFERROR(Underwriting!$Z8/(((R9)*(1+BuyerPremium)+IF(N(Deals!S8)=0,0,MIN(N(Deals!S8),MAX(0,N(Deals!S8)+SheriffCostsFromBid-(R9)*(1-RTTPurchase)))))+Underwriting!$AA8),0)) -> 0.053952019 | V9: =IF(Underwriting!$A8="","",ROUND(V$2*$C9,-3)) -> 213000 | W9: =IF(Underwriting!$A8="","",Underwriting!$T8-((V9)*(1+BuyerPremium)+IF(N(Deals!S8)=0,0,MIN(N(Deals!S8),MAX(0,N(Deals!S8)+SheriffCostsFromBid-(V9)*(1-RTTPurchase)))))) -> 56353.886 | X9: =IF(Underwriting!$A8="","",IFERROR(W9/(((V9)*(1+BuyerPremium)+IF(N(Deals!S8)=0,0,MIN(N(Deals!S8),MAX(0,N(Deals!S8)+SheriffCostsFromBid-(V9)*(1-RTTPurchase)))))+Underwriting!$S8)/(Underwriting!$M8/12),0)) -> 0.079015873 | Y9: =IF(Underwriting!$A8="","",IFERROR(Underwriting!$Z8/(((V9)*(1+BuyerPremium)+IF(N(Deals!S8)=0,0,MIN(N(Deals!S8),MAX(0,N(Deals!S8)+SheriffCostsFromBid-(V9)*(1-RTTPurchase)))))+Underwriting!$AA8),0)) -> 0.04678191 | Z9: =IF(Underwriting!$A8="","",ROUND(Z$2*$C9,-3)) -> 255000 | AA9: =IF(Underwriting!$A8="","",Underwriting!$T8-((Z9)*(1+BuyerPremium)+IF(N(Deals!S8)=0,0,MIN(N(Deals!S8),MAX(0,N(Deals!S8)+SheriffCostsFromBid-(Z9)*(1-RTTPurchase)))))) -> 13723.886 | AB9: =IF(Underwriting!$A8="","",IFERROR(AA9/(((Z9)*(1+BuyerPremium)+IF(N(Deals!S8)=0,0,MIN(N(Deals!S8),MAX(0,N(Deals!S8)+SheriffCostsFromBid-(Z9)*(1-RTTPurchase)))))+Underwriting!$S8)/(Underwriting!$M8/12),0)) -> 0.017036411 | AC9: =IF(Underwriting!$A8="","",IFERROR(Underwriting!$Z8/(((Z9)*(1+BuyerPremium)+IF(N(Deals!S8)=0,0,MIN(N(Deals!S8),MAX(0,N(Deals!S8)+SheriffCostsFromBid-(Z9)*(1-RTTPurchase)))))+Underwriting!$AA8),0)) -> 0.041406984 | AD9: =IF(Underwriting!$A8="","",ROUND(AD$2*$C9,-3)) -> 298000 | AE9: =IF(Underwriting!$A8="","",Underwriting!$T8-((AD9)*(1+BuyerPremium)+IF(N(Deals!S8)=0,0,MIN(N(Deals!S8),MAX(0,N(Deals!S8)+SheriffCostsFromBid-(AD9)*(1-RTTPurchase)))))) -> -29921.114 | AF9: =IF(Underwriting!$A8="","",IFERROR(AE9/(((AD9)*(1+BuyerPremium)+IF(N(Deals!S8)=0,0,MIN(N(Deals!S8),MAX(0,N(Deals!S8)+SheriffCostsFromBid-(AD9)*(1-RTTPurchase)))))+Underwriting!$S8)/(Underwriting!$M8/12),0)) -> -0.033241021 | AG9: =IF(Underwriting!$A8="","",IFERROR(Underwriting!$Z8/(((AD9)*(1+BuyerPremium)+IF(N(Deals!S8)=0,0,MIN(N(Deals!S8),MAX(0,N(Deals!S8)+SheriffCostsFromBid-(AD9)*(1-RTTPurchase)))))+Underwriting!$AA8),0)) -> 0.037048959 | AH9: =IF(Underwriting!$A8="","",$E9) -> 175356.6 | AI9: =IF(Underwriting!$A8="","",Underwriting!$T8-((AH9)*(1+BuyerPremium)+IF(N(Deals!S8)=0,0,MIN(N(Deals!S8),MAX(0,N(Deals!S8)+SheriffCostsFromBid-(AH9)*(1-RTTPurchase)))))) -> 94561.939 | AJ9: =IF(Underwriting!$A8="","",IFERROR(AI9/(((AH9)*(1+BuyerPremium)+IF(N(Deals!S8)=0,0,MIN(N(Deals!S8),MAX(0,N(Deals!S8)+SheriffCostsFromBid-(AH9)*(1-RTTPurchase)))))+Underwriting!$S8)/(Underwriting!$M8/12),0)) -> 0.15 | AK9: =IF(Underwriting!$A8="","",IFERROR(Underwriting!$Z8/(((AH9)*(1+BuyerPremium)+IF(N(Deals!S8)=0,0,MIN(N(Deals!S8),MAX(0,N(Deals!S8)+SheriffCostsFromBid-(AH9)*(1-RTTPurchase)))))+Underwriting!$AA8),0)) -> 0.052941226
A10: =Underwriting!$A9 -> 1318974-6 | B10: =Underwriting!$B9 -> 6 Slow ejectment proxy: ARV 395k, Medium, occupied, Heavy timeline | C10: =IF(Underwriting!$A9="","",N(Deals!M9)) -> 395000 | D10: =IF(Underwriting!$A9="","",N(Deals!D9)) -> 24700 | E10: =IF(Underwriting!$A9="","",Underwriting!$D9) -> 143571.62 | F10: =IF(Underwriting!$A9="","",$D10) -> 24700 | G10: =IF(Underwriting!$A9="","",Underwriting!$T9-((F10)*(1+BuyerPremium)+IF(N(Deals!S9)=0,0,MIN(N(Deals!S9),MAX(0,N(Deals!S9)+SheriffCostsFromBid-(F10)*(1-RTTPurchase)))))) -> 213549.48 | H10: =IF(Underwriting!$A9="","",IFERROR(G10/(((F10)*(1+BuyerPremium)+IF(N(Deals!S9)=0,0,MIN(N(Deals!S9),MAX(0,N(Deals!S9)+SheriffCostsFromBid-(F10)*(1-RTTPurchase)))))+Underwriting!$S9)/(Underwriting!$M9/12),0)) -> 0.63223168 | I10: =IF(Underwriting!$A9="","",IFERROR(Underwriting!$Z9/(((F10)*(1+BuyerPremium)+IF(N(Deals!S9)=0,0,MIN(N(Deals!S9),MAX(0,N(Deals!S9)+SheriffCostsFromBid-(F10)*(1-RTTPurchase)))))+Underwriting!$AA9),0)) -> 0.10960738 | J10: =IF(Underwriting!$A9="","",ROUND(J$2*$C10,-3)) -> 79000 | K10: =IF(Underwriting!$A9="","",Underwriting!$T9-((J10)*(1+BuyerPremium)+IF(N(Deals!S9)=0,0,MIN(N(Deals!S9),MAX(0,N(Deals!S9)+SheriffCostsFromBid-(J10)*(1-RTTPurchase)))))) -> 158434.98 | L10: =IF(Underwriting!$A9="","",IFERROR(K10/(((J10)*(1+BuyerPremium)+IF(N(Deals!S9)=0,0,MIN(N(Deals!S9),MAX(0,N(Deals!S9)+SheriffCostsFromBid-(J10)*(1-RTTPurchase)))))+Underwriting!$S9)/(Underwriting!$M9/12),0)) -> 0.33971846 | M10: =IF(Underwriting!$A9="","",IFERROR(Underwriting!$Z9/(((J10)*(1+BuyerPremium)+IF(N(Deals!S9)=0,0,MIN(N(Deals!S9),MAX(0,N(Deals!S9)+SheriffCostsFromBid-(J10)*(1-RTTPurchase)))))+Underwriting!$AA9),0)) -> 0.079268449 | N10: =IF(Underwriting!$A9="","",ROUND(N$2*$C10,-3)) -> 119000 | O10: =IF(Underwriting!$A9="","",Underwriting!$T9-((N10)*(1+BuyerPremium)+IF(N(Deals!S9)=0,0,MIN(N(Deals!S9),MAX(0,N(Deals!S9)+SheriffCostsFromBid-(N10)*(1-RTTPurchase)))))) -> 117834.98 | P10: =IF(Underwriting!$A9="","",IFERROR(O10/(((N10)*(1+BuyerPremium)+IF(N(Deals!S9)=0,0,MIN(N(Deals!S9),MAX(0,N(Deals!S9)+SheriffCostsFromBid-(N10)*(1-RTTPurchase)))))+Underwriting!$S9)/(Underwriting!$M9/12),0)) -> 0.21000531 | Q10: =IF(Underwriting!$A9="","",IFERROR(Underwriting!$Z9/(((N10)*(1+BuyerPremium)+IF(N(Deals!S9)=0,0,MIN(N(Deals!S9),MAX(0,N(Deals!S9)+SheriffCostsFromBid-(N10)*(1-RTTPurchase)))))+Underwriting!$AA9),0)) -> 0.065842964 | R10: =IF(Underwriting!$A9="","",ROUND(R$2*$C10,-3)) -> 158000 | S10: =IF(Underwriting!$A9="","",Underwriting!$T9-((R10)*(1+BuyerPremium)+IF(N(Deals!S9)=0,0,MIN(N(Deals!S9),MAX(0,N(Deals!S9)+SheriffCostsFromBid-(R10)*(1-RTTPurchase)))))) -> 78249.981 | T10: =IF(Underwriting!$A9="","",IFERROR(S10/(((R10)*(1+BuyerPremium)+IF(N(Deals!S9)=0,0,MIN(N(Deals!S9),MAX(0,N(Deals!S9)+SheriffCostsFromBid-(R10)*(1-RTTPurchase)))))+Underwriting!$S9)/(Underwriting!$M9/12),0)) -> 0.11974537 | U10: =IF(Underwriting!$A9="","",IFERROR(Underwriting!$Z9/(((R10)*(1+BuyerPremium)+IF(N(Deals!S9)=0,0,MIN(N(Deals!S9),MAX(0,N(Deals!S9)+SheriffCostsFromBid-(R10)*(1-RTTPurchase)))))+Underwriting!$AA9),0)) -> 0.056511108 | V10: =IF(Underwriting!$A9="","",ROUND(V$2*$C10,-3)) -> 198000 | W10: =IF(Underwriting!$A9="","",Underwriting!$T9-((V10)*(1+BuyerPremium)+IF(N(Deals!S9)=0,0,MIN(N(Deals!S9),MAX(0,N(Deals!S9)+SheriffCostsFromBid-(V10)*(1-RTTPurchase)))))) -> 37649.981 | X10: =IF(Underwriting!$A9="","",IFERROR(W10/(((V10)*(1+BuyerPremium)+IF(N(Deals!S9)=0,0,MIN(N(Deals!S9),MAX(0,N(Deals!S9)+SheriffCostsFromBid-(V10)*(1-RTTPurchase)))))+Underwriting!$S9)/(Underwriting!$M9/12),0)) -> 0.050320537 | Y10: =IF(Underwriting!$A9="","",IFERROR(Underwriting!$Z9/(((V10)*(1+BuyerPremium)+IF(N(Deals!S9)=0,0,MIN(N(Deals!S9),MAX(0,N(Deals!S9)+SheriffCostsFromBid-(V10)*(1-RTTPurchase)))))+Underwriting!$AA9),0)) -> 0.049339034 | Z10: =IF(Underwriting!$A9="","",ROUND(Z$2*$C10,-3)) -> 237000 | AA10: =IF(Underwriting!$A9="","",Underwriting!$T9-((Z10)*(1+BuyerPremium)+IF(N(Deals!S9)=0,0,MIN(N(Deals!S9),MAX(0,N(Deals!S9)+SheriffCostsFromBid-(Z10)*(1-RTTPurchase)))))) -> -1935.0186 | AB10: =IF(Underwriting!$A9="","",IFERROR(AA10/(((Z10)*(1+BuyerPremium)+IF(N(Deals!S9)=0,0,MIN(N(Deals!S9),MAX(0,N(Deals!S9)+SheriffCostsFromBid-(Z10)*(1-RTTPurchase)))))+Underwriting!$S9)/(Underwriting!$M9/12),0)) -> -0.0023020367 | AC10: =IF(Underwriting!$A9="","",IFERROR(Underwriting!$Z9/(((Z10)*(1+BuyerPremium)+IF(N(Deals!S9)=0,0,MIN(N(Deals!S9),MAX(0,N(Deals!S9)+SheriffCostsFromBid-(Z10)*(1-RTTPurchase)))))+Underwriting!$AA9),0)) -> 0.043906034 | AD10: =IF(Underwriting!$A9="","",ROUND(AD$2*$C10,-3)) -> 277000 | AE10: =IF(Underwriting!$A9="","",Underwriting!$T9-((AD10)*(1+BuyerPremium)+IF(N(Deals!S9)=0,0,MIN(N(Deals!S9),MAX(0,N(Deals!S9)+SheriffCostsFromBid-(AD10)*(1-RTTPurchase)))))) -> -42535.019 | AF10: =IF(Underwriting!$A9="","",IFERROR(AE10/(((AD10)*(1+BuyerPremium)+IF(N(Deals!S9)=0,0,MIN(N(Deals!S9),MAX(0,N(Deals!S9)+SheriffCostsFromBid-(AD10)*(1-RTTPurchase)))))+Underwriting!$S9)/(Underwriting!$M9/12),0)) -> -0.045477337 | AG10: =IF(Underwriting!$A9="","",IFERROR(Underwriting!$Z9/(((AD10)*(1+BuyerPremium)+IF(N(Deals!S9)=0,0,MIN(N(Deals!S9),MAX(0,N(Deals!S9)+SheriffCostsFromBid-(AD10)*(1-RTTPurchase)))))+Underwriting!$AA9),0)) -> 0.039450526 | AH10: =IF(Underwriting!$A9="","",$E10) -> 143571.62 | AI10: =IF(Underwriting!$A9="","",Underwriting!$T9-((AH10)*(1+BuyerPremium)+IF(N(Deals!S9)=0,0,MIN(N(Deals!S9),MAX(0,N(Deals!S9)+SheriffCostsFromBid-(AH10)*(1-RTTPurchase)))))) -> 92894.783 | AJ10: =IF(Underwriting!$A9="","",IFERROR(AI10/(((AH10)*(1+BuyerPremium)+IF(N(Deals!S9)=0,0,MIN(N(Deals!S9),MAX(0,N(Deals!S9)+SheriffCostsFromBid-(AH10)*(1-RTTPurchase)))))+Underwriting!$S9)/(Underwriting!$M9/12),0)) -> 0.15 | AK10: =IF(Underwriting!$A9="","",IFERROR(Underwriting!$Z9/(((AH10)*(1+BuyerPremium)+IF(N(Deals!S9)=0,0,MIN(N(Deals!S9),MAX(0,N(Deals!S9)+SheriffCostsFromBid-(AH10)*(1-RTTPurchase)))))+Underwriting!$AA9),0)) -> 0.059638165
A11: =Underwriting!$A10 | B11: =Underwriting!$B10 | C11: =IF(Underwriting!$A10="","",N(Deals!M10)) | D11: =IF(Underwriting!$A10="","",N(Deals!D10)) | E11: =IF(Underwriting!$A10="","",Underwriting!$D10) | F11: =IF(Underwriting!$A10="","",$D11) | G11: =IF(Underwriting!$A10="","",Underwriting!$T10-((F11)*(1+BuyerPremium)+IF(N(Deals!S10)=0,0,MIN(N(Deals!S10),MAX(0,N(Deals!S10)+SheriffCostsFromBid-(F11)*(1-RTTPurchase)))))) | H11: =IF(Underwriting!$A10="","",IFERROR(G11/(((F11)*(1+BuyerPremium)+IF(N(Deals!S10)=0,0,MIN(N(Deals!S10),MAX(0,N(Deals!S10)+SheriffCostsFromBid-(F11)*(1-RTTPurchase)))))+Underwriting!$S10)/(Underwriting!$M10/12),0)) | I11: =IF(Underwriting!$A10="","",IFERROR(Underwriting!$Z10/(((F11)*(1+BuyerPremium)+IF(N(Deals!S10)=0,0,MIN(N(Deals!S10),MAX(0,N(Deals!S10)+SheriffCostsFromBid-(F11)*(1-RTTPurchase)))))+Underwriting!$AA10),0)) | J11: =IF(Underwriting!$A10="","",ROUND(J$2*$C11,-3)) | K11: =IF(Underwriting!$A10="","",Underwriting!$T10-((J11)*(1+BuyerPremium)+IF(N(Deals!S10)=0,0,MIN(N(Deals!S10),MAX(0,N(Deals!S10)+SheriffCostsFromBid-(J11)*(1-RTTPurchase)))))) | L11: =IF(Underwriting!$A10="","",IFERROR(K11/(((J11)*(1+BuyerPremium)+IF(N(Deals!S10)=0,0,MIN(N(Deals!S10),MAX(0,N(Deals!S10)+SheriffCostsFromBid-(J11)*(1-RTTPurchase)))))+Underwriting!$S10)/(Underwriting!$M10/12),0)) | M11: =IF(Underwriting!$A10="","",IFERROR(Underwriting!$Z10/(((J11)*(1+BuyerPremium)+IF(N(Deals!S10)=0,0,MIN(N(Deals!S10),MAX(0,N(Deals!S10)+SheriffCostsFromBid-(J11)*(1-RTTPurchase)))))+Underwriting!$AA10),0)) | N11: =IF(Underwriting!$A10="","",ROUND(N$2*$C11,-3)) | O11: =IF(Underwriting!$A10="","",Underwriting!$T10-((N11)*(1+BuyerPremium)+IF(N(Deals!S10)=0,0,MIN(N(Deals!S10),MAX(0,N(Deals!S10)+SheriffCostsFromBid-(N11)*(1-RTTPurchase)))))) | P11: =IF(Underwriting!$A10="","",IFERROR(O11/(((N11)*(1+BuyerPremium)+IF(N(Deals!S10)=0,0,MIN(N(Deals!S10),MAX(0,N(Deals!S10)+SheriffCostsFromBid-(N11)*(1-RTTPurchase)))))+Underwriting!$S10)/(Underwriting!$M10/12),0)) | Q11: =IF(Underwriting!$A10="","",IFERROR(Underwriting!$Z10/(((N11)*(1+BuyerPremium)+IF(N(Deals!S10)=0,0,MIN(N(Deals!S10),MAX(0,N(Deals!S10)+SheriffCostsFromBid-(N11)*(1-RTTPurchase)))))+Underwriting!$AA10),0)) | R11: =IF(Underwriting!$A10="","",ROUND(R$2*$C11,-3)) | S11: =IF(Underwriting!$A10="","",Underwriting!$T10-((R11)*(1+BuyerPremium)+IF(N(Deals!S10)=0,0,MIN(N(Deals!S10),MAX(0,N(Deals!S10)+SheriffCostsFromBid-(R11)*(1-RTTPurchase)))))) | T11: =IF(Underwriting!$A10="","",IFERROR(S11/(((R11)*(1+BuyerPremium)+IF(N(Deals!S10)=0,0,MIN(N(Deals!S10),MAX(0,N(Deals!S10)+SheriffCostsFromBid-(R11)*(1-RTTPurchase)))))+Underwriting!$S10)/(Underwriting!$M10/12),0)) | U11: =IF(Underwriting!$A10="","",IFERROR(Underwriting!$Z10/(((R11)*(1+BuyerPremium)+IF(N(Deals!S10)=0,0,MIN(N(Deals!S10),MAX(0,N(Deals!S10)+SheriffCostsFromBid-(R11)*(1-RTTPurchase)))))+Underwriting!$AA10),0)) | V11: =IF(Underwriting!$A10="","",ROUND(V$2*$C11,-3)) | W11: =IF(Underwriting!$A10="","",Underwriting!$T10-((V11)*(1+BuyerPremium)+IF(N(Deals!S10)=0,0,MIN(N(Deals!S10),MAX(0,N(Deals!S10)+SheriffCostsFromBid-(V11)*(1-RTTPurchase)))))) | X11: =IF(Underwriting!$A10="","",IFERROR(W11/(((V11)*(1+BuyerPremium)+IF(N(Deals!S10)=0,0,MIN(N(Deals!S10),MAX(0,N(Deals!S10)+SheriffCostsFromBid-(V11)*(1-RTTPurchase)))))+Underwriting!$S10)/(Underwriting!$M10/12),0)) | Y11: =IF(Underwriting!$A10="","",IFERROR(Underwriting!$Z10/(((V11)*(1+BuyerPremium)+IF(N(Deals!S10)=0,0,MIN(N(Deals!S10),MAX(0,N(Deals!S10)+SheriffCostsFromBid-(V11)*(1-RTTPurchase)))))+Underwriting!$AA10),0)) | Z11: =IF(Underwriting!$A10="","",ROUND(Z$2*$C11,-3)) | AA11: =IF(Underwriting!$A10="","",Underwriting!$T10-((Z11)*(1+BuyerPremium)+IF(N(Deals!S10)=0,0,MIN(N(Deals!S10),MAX(0,N(Deals!S10)+SheriffCostsFromBid-(Z11)*(1-RTTPurchase)))))) | AB11: =IF(Underwriting!$A10="","",IFERROR(AA11/(((Z11)*(1+BuyerPremium)+IF(N(Deals!S10)=0,0,MIN(N(Deals!S10),MAX(0,N(Deals!S10)+SheriffCostsFromBid-(Z11)*(1-RTTPurchase)))))+Underwriting!$S10)/(Underwriting!$M10/12),0)) | AC11: =IF(Underwriting!$A10="","",IFERROR(Underwriting!$Z10/(((Z11)*(1+BuyerPremium)+IF(N(Deals!S10)=0,0,MIN(N(Deals!S10),MAX(0,N(Deals!S10)+SheriffCostsFromBid-(Z11)*(1-RTTPurchase)))))+Underwriting!$AA10),0)) | AD11: =IF(Underwriting!$A10="","",ROUND(AD$2*$C11,-3)) | AE11: =IF(Underwriting!$A10="","",Underwriting!$T10-((AD11)*(1+BuyerPremium)+IF(N(Deals!S10)=0,0,MIN(N(Deals!S10),MAX(0,N(Deals!S10)+SheriffCostsFromBid-(AD11)*(1-RTTPurchase)))))) | AF11: =IF(Underwriting!$A10="","",IFERROR(AE11/(((AD11)*(1+BuyerPremium)+IF(N(Deals!S10)=0,0,MIN(N(Deals!S10),MAX(0,N(Deals!S10)+SheriffCostsFromBid-(AD11)*(1-RTTPurchase)))))+Underwriting!$S10)/(Underwriting!$M10/12),0)) | AG11: =IF(Underwriting!$A10="","",IFERROR(Underwriting!$Z10/(((AD11)*(1+BuyerPremium)+IF(N(Deals!S10)=0,0,MIN(N(Deals!S10),MAX(0,N(Deals!S10)+SheriffCostsFromBid-(AD11)*(1-RTTPurchase)))))+Underwriting!$AA10),0)) | AH11: =IF(Underwriting!$A10="","",$E11) | AI11: =IF(Underwriting!$A10="","",Underwriting!$T10-((AH11)*(1+BuyerPremium)+IF(N(Deals!S10)=0,0,MIN(N(Deals!S10),MAX(0,N(Deals!S10)+SheriffCostsFromBid-(AH11)*(1-RTTPurchase)))))) | AJ11: =IF(Underwriting!$A10="","",IFERROR(AI11/(((AH11)*(1+BuyerPremium)+IF(N(Deals!S10)=0,0,MIN(N(Deals!S10),MAX(0,N(Deals!S10)+SheriffCostsFromBid-(AH11)*(1-RTTPurchase)))))+Underwriting!$S10)/(Underwriting!$M10/12),0)) | AK11: =IF(Underwriting!$A10="","",IFERROR(Underwriting!$Z10/(((AH11)*(1+BuyerPremium)+IF(N(Deals!S10)=0,0,MIN(N(Deals!S10),MAX(0,N(Deals!S10)+SheriffCostsFromBid-(AH11)*(1-RTTPurchase)))))+Underwriting!$AA10),0))
A12: =Underwriting!$A11 | B12: =Underwriting!$B11 | C12: =IF(Underwriting!$A11="","",N(Deals!M11)) | D12: =IF(Underwriting!$A11="","",N(Deals!D11)) | E12: =IF(Underwriting!$A11="","",Underwriting!$D11) | F12: =IF(Underwriting!$A11="","",$D12) | G12: =IF(Underwriting!$A11="","",Underwriting!$T11-((F12)*(1+BuyerPremium)+IF(N(Deals!S11)=0,0,MIN(N(Deals!S11),MAX(0,N(Deals!S11)+SheriffCostsFromBid-(F12)*(1-RTTPurchase)))))) | H12: =IF(Underwriting!$A11="","",IFERROR(G12/(((F12)*(1+BuyerPremium)+IF(N(Deals!S11)=0,0,MIN(N(Deals!S11),MAX(0,N(Deals!S11)+SheriffCostsFromBid-(F12)*(1-RTTPurchase)))))+Underwriting!$S11)/(Underwriting!$M11/12),0)) | I12: =IF(Underwriting!$A11="","",IFERROR(Underwriting!$Z11/(((F12)*(1+BuyerPremium)+IF(N(Deals!S11)=0,0,MIN(N(Deals!S11),MAX(0,N(Deals!S11)+SheriffCostsFromBid-(F12)*(1-RTTPurchase)))))+Underwriting!$AA11),0)) | J12: =IF(Underwriting!$A11="","",ROUND(J$2*$C12,-3)) | K12: =IF(Underwriting!$A11="","",Underwriting!$T11-((J12)*(1+BuyerPremium)+IF(N(Deals!S11)=0,0,MIN(N(Deals!S11),MAX(0,N(Deals!S11)+SheriffCostsFromBid-(J12)*(1-RTTPurchase)))))) | L12: =IF(Underwriting!$A11="","",IFERROR(K12/(((J12)*(1+BuyerPremium)+IF(N(Deals!S11)=0,0,MIN(N(Deals!S11),MAX(0,N(Deals!S11)+SheriffCostsFromBid-(J12)*(1-RTTPurchase)))))+Underwriting!$S11)/(Underwriting!$M11/12),0)) | M12: =IF(Underwriting!$A11="","",IFERROR(Underwriting!$Z11/(((J12)*(1+BuyerPremium)+IF(N(Deals!S11)=0,0,MIN(N(Deals!S11),MAX(0,N(Deals!S11)+SheriffCostsFromBid-(J12)*(1-RTTPurchase)))))+Underwriting!$AA11),0)) | N12: =IF(Underwriting!$A11="","",ROUND(N$2*$C12,-3)) | O12: =IF(Underwriting!$A11="","",Underwriting!$T11-((N12)*(1+BuyerPremium)+IF(N(Deals!S11)=0,0,MIN(N(Deals!S11),MAX(0,N(Deals!S11)+SheriffCostsFromBid-(N12)*(1-RTTPurchase)))))) | P12: =IF(Underwriting!$A11="","",IFERROR(O12/(((N12)*(1+BuyerPremium)+IF(N(Deals!S11)=0,0,MIN(N(Deals!S11),MAX(0,N(Deals!S11)+SheriffCostsFromBid-(N12)*(1-RTTPurchase)))))+Underwriting!$S11)/(Underwriting!$M11/12),0)) | Q12: =IF(Underwriting!$A11="","",IFERROR(Underwriting!$Z11/(((N12)*(1+BuyerPremium)+IF(N(Deals!S11)=0,0,MIN(N(Deals!S11),MAX(0,N(Deals!S11)+SheriffCostsFromBid-(N12)*(1-RTTPurchase)))))+Underwriting!$AA11),0)) | R12: =IF(Underwriting!$A11="","",ROUND(R$2*$C12,-3)) | S12: =IF(Underwriting!$A11="","",Underwriting!$T11-((R12)*(1+BuyerPremium)+IF(N(Deals!S11)=0,0,MIN(N(Deals!S11),MAX(0,N(Deals!S11)+SheriffCostsFromBid-(R12)*(1-RTTPurchase)))))) | T12: =IF(Underwriting!$A11="","",IFERROR(S12/(((R12)*(1+BuyerPremium)+IF(N(Deals!S11)=0,0,MIN(N(Deals!S11),MAX(0,N(Deals!S11)+SheriffCostsFromBid-(R12)*(1-RTTPurchase)))))+Underwriting!$S11)/(Underwriting!$M11/12),0)) | U12: =IF(Underwriting!$A11="","",IFERROR(Underwriting!$Z11/(((R12)*(1+BuyerPremium)+IF(N(Deals!S11)=0,0,MIN(N(Deals!S11),MAX(0,N(Deals!S11)+SheriffCostsFromBid-(R12)*(1-RTTPurchase)))))+Underwriting!$AA11),0)) | V12: =IF(Underwriting!$A11="","",ROUND(V$2*$C12,-3)) | W12: =IF(Underwriting!$A11="","",Underwriting!$T11-((V12)*(1+BuyerPremium)+IF(N(Deals!S11)=0,0,MIN(N(Deals!S11),MAX(0,N(Deals!S11)+SheriffCostsFromBid-(V12)*(1-RTTPurchase)))))) | X12: =IF(Underwriting!$A11="","",IFERROR(W12/(((V12)*(1+BuyerPremium)+IF(N(Deals!S11)=0,0,MIN(N(Deals!S11),MAX(0,N(Deals!S11)+SheriffCostsFromBid-(V12)*(1-RTTPurchase)))))+Underwriting!$S11)/(Underwriting!$M11/12),0)) | Y12: =IF(Underwriting!$A11="","",IFERROR(Underwriting!$Z11/(((V12)*(1+BuyerPremium)+IF(N(Deals!S11)=0,0,MIN(N(Deals!S11),MAX(0,N(Deals!S11)+SheriffCostsFromBid-(V12)*(1-RTTPurchase)))))+Underwriting!$AA11),0)) | Z12: =IF(Underwriting!$A11="","",ROUND(Z$2*$C12,-3)) | AA12: =IF(Underwriting!$A11="","",Underwriting!$T11-((Z12)*(1+BuyerPremium)+IF(N(Deals!S11)=0,0,MIN(N(Deals!S11),MAX(0,N(Deals!S11)+SheriffCostsFromBid-(Z12)*(1-RTTPurchase)))))) | AB12: =IF(Underwriting!$A11="","",IFERROR(AA12/(((Z12)*(1+BuyerPremium)+IF(N(Deals!S11)=0,0,MIN(N(Deals!S11),MAX(0,N(Deals!S11)+SheriffCostsFromBid-(Z12)*(1-RTTPurchase)))))+Underwriting!$S11)/(Underwriting!$M11/12),0)) | AC12: =IF(Underwriting!$A11="","",IFERROR(Underwriting!$Z11/(((Z12)*(1+BuyerPremium)+IF(N(Deals!S11)=0,0,MIN(N(Deals!S11),MAX(0,N(Deals!S11)+SheriffCostsFromBid-(Z12)*(1-RTTPurchase)))))+Underwriting!$AA11),0)) | AD12: =IF(Underwriting!$A11="","",ROUND(AD$2*$C12,-3)) | AE12: =IF(Underwriting!$A11="","",Underwriting!$T11-((AD12)*(1+BuyerPremium)+IF(N(Deals!S11)=0,0,MIN(N(Deals!S11),MAX(0,N(Deals!S11)+SheriffCostsFromBid-(AD12)*(1-RTTPurchase)))))) | AF12: =IF(Underwriting!$A11="","",IFERROR(AE12/(((AD12)*(1+BuyerPremium)+IF(N(Deals!S11)=0,0,MIN(N(Deals!S11),MAX(0,N(Deals!S11)+SheriffCostsFromBid-(AD12)*(1-RTTPurchase)))))+Underwriting!$S11)/(Underwriting!$M11/12),0)) | AG12: =IF(Underwriting!$A11="","",IFERROR(Underwriting!$Z11/(((AD12)*(1+BuyerPremium)+IF(N(Deals!S11)=0,0,MIN(N(Deals!S11),MAX(0,N(Deals!S11)+SheriffCostsFromBid-(AD12)*(1-RTTPurchase)))))+Underwriting!$AA11),0)) | AH12: =IF(Underwriting!$A11="","",$E12) | AI12: =IF(Underwriting!$A11="","",Underwriting!$T11-((AH12)*(1+BuyerPremium)+IF(N(Deals!S11)=0,0,MIN(N(Deals!S11),MAX(0,N(Deals!S11)+SheriffCostsFromBid-(AH12)*(1-RTTPurchase)))))) | AJ12: =IF(Underwriting!$A11="","",IFERROR(AI12/(((AH12)*(1+BuyerPremium)+IF(N(Deals!S11)=0,0,MIN(N(Deals!S11),MAX(0,N(Deals!S11)+SheriffCostsFromBid-(AH12)*(1-RTTPurchase)))))+Underwriting!$S11)/(Underwriting!$M11/12),0)) | AK12: =IF(Underwriting!$A11="","",IFERROR(Underwriting!$Z11/(((AH12)*(1+BuyerPremium)+IF(N(Deals!S11)=0,0,MIN(N(Deals!S11),MAX(0,N(Deals!S11)+SheriffCostsFromBid-(AH12)*(1-RTTPurchase)))))+Underwriting!$AA11),0))
A13: =Underwriting!$A12 | B13: =Underwriting!$B12 | C13: =IF(Underwriting!$A12="","",N(Deals!M12)) | D13: =IF(Underwriting!$A12="","",N(Deals!D12)) | E13: =IF(Underwriting!$A12="","",Underwriting!$D12) | F13: =IF(Underwriting!$A12="","",$D13) | G13: =IF(Underwriting!$A12="","",Underwriting!$T12-((F13)*(1+BuyerPremium)+IF(N(Deals!S12)=0,0,MIN(N(Deals!S12),MAX(0,N(Deals!S12)+SheriffCostsFromBid-(F13)*(1-RTTPurchase)))))) | H13: =IF(Underwriting!$A12="","",IFERROR(G13/(((F13)*(1+BuyerPremium)+IF(N(Deals!S12)=0,0,MIN(N(Deals!S12),MAX(0,N(Deals!S12)+SheriffCostsFromBid-(F13)*(1-RTTPurchase)))))+Underwriting!$S12)/(Underwriting!$M12/12),0)) | I13: =IF(Underwriting!$A12="","",IFERROR(Underwriting!$Z12/(((F13)*(1+BuyerPremium)+IF(N(Deals!S12)=0,0,MIN(N(Deals!S12),MAX(0,N(Deals!S12)+SheriffCostsFromBid-(F13)*(1-RTTPurchase)))))+Underwriting!$AA12),0)) | J13: =IF(Underwriting!$A12="","",ROUND(J$2*$C13,-3)) | K13: =IF(Underwriting!$A12="","",Underwriting!$T12-((J13)*(1+BuyerPremium)+IF(N(Deals!S12)=0,0,MIN(N(Deals!S12),MAX(0,N(Deals!S12)+SheriffCostsFromBid-(J13)*(1-RTTPurchase)))))) | L13: =IF(Underwriting!$A12="","",IFERROR(K13/(((J13)*(1+BuyerPremium)+IF(N(Deals!S12)=0,0,MIN(N(Deals!S12),MAX(0,N(Deals!S12)+SheriffCostsFromBid-(J13)*(1-RTTPurchase)))))+Underwriting!$S12)/(Underwriting!$M12/12),0)) | M13: =IF(Underwriting!$A12="","",IFERROR(Underwriting!$Z12/(((J13)*(1+BuyerPremium)+IF(N(Deals!S12)=0,0,MIN(N(Deals!S12),MAX(0,N(Deals!S12)+SheriffCostsFromBid-(J13)*(1-RTTPurchase)))))+Underwriting!$AA12),0)) | N13: =IF(Underwriting!$A12="","",ROUND(N$2*$C13,-3)) | O13: =IF(Underwriting!$A12="","",Underwriting!$T12-((N13)*(1+BuyerPremium)+IF(N(Deals!S12)=0,0,MIN(N(Deals!S12),MAX(0,N(Deals!S12)+SheriffCostsFromBid-(N13)*(1-RTTPurchase)))))) | P13: =IF(Underwriting!$A12="","",IFERROR(O13/(((N13)*(1+BuyerPremium)+IF(N(Deals!S12)=0,0,MIN(N(Deals!S12),MAX(0,N(Deals!S12)+SheriffCostsFromBid-(N13)*(1-RTTPurchase)))))+Underwriting!$S12)/(Underwriting!$M12/12),0)) | Q13: =IF(Underwriting!$A12="","",IFERROR(Underwriting!$Z12/(((N13)*(1+BuyerPremium)+IF(N(Deals!S12)=0,0,MIN(N(Deals!S12),MAX(0,N(Deals!S12)+SheriffCostsFromBid-(N13)*(1-RTTPurchase)))))+Underwriting!$AA12),0)) | R13: =IF(Underwriting!$A12="","",ROUND(R$2*$C13,-3)) | S13: =IF(Underwriting!$A12="","",Underwriting!$T12-((R13)*(1+BuyerPremium)+IF(N(Deals!S12)=0,0,MIN(N(Deals!S12),MAX(0,N(Deals!S12)+SheriffCostsFromBid-(R13)*(1-RTTPurchase)))))) | T13: =IF(Underwriting!$A12="","",IFERROR(S13/(((R13)*(1+BuyerPremium)+IF(N(Deals!S12)=0,0,MIN(N(Deals!S12),MAX(0,N(Deals!S12)+SheriffCostsFromBid-(R13)*(1-RTTPurchase)))))+Underwriting!$S12)/(Underwriting!$M12/12),0)) | U13: =IF(Underwriting!$A12="","",IFERROR(Underwriting!$Z12/(((R13)*(1+BuyerPremium)+IF(N(Deals!S12)=0,0,MIN(N(Deals!S12),MAX(0,N(Deals!S12)+SheriffCostsFromBid-(R13)*(1-RTTPurchase)))))+Underwriting!$AA12),0)) | V13: =IF(Underwriting!$A12="","",ROUND(V$2*$C13,-3)) | W13: =IF(Underwriting!$A12="","",Underwriting!$T12-((V13)*(1+BuyerPremium)+IF(N(Deals!S12)=0,0,MIN(N(Deals!S12),MAX(0,N(Deals!S12)+SheriffCostsFromBid-(V13)*(1-RTTPurchase)))))) | X13: =IF(Underwriting!$A12="","",IFERROR(W13/(((V13)*(1+BuyerPremium)+IF(N(Deals!S12)=0,0,MIN(N(Deals!S12),MAX(0,N(Deals!S12)+SheriffCostsFromBid-(V13)*(1-RTTPurchase)))))+Underwriting!$S12)/(Underwriting!$M12/12),0)) | Y13: =IF(Underwriting!$A12="","",IFERROR(Underwriting!$Z12/(((V13)*(1+BuyerPremium)+IF(N(Deals!S12)=0,0,MIN(N(Deals!S12),MAX(0,N(Deals!S12)+SheriffCostsFromBid-(V13)*(1-RTTPurchase)))))+Underwriting!$AA12),0)) | Z13: =IF(Underwriting!$A12="","",ROUND(Z$2*$C13,-3)) | AA13: =IF(Underwriting!$A12="","",Underwriting!$T12-((Z13)*(1+BuyerPremium)+IF(N(Deals!S12)=0,0,MIN(N(Deals!S12),MAX(0,N(Deals!S12)+SheriffCostsFromBid-(Z13)*(1-RTTPurchase)))))) | AB13: =IF(Underwriting!$A12="","",IFERROR(AA13/(((Z13)*(1+BuyerPremium)+IF(N(Deals!S12)=0,0,MIN(N(Deals!S12),MAX(0,N(Deals!S12)+SheriffCostsFromBid-(Z13)*(1-RTTPurchase)))))+Underwriting!$S12)/(Underwriting!$M12/12),0)) | AC13: =IF(Underwriting!$A12="","",IFERROR(Underwriting!$Z12/(((Z13)*(1+BuyerPremium)+IF(N(Deals!S12)=0,0,MIN(N(Deals!S12),MAX(0,N(Deals!S12)+SheriffCostsFromBid-(Z13)*(1-RTTPurchase)))))+Underwriting!$AA12),0)) | AD13: =IF(Underwriting!$A12="","",ROUND(AD$2*$C13,-3)) | AE13: =IF(Underwriting!$A12="","",Underwriting!$T12-((AD13)*(1+BuyerPremium)+IF(N(Deals!S12)=0,0,MIN(N(Deals!S12),MAX(0,N(Deals!S12)+SheriffCostsFromBid-(AD13)*(1-RTTPurchase)))))) | AF13: =IF(Underwriting!$A12="","",IFERROR(AE13/(((AD13)*(1+BuyerPremium)+IF(N(Deals!S12)=0,0,MIN(N(Deals!S12),MAX(0,N(Deals!S12)+SheriffCostsFromBid-(AD13)*(1-RTTPurchase)))))+Underwriting!$S12)/(Underwriting!$M12/12),0)) | AG13: =IF(Underwriting!$A12="","",IFERROR(Underwriting!$Z12/(((AD13)*(1+BuyerPremium)+IF(N(Deals!S12)=0,0,MIN(N(Deals!S12),MAX(0,N(Deals!S12)+SheriffCostsFromBid-(AD13)*(1-RTTPurchase)))))+Underwriting!$AA12),0)) | AH13: =IF(Underwriting!$A12="","",$E13) | AI13: =IF(Underwriting!$A12="","",Underwriting!$T12-((AH13)*(1+BuyerPremium)+IF(N(Deals!S12)=0,0,MIN(N(Deals!S12),MAX(0,N(Deals!S12)+SheriffCostsFromBid-(AH13)*(1-RTTPurchase)))))) | AJ13: =IF(Underwriting!$A12="","",IFERROR(AI13/(((AH13)*(1+BuyerPremium)+IF(N(Deals!S12)=0,0,MIN(N(Deals!S12),MAX(0,N(Deals!S12)+SheriffCostsFromBid-(AH13)*(1-RTTPurchase)))))+Underwriting!$S12)/(Underwriting!$M12/12),0)) | AK13: =IF(Underwriting!$A12="","",IFERROR(Underwriting!$Z12/(((AH13)*(1+BuyerPremium)+IF(N(Deals!S12)=0,0,MIN(N(Deals!S12),MAX(0,N(Deals!S12)+SheriffCostsFromBid-(AH13)*(1-RTTPurchase)))))+Underwriting!$AA12),0))
A14: =Underwriting!$A13 | B14: =Underwriting!$B13 | C14: =IF(Underwriting!$A13="","",N(Deals!M13)) | D14: =IF(Underwriting!$A13="","",N(Deals!D13)) | E14: =IF(Underwriting!$A13="","",Underwriting!$D13) | F14: =IF(Underwriting!$A13="","",$D14) | G14: =IF(Underwriting!$A13="","",Underwriting!$T13-((F14)*(1+BuyerPremium)+IF(N(Deals!S13)=0,0,MIN(N(Deals!S13),MAX(0,N(Deals!S13)+SheriffCostsFromBid-(F14)*(1-RTTPurchase)))))) | H14: =IF(Underwriting!$A13="","",IFERROR(G14/(((F14)*(1+BuyerPremium)+IF(N(Deals!S13)=0,0,MIN(N(Deals!S13),MAX(0,N(Deals!S13)+SheriffCostsFromBid-(F14)*(1-RTTPurchase)))))+Underwriting!$S13)/(Underwriting!$M13/12),0)) | I14: =IF(Underwriting!$A13="","",IFERROR(Underwriting!$Z13/(((F14)*(1+BuyerPremium)+IF(N(Deals!S13)=0,0,MIN(N(Deals!S13),MAX(0,N(Deals!S13)+SheriffCostsFromBid-(F14)*(1-RTTPurchase)))))+Underwriting!$AA13),0)) | J14: =IF(Underwriting!$A13="","",ROUND(J$2*$C14,-3)) | K14: =IF(Underwriting!$A13="","",Underwriting!$T13-((J14)*(1+BuyerPremium)+IF(N(Deals!S13)=0,0,MIN(N(Deals!S13),MAX(0,N(Deals!S13)+SheriffCostsFromBid-(J14)*(1-RTTPurchase)))))) | L14: =IF(Underwriting!$A13="","",IFERROR(K14/(((J14)*(1+BuyerPremium)+IF(N(Deals!S13)=0,0,MIN(N(Deals!S13),MAX(0,N(Deals!S13)+SheriffCostsFromBid-(J14)*(1-RTTPurchase)))))+Underwriting!$S13)/(Underwriting!$M13/12),0)) | M14: =IF(Underwriting!$A13="","",IFERROR(Underwriting!$Z13/(((J14)*(1+BuyerPremium)+IF(N(Deals!S13)=0,0,MIN(N(Deals!S13),MAX(0,N(Deals!S13)+SheriffCostsFromBid-(J14)*(1-RTTPurchase)))))+Underwriting!$AA13),0)) | N14: =IF(Underwriting!$A13="","",ROUND(N$2*$C14,-3)) | O14: =IF(Underwriting!$A13="","",Underwriting!$T13-((N14)*(1+BuyerPremium)+IF(N(Deals!S13)=0,0,MIN(N(Deals!S13),MAX(0,N(Deals!S13)+SheriffCostsFromBid-(N14)*(1-RTTPurchase)))))) | P14: =IF(Underwriting!$A13="","",IFERROR(O14/(((N14)*(1+BuyerPremium)+IF(N(Deals!S13)=0,0,MIN(N(Deals!S13),MAX(0,N(Deals!S13)+SheriffCostsFromBid-(N14)*(1-RTTPurchase)))))+Underwriting!$S13)/(Underwriting!$M13/12),0)) | Q14: =IF(Underwriting!$A13="","",IFERROR(Underwriting!$Z13/(((N14)*(1+BuyerPremium)+IF(N(Deals!S13)=0,0,MIN(N(Deals!S13),MAX(0,N(Deals!S13)+SheriffCostsFromBid-(N14)*(1-RTTPurchase)))))+Underwriting!$AA13),0)) | R14: =IF(Underwriting!$A13="","",ROUND(R$2*$C14,-3)) | S14: =IF(Underwriting!$A13="","",Underwriting!$T13-((R14)*(1+BuyerPremium)+IF(N(Deals!S13)=0,0,MIN(N(Deals!S13),MAX(0,N(Deals!S13)+SheriffCostsFromBid-(R14)*(1-RTTPurchase)))))) | T14: =IF(Underwriting!$A13="","",IFERROR(S14/(((R14)*(1+BuyerPremium)+IF(N(Deals!S13)=0,0,MIN(N(Deals!S13),MAX(0,N(Deals!S13)+SheriffCostsFromBid-(R14)*(1-RTTPurchase)))))+Underwriting!$S13)/(Underwriting!$M13/12),0)) | U14: =IF(Underwriting!$A13="","",IFERROR(Underwriting!$Z13/(((R14)*(1+BuyerPremium)+IF(N(Deals!S13)=0,0,MIN(N(Deals!S13),MAX(0,N(Deals!S13)+SheriffCostsFromBid-(R14)*(1-RTTPurchase)))))+Underwriting!$AA13),0)) | V14: =IF(Underwriting!$A13="","",ROUND(V$2*$C14,-3)) | W14: =IF(Underwriting!$A13="","",Underwriting!$T13-((V14)*(1+BuyerPremium)+IF(N(Deals!S13)=0,0,MIN(N(Deals!S13),MAX(0,N(Deals!S13)+SheriffCostsFromBid-(V14)*(1-RTTPurchase)))))) | X14: =IF(Underwriting!$A13="","",IFERROR(W14/(((V14)*(1+BuyerPremium)+IF(N(Deals!S13)=0,0,MIN(N(Deals!S13),MAX(0,N(Deals!S13)+SheriffCostsFromBid-(V14)*(1-RTTPurchase)))))+Underwriting!$S13)/(Underwriting!$M13/12),0)) | Y14: =IF(Underwriting!$A13="","",IFERROR(Underwriting!$Z13/(((V14)*(1+BuyerPremium)+IF(N(Deals!S13)=0,0,MIN(N(Deals!S13),MAX(0,N(Deals!S13)+SheriffCostsFromBid-(V14)*(1-RTTPurchase)))))+Underwriting!$AA13),0)) | Z14: =IF(Underwriting!$A13="","",ROUND(Z$2*$C14,-3)) | AA14: =IF(Underwriting!$A13="","",Underwriting!$T13-((Z14)*(1+BuyerPremium)+IF(N(Deals!S13)=0,0,MIN(N(Deals!S13),MAX(0,N(Deals!S13)+SheriffCostsFromBid-(Z14)*(1-RTTPurchase)))))) | AB14: =IF(Underwriting!$A13="","",IFERROR(AA14/(((Z14)*(1+BuyerPremium)+IF(N(Deals!S13)=0,0,MIN(N(Deals!S13),MAX(0,N(Deals!S13)+SheriffCostsFromBid-(Z14)*(1-RTTPurchase)))))+Underwriting!$S13)/(Underwriting!$M13/12),0)) | AC14: =IF(Underwriting!$A13="","",IFERROR(Underwriting!$Z13/(((Z14)*(1+BuyerPremium)+IF(N(Deals!S13)=0,0,MIN(N(Deals!S13),MAX(0,N(Deals!S13)+SheriffCostsFromBid-(Z14)*(1-RTTPurchase)))))+Underwriting!$AA13),0)) | AD14: =IF(Underwriting!$A13="","",ROUND(AD$2*$C14,-3)) | AE14: =IF(Underwriting!$A13="","",Underwriting!$T13-((AD14)*(1+BuyerPremium)+IF(N(Deals!S13)=0,0,MIN(N(Deals!S13),MAX(0,N(Deals!S13)+SheriffCostsFromBid-(AD14)*(1-RTTPurchase)))))) | AF14: =IF(Underwriting!$A13="","",IFERROR(AE14/(((AD14)*(1+BuyerPremium)+IF(N(Deals!S13)=0,0,MIN(N(Deals!S13),MAX(0,N(Deals!S13)+SheriffCostsFromBid-(AD14)*(1-RTTPurchase)))))+Underwriting!$S13)/(Underwriting!$M13/12),0)) | AG14: =IF(Underwriting!$A13="","",IFERROR(Underwriting!$Z13/(((AD14)*(1+BuyerPremium)+IF(N(Deals!S13)=0,0,MIN(N(Deals!S13),MAX(0,N(Deals!S13)+SheriffCostsFromBid-(AD14)*(1-RTTPurchase)))))+Underwriting!$AA13),0)) | AH14: =IF(Underwriting!$A13="","",$E14) | AI14: =IF(Underwriting!$A13="","",Underwriting!$T13-((AH14)*(1+BuyerPremium)+IF(N(Deals!S13)=0,0,MIN(N(Deals!S13),MAX(0,N(Deals!S13)+SheriffCostsFromBid-(AH14)*(1-RTTPurchase)))))) | AJ14: =IF(Underwriting!$A13="","",IFERROR(AI14/(((AH14)*(1+BuyerPremium)+IF(N(Deals!S13)=0,0,MIN(N(Deals!S13),MAX(0,N(Deals!S13)+SheriffCostsFromBid-(AH14)*(1-RTTPurchase)))))+Underwriting!$S13)/(Underwriting!$M13/12),0)) | AK14: =IF(Underwriting!$A13="","",IFERROR(Underwriting!$Z13/(((AH14)*(1+BuyerPremium)+IF(N(Deals!S13)=0,0,MIN(N(Deals!S13),MAX(0,N(Deals!S13)+SheriffCostsFromBid-(AH14)*(1-RTTPurchase)))))+Underwriting!$AA13),0))
A15: =Underwriting!$A14 | B15: =Underwriting!$B14 | C15: =IF(Underwriting!$A14="","",N(Deals!M14)) | D15: =IF(Underwriting!$A14="","",N(Deals!D14)) | E15: =IF(Underwriting!$A14="","",Underwriting!$D14) | F15: =IF(Underwriting!$A14="","",$D15) | G15: =IF(Underwriting!$A14="","",Underwriting!$T14-((F15)*(1+BuyerPremium)+IF(N(Deals!S14)=0,0,MIN(N(Deals!S14),MAX(0,N(Deals!S14)+SheriffCostsFromBid-(F15)*(1-RTTPurchase)))))) | H15: =IF(Underwriting!$A14="","",IFERROR(G15/(((F15)*(1+BuyerPremium)+IF(N(Deals!S14)=0,0,MIN(N(Deals!S14),MAX(0,N(Deals!S14)+SheriffCostsFromBid-(F15)*(1-RTTPurchase)))))+Underwriting!$S14)/(Underwriting!$M14/12),0)) | I15: =IF(Underwriting!$A14="","",IFERROR(Underwriting!$Z14/(((F15)*(1+BuyerPremium)+IF(N(Deals!S14)=0,0,MIN(N(Deals!S14),MAX(0,N(Deals!S14)+SheriffCostsFromBid-(F15)*(1-RTTPurchase)))))+Underwriting!$AA14),0)) | J15: =IF(Underwriting!$A14="","",ROUND(J$2*$C15,-3)) | K15: =IF(Underwriting!$A14="","",Underwriting!$T14-((J15)*(1+BuyerPremium)+IF(N(Deals!S14)=0,0,MIN(N(Deals!S14),MAX(0,N(Deals!S14)+SheriffCostsFromBid-(J15)*(1-RTTPurchase)))))) | L15: =IF(Underwriting!$A14="","",IFERROR(K15/(((J15)*(1+BuyerPremium)+IF(N(Deals!S14)=0,0,MIN(N(Deals!S14),MAX(0,N(Deals!S14)+SheriffCostsFromBid-(J15)*(1-RTTPurchase)))))+Underwriting!$S14)/(Underwriting!$M14/12),0)) | M15: =IF(Underwriting!$A14="","",IFERROR(Underwriting!$Z14/(((J15)*(1+BuyerPremium)+IF(N(Deals!S14)=0,0,MIN(N(Deals!S14),MAX(0,N(Deals!S14)+SheriffCostsFromBid-(J15)*(1-RTTPurchase)))))+Underwriting!$AA14),0)) | N15: =IF(Underwriting!$A14="","",ROUND(N$2*$C15,-3)) | O15: =IF(Underwriting!$A14="","",Underwriting!$T14-((N15)*(1+BuyerPremium)+IF(N(Deals!S14)=0,0,MIN(N(Deals!S14),MAX(0,N(Deals!S14)+SheriffCostsFromBid-(N15)*(1-RTTPurchase)))))) | P15: =IF(Underwriting!$A14="","",IFERROR(O15/(((N15)*(1+BuyerPremium)+IF(N(Deals!S14)=0,0,MIN(N(Deals!S14),MAX(0,N(Deals!S14)+SheriffCostsFromBid-(N15)*(1-RTTPurchase)))))+Underwriting!$S14)/(Underwriting!$M14/12),0)) | Q15: =IF(Underwriting!$A14="","",IFERROR(Underwriting!$Z14/(((N15)*(1+BuyerPremium)+IF(N(Deals!S14)=0,0,MIN(N(Deals!S14),MAX(0,N(Deals!S14)+SheriffCostsFromBid-(N15)*(1-RTTPurchase)))))+Underwriting!$AA14),0)) | R15: =IF(Underwriting!$A14="","",ROUND(R$2*$C15,-3)) | S15: =IF(Underwriting!$A14="","",Underwriting!$T14-((R15)*(1+BuyerPremium)+IF(N(Deals!S14)=0,0,MIN(N(Deals!S14),MAX(0,N(Deals!S14)+SheriffCostsFromBid-(R15)*(1-RTTPurchase)))))) | T15: =IF(Underwriting!$A14="","",IFERROR(S15/(((R15)*(1+BuyerPremium)+IF(N(Deals!S14)=0,0,MIN(N(Deals!S14),MAX(0,N(Deals!S14)+SheriffCostsFromBid-(R15)*(1-RTTPurchase)))))+Underwriting!$S14)/(Underwriting!$M14/12),0)) | U15: =IF(Underwriting!$A14="","",IFERROR(Underwriting!$Z14/(((R15)*(1+BuyerPremium)+IF(N(Deals!S14)=0,0,MIN(N(Deals!S14),MAX(0,N(Deals!S14)+SheriffCostsFromBid-(R15)*(1-RTTPurchase)))))+Underwriting!$AA14),0)) | V15: =IF(Underwriting!$A14="","",ROUND(V$2*$C15,-3)) | W15: =IF(Underwriting!$A14="","",Underwriting!$T14-((V15)*(1+BuyerPremium)+IF(N(Deals!S14)=0,0,MIN(N(Deals!S14),MAX(0,N(Deals!S14)+SheriffCostsFromBid-(V15)*(1-RTTPurchase)))))) | X15: =IF(Underwriting!$A14="","",IFERROR(W15/(((V15)*(1+BuyerPremium)+IF(N(Deals!S14)=0,0,MIN(N(Deals!S14),MAX(0,N(Deals!S14)+SheriffCostsFromBid-(V15)*(1-RTTPurchase)))))+Underwriting!$S14)/(Underwriting!$M14/12),0)) | Y15: =IF(Underwriting!$A14="","",IFERROR(Underwriting!$Z14/(((V15)*(1+BuyerPremium)+IF(N(Deals!S14)=0,0,MIN(N(Deals!S14),MAX(0,N(Deals!S14)+SheriffCostsFromBid-(V15)*(1-RTTPurchase)))))+Underwriting!$AA14),0)) | Z15: =IF(Underwriting!$A14="","",ROUND(Z$2*$C15,-3)) | AA15: =IF(Underwriting!$A14="","",Underwriting!$T14-((Z15)*(1+BuyerPremium)+IF(N(Deals!S14)=0,0,MIN(N(Deals!S14),MAX(0,N(Deals!S14)+SheriffCostsFromBid-(Z15)*(1-RTTPurchase)))))) | AB15: =IF(Underwriting!$A14="","",IFERROR(AA15/(((Z15)*(1+BuyerPremium)+IF(N(Deals!S14)=0,0,MIN(N(Deals!S14),MAX(0,N(Deals!S14)+SheriffCostsFromBid-(Z15)*(1-RTTPurchase)))))+Underwriting!$S14)/(Underwriting!$M14/12),0)) | AC15: =IF(Underwriting!$A14="","",IFERROR(Underwriting!$Z14/(((Z15)*(1+BuyerPremium)+IF(N(Deals!S14)=0,0,MIN(N(Deals!S14),MAX(0,N(Deals!S14)+SheriffCostsFromBid-(Z15)*(1-RTTPurchase)))))+Underwriting!$AA14),0)) | AD15: =IF(Underwriting!$A14="","",ROUND(AD$2*$C15,-3)) | AE15: =IF(Underwriting!$A14="","",Underwriting!$T14-((AD15)*(1+BuyerPremium)+IF(N(Deals!S14)=0,0,MIN(N(Deals!S14),MAX(0,N(Deals!S14)+SheriffCostsFromBid-(AD15)*(1-RTTPurchase)))))) | AF15: =IF(Underwriting!$A14="","",IFERROR(AE15/(((AD15)*(1+BuyerPremium)+IF(N(Deals!S14)=0,0,MIN(N(Deals!S14),MAX(0,N(Deals!S14)+SheriffCostsFromBid-(AD15)*(1-RTTPurchase)))))+Underwriting!$S14)/(Underwriting!$M14/12),0)) | AG15: =IF(Underwriting!$A14="","",IFERROR(Underwriting!$Z14/(((AD15)*(1+BuyerPremium)+IF(N(Deals!S14)=0,0,MIN(N(Deals!S14),MAX(0,N(Deals!S14)+SheriffCostsFromBid-(AD15)*(1-RTTPurchase)))))+Underwriting!$AA14),0)) | AH15: =IF(Underwriting!$A14="","",$E15) | AI15: =IF(Underwriting!$A14="","",Underwriting!$T14-((AH15)*(1+BuyerPremium)+IF(N(Deals!S14)=0,0,MIN(N(Deals!S14),MAX(0,N(Deals!S14)+SheriffCostsFromBid-(AH15)*(1-RTTPurchase)))))) | AJ15: =IF(Underwriting!$A14="","",IFERROR(AI15/(((AH15)*(1+BuyerPremium)+IF(N(Deals!S14)=0,0,MIN(N(Deals!S14),MAX(0,N(Deals!S14)+SheriffCostsFromBid-(AH15)*(1-RTTPurchase)))))+Underwriting!$S14)/(Underwriting!$M14/12),0)) | AK15: =IF(Underwriting!$A14="","",IFERROR(Underwriting!$Z14/(((AH15)*(1+BuyerPremium)+IF(N(Deals!S14)=0,0,MIN(N(Deals!S14),MAX(0,N(Deals!S14)+SheriffCostsFromBid-(AH15)*(1-RTTPurchase)))))+Underwriting!$AA14),0))
... A43: =Underwriting!$A42 | B43: =Underwriting!$B42 | C43: =IF(Underwriting!$A42="","",N(Deals!M42)) | D43: =IF(Underwriting!$A42="","",N(Deals!D42)) | E43: =IF(Underwriting!$A42="","",Underwriting!$D42) | F43: =IF(Underwriting!$A42="","",$D43) | G43: =IF(Underwriting!$A42="","",Underwriting!$T42-((F43)*(1+BuyerPremium)+IF(N(Deals!S42)=0,0,MIN(N(Deals!S42),MAX(0,N(Deals!S42)+SheriffCostsFromBid-(F43)*(1-RTTPurchase)))))) | H43: =IF(Underwriting!$A42="","",IFERROR(G43/(((F43)*(1+BuyerPremium)+IF(N(Deals!S42)=0,0,MIN(N(Deals!S42),MAX(0,N(Deals!S42)+SheriffCostsFromBid-(F43)*(1-RTTPurchase)))))+Underwriting!$S42)/(Underwriting!$M42/12),0)) | I43: =IF(Underwriting!$A42="","",IFERROR(Underwriting!$Z42/(((F43)*(1+BuyerPremium)+IF(N(Deals!S42)=0,0,MIN(N(Deals!S42),MAX(0,N(Deals!S42)+SheriffCostsFromBid-(F43)*(1-RTTPurchase)))))+Underwriting!$AA42),0)) | J43: =IF(Underwriting!$A42="","",ROUND(J$2*$C43,-3)) | K43: =IF(Underwriting!$A42="","",Underwriting!$T42-((J43)*(1+BuyerPremium)+IF(N(Deals!S42)=0,0,MIN(N(Deals!S42),MAX(0,N(Deals!S42)+SheriffCostsFromBid-(J43)*(1-RTTPurchase)))))) | L43: =IF(Underwriting!$A42="","",IFERROR(K43/(((J43)*(1+BuyerPremium)+IF(N(Deals!S42)=0,0,MIN(N(Deals!S42),MAX(0,N(Deals!S42)+SheriffCostsFromBid-(J43)*(1-RTTPurchase)))))+Underwriting!$S42)/(Underwriting!$M42/12),0)) | M43: =IF(Underwriting!$A42="","",IFERROR(Underwriting!$Z42/(((J43)*(1+BuyerPremium)+IF(N(Deals!S42)=0,0,MIN(N(Deals!S42),MAX(0,N(Deals!S42)+SheriffCostsFromBid-(J43)*(1-RTTPurchase)))))+Underwriting!$AA42),0)) | N43: =IF(Underwriting!$A42="","",ROUND(N$2*$C43,-3)) | O43: =IF(Underwriting!$A42="","",Underwriting!$T42-((N43)*(1+BuyerPremium)+IF(N(Deals!S42)=0,0,MIN(N(Deals!S42),MAX(0,N(Deals!S42)+SheriffCostsFromBid-(N43)*(1-RTTPurchase)))))) | P43: =IF(Underwriting!$A42="","",IFERROR(O43/(((N43)*(1+BuyerPremium)+IF(N(Deals!S42)=0,0,MIN(N(Deals!S42),MAX(0,N(Deals!S42)+SheriffCostsFromBid-(N43)*(1-RTTPurchase)))))+Underwriting!$S42)/(Underwriting!$M42/12),0)) | Q43: =IF(Underwriting!$A42="","",IFERROR(Underwriting!$Z42/(((N43)*(1+BuyerPremium)+IF(N(Deals!S42)=0,0,MIN(N(Deals!S42),MAX(0,N(Deals!S42)+SheriffCostsFromBid-(N43)*(1-RTTPurchase)))))+Underwriting!$AA42),0)) | R43: =IF(Underwriting!$A42="","",ROUND(R$2*$C43,-3)) | S43: =IF(Underwriting!$A42="","",Underwriting!$T42-((R43)*(1+BuyerPremium)+IF(N(Deals!S42)=0,0,MIN(N(Deals!S42),MAX(0,N(Deals!S42)+SheriffCostsFromBid-(R43)*(1-RTTPurchase)))))) | T43: =IF(Underwriting!$A42="","",IFERROR(S43/(((R43)*(1+BuyerPremium)+IF(N(Deals!S42)=0,0,MIN(N(Deals!S42),MAX(0,N(Deals!S42)+SheriffCostsFromBid-(R43)*(1-RTTPurchase)))))+Underwriting!$S42)/(Underwriting!$M42/12),0)) | U43: =IF(Underwriting!$A42="","",IFERROR(Underwriting!$Z42/(((R43)*(1+BuyerPremium)+IF(N(Deals!S42)=0,0,MIN(N(Deals!S42),MAX(0,N(Deals!S42)+SheriffCostsFromBid-(R43)*(1-RTTPurchase)))))+Underwriting!$AA42),0)) | V43: =IF(Underwriting!$A42="","",ROUND(V$2*$C43,-3)) | W43: =IF(Underwriting!$A42="","",Underwriting!$T42-((V43)*(1+BuyerPremium)+IF(N(Deals!S42)=0,0,MIN(N(Deals!S42),MAX(0,N(Deals!S42)+SheriffCostsFromBid-(V43)*(1-RTTPurchase)))))) | X43: =IF(Underwriting!$A42="","",IFERROR(W43/(((V43)*(1+BuyerPremium)+IF(N(Deals!S42)=0,0,MIN(N(Deals!S42),MAX(0,N(Deals!S42)+SheriffCostsFromBid-(V43)*(1-RTTPurchase)))))+Underwriting!$S42)/(Underwriting!$M42/12),0)) | Y43: =IF(Underwriting!$A42="","",IFERROR(Underwriting!$Z42/(((V43)*(1+BuyerPremium)+IF(N(Deals!S42)=0,0,MIN(N(Deals!S42),MAX(0,N(Deals!S42)+SheriffCostsFromBid-(V43)*(1-RTTPurchase)))))+Underwriting!$AA42),0)) | Z43: =IF(Underwriting!$A42="","",ROUND(Z$2*$C43,-3)) | AA43: =IF(Underwriting!$A42="","",Underwriting!$T42-((Z43)*(1+BuyerPremium)+IF(N(Deals!S42)=0,0,MIN(N(Deals!S42),MAX(0,N(Deals!S42)+SheriffCostsFromBid-(Z43)*(1-RTTPurchase)))))) | AB43: =IF(Underwriting!$A42="","",IFERROR(AA43/(((Z43)*(1+BuyerPremium)+IF(N(Deals!S42)=0,0,MIN(N(Deals!S42),MAX(0,N(Deals!S42)+SheriffCostsFromBid-(Z43)*(1-RTTPurchase)))))+Underwriting!$S42)/(Underwriting!$M42/12),0)) | AC43: =IF(Underwriting!$A42="","",IFERROR(Underwriting!$Z42/(((Z43)*(1+BuyerPremium)+IF(N(Deals!S42)=0,0,MIN(N(Deals!S42),MAX(0,N(Deals!S42)+SheriffCostsFromBid-(Z43)*(1-RTTPurchase)))))+Underwriting!$AA42),0)) | AD43: =IF(Underwriting!$A42="","",ROUND(AD$2*$C43,-3)) | AE43: =IF(Underwriting!$A42="","",Underwriting!$T42-((AD43)*(1+BuyerPremium)+IF(N(Deals!S42)=0,0,MIN(N(Deals!S42),MAX(0,N(Deals!S42)+SheriffCostsFromBid-(AD43)*(1-RTTPurchase)))))) | AF43: =IF(Underwriting!$A42="","",IFERROR(AE43/(((AD43)*(1+BuyerPremium)+IF(N(Deals!S42)=0,0,MIN(N(Deals!S42),MAX(0,N(Deals!S42)+SheriffCostsFromBid-(AD43)*(1-RTTPurchase)))))+Underwriting!$S42)/(Underwriting!$M42/12),0)) | AG43: =IF(Underwriting!$A42="","",IFERROR(Underwriting!$Z42/(((AD43)*(1+BuyerPremium)+IF(N(Deals!S42)=0,0,MIN(N(Deals!S42),MAX(0,N(Deals!S42)+SheriffCostsFromBid-(AD43)*(1-RTTPurchase)))))+Underwriting!$AA42),0)) | AH43: =IF(Underwriting!$A42="","",$E43) | AI43: =IF(Underwriting!$A42="","",Underwriting!$T42-((AH43)*(1+BuyerPremium)+IF(N(Deals!S42)=0,0,MIN(N(Deals!S42),MAX(0,N(Deals!S42)+SheriffCostsFromBid-(AH43)*(1-RTTPurchase)))))) | AJ43: =IF(Underwriting!$A42="","",IFERROR(AI43/(((AH43)*(1+BuyerPremium)+IF(N(Deals!S42)=0,0,MIN(N(Deals!S42),MAX(0,N(Deals!S42)+SheriffCostsFromBid-(AH43)*(1-RTTPurchase)))))+Underwriting!$S42)/(Underwriting!$M42/12),0)) | AK43: =IF(Underwriting!$A42="","",IFERROR(Underwriting!$Z42/(((AH43)*(1+BuyerPremium)+IF(N(Deals!S42)=0,0,MIN(N(Deals!S42),MAX(0,N(Deals!S42)+SheriffCostsFromBid-(AH43)*(1-RTTPurchase)))))+Underwriting!$AA42),0))

Sheet Portfolio
A1: Capital plan. Planned bid defaults to the max bid; overwrite it (yellow) with what you intend to bid. Include = Y to count it against the cash cap.
A2: Auction ID | B2: Address | C2: Best exit | D2: Max bid | E2: Planned bid | F2: Include? (Y/N) | G2: Due Nov 4 (10% + premium) | H2: Due Nov 18 (90%) | I2: Cash after the sale (rehab, carry, legal, liens, unpaid city claims) | J2: Total cash in | K2: Running total (included) | L2: Profit / return at planned bid
A3: =Underwriting!$A3 -> 1318974-0 | B3: =Underwriting!$B3 -> 0 Bench screen (ARV 354k, Heavy, occupied) | C3: =Underwriting!$C3 -> Flip | D3: =Underwriting!$D3 -> 116429.49 | E3: =IF(Underwriting!$A3="","",Underwriting!$D3) -> 116429.49 | F3: =IF(Underwriting!$A3="","",IF(Underwriting!$D3>0,"Y","N")) -> Y | G3: =IF(Underwriting!$A3="","",N(E3)*(DownPct+BuyerPremium)) -> 13389.391 | H3: =IF(Underwriting!$A3="","",IF(N(E3)>0,N(E3)*(1-DownPct)+35,0)) -> 104821.54 | I3: =IF(Underwriting!$A3="","",IF(C3="Value-add hold",Underwriting!$AA3,Underwriting!$S3)+((N(E3))*(1+BuyerPremium)+IF(N(Deals!S3)=0,0,MIN(N(Deals!S3),MAX(0,N(Deals!S3)+SheriffCostsFromBid-(N(E3))*(1-RTTPurchase)))))-N(E3)*(1+BuyerPremium)) -> 119688.47 | J3: =IF(Underwriting!$A3="","",G3+H3+I3) -> 237899.4 | K3: =IF(Underwriting!$A3="","",SUMIF($F$3:F3,"Y",$J$3:J3)) -> 237899.4 | L3: =IF(Underwriting!$A3="","",IF(C3="Value-add hold",TEXT(IFERROR(Underwriting!$Z3/(((N(E3))*(1+BuyerPremium)+IF(N(Deals!S3)=0,0,MIN(N(Deals!S3),MAX(0,N(Deals!S3)+SheriffCostsFromBid-(N(E3))*(1-RTTPurchase)))))+Underwriting!$AA3),0),"0.0%")&" yield on cost",TEXT(Underwriting!$T3-((N(E3))*(1+BuyerPremium)+IF(N(Deals!S3)=0,0,MIN(N(Deals!S3),MAX(0,N(Deals!S3)+SheriffCostsFromBid-(N(E3))*(1-RTTPurchase))))),"$#,##0")&" flip profit")) -> $83,253 flip profit
A4: =Underwriting!$A4 -> 1318974-1 | B4: =Underwriting!$B4 -> 1 Base: ARV 395k, Medium (+$8k roof/front), occupied | C4: =Underwriting!$C4 -> Flip | D4: =Underwriting!$D4 -> 166944.44 | E4: =IF(Underwriting!$A4="","",Underwriting!$D4) -> 166944.44 | F4: =IF(Underwriting!$A4="","",IF(Underwriting!$D4>0,"Y","N")) -> Y | G4: =IF(Underwriting!$A4="","",N(E4)*(DownPct+BuyerPremium)) -> 19198.611 | H4: =IF(Underwriting!$A4="","",IF(N(E4)>0,N(E4)*(1-DownPct)+35,0)) -> 150285 | I4: =IF(Underwriting!$A4="","",IF(C4="Value-add hold",Underwriting!$AA4,Underwriting!$S4)+((N(E4))*(1+BuyerPremium)+IF(N(Deals!S4)=0,0,MIN(N(Deals!S4),MAX(0,N(Deals!S4)+SheriffCostsFromBid-(N(E4))*(1-RTTPurchase)))))-N(E4)*(1+BuyerPremium)) -> 100972.86 | J4: =IF(Underwriting!$A4="","",G4+H4+I4) -> 270456.47 | K4: =IF(Underwriting!$A4="","",SUMIF($F$3:F4,"Y",$J$3:J4)) -> 508355.87 | L4: =IF(Underwriting!$A4="","",IF(C4="Value-add hold",TEXT(IFERROR(Underwriting!$Z4/(((N(E4))*(1+BuyerPremium)+IF(N(Deals!S4)=0,0,MIN(N(Deals!S4),MAX(0,N(Deals!S4)+SheriffCostsFromBid-(N(E4))*(1-RTTPurchase)))))+Underwriting!$AA4),0),"0.0%")&" yield on cost",TEXT(Underwriting!$T4-((N(E4))*(1+BuyerPremium)+IF(N(Deals!S4)=0,0,MIN(N(Deals!S4),MAX(0,N(Deals!S4)+SheriffCostsFromBid-(N(E4))*(1-RTTPurchase))))),"$#,##0")&" flip profit")) -> $87,887 flip profit
A5: =Underwriting!$A5 -> 1318974-2 | B5: =Underwriting!$B5 -> 2 Base but vacant at deed | C5: =Underwriting!$C5 -> Flip | D5: =Underwriting!$D5 -> 204518.47 | E5: =IF(Underwriting!$A5="","",Underwriting!$D5) -> 204518.47 | F5: =IF(Underwriting!$A5="","",IF(Underwriting!$D5>0,"Y","N")) -> Y | G5: =IF(Underwriting!$A5="","",N(E5)*(DownPct+BuyerPremium)) -> 23519.624 | H5: =IF(Underwriting!$A5="","",IF(N(E5)>0,N(E5)*(1-DownPct)+35,0)) -> 184101.63 | I5: =IF(Underwriting!$A5="","",IF(C5="Value-add hold",Underwriting!$AA5,Underwriting!$S5)+((N(E5))*(1+BuyerPremium)+IF(N(Deals!S5)=0,0,MIN(N(Deals!S5),MAX(0,N(Deals!S5)+SheriffCostsFromBid-(N(E5))*(1-RTTPurchase)))))-N(E5)*(1+BuyerPremium)) -> 84910.444 | J5: =IF(Underwriting!$A5="","",G5+H5+I5) -> 292531.69 | K5: =IF(Underwriting!$A5="","",SUMIF($F$3:F5,"Y",$J$3:J5)) -> 800887.57 | L5: =IF(Underwriting!$A5="","",IF(C5="Value-add hold",TEXT(IFERROR(Underwriting!$Z5/(((N(E5))*(1+BuyerPremium)+IF(N(Deals!S5)=0,0,MIN(N(Deals!S5),MAX(0,N(Deals!S5)+SheriffCostsFromBid-(N(E5))*(1-RTTPurchase)))))+Underwriting!$AA5),0),"0.0%")&" yield on cost",TEXT(Underwriting!$T5-((N(E5))*(1+BuyerPremium)+IF(N(Deals!S5)=0,0,MIN(N(Deals!S5),MAX(0,N(Deals!S5)+SheriffCostsFromBid-(N(E5))*(1-RTTPurchase))))),"$#,##0")&" flip profit")) -> $65,812 flip profit
A6: =Underwriting!$A6 -> 1318974-3 | B6: =Underwriting!$B6 -> 3 Light cosmetic: ARV 375k, Light, occupied | C6: =Underwriting!$C6 -> Flip | D6: =Underwriting!$D6 -> 185181.5 | E6: =IF(Underwriting!$A6="","",Underwriting!$D6) -> 185181.5 | F6: =IF(Underwriting!$A6="","",IF(Underwriting!$D6>0,"Y","N")) -> Y | G6: =IF(Underwriting!$A6="","",N(E6)*(DownPct+BuyerPremium)) -> 21295.873 | H6: =IF(Underwriting!$A6="","",IF(N(E6)>0,N(E6)*(1-DownPct)+35,0)) -> 166698.35 | I6: =IF(Underwriting!$A6="","",IF(C6="Value-add hold",Underwriting!$AA6,Underwriting!$S6)+((N(E6))*(1+BuyerPremium)+IF(N(Deals!S6)=0,0,MIN(N(Deals!S6),MAX(0,N(Deals!S6)+SheriffCostsFromBid-(N(E6))*(1-RTTPurchase)))))-N(E6)*(1+BuyerPremium)) -> 71215.061 | J6: =IF(Underwriting!$A6="","",G6+H6+I6) -> 259209.29 | K6: =IF(Underwriting!$A6="","",SUMIF($F$3:F6,"Y",$J$3:J6)) -> 1060096.9 | L6: =IF(Underwriting!$A6="","",IF(C6="Value-add hold",TEXT(IFERROR(Underwriting!$Z6/(((N(E6))*(1+BuyerPremium)+IF(N(Deals!S6)=0,0,MIN(N(Deals!S6),MAX(0,N(Deals!S6)+SheriffCostsFromBid-(N(E6))*(1-RTTPurchase)))))+Underwriting!$AA6),0),"0.0%")&" yield on cost",TEXT(Underwriting!$T6-((N(E6))*(1+BuyerPremium)+IF(N(Deals!S6)=0,0,MIN(N(Deals!S6),MAX(0,N(Deals!S6)+SheriffCostsFromBid-(N(E6))*(1-RTTPurchase))))),"$#,##0")&" flip profit")) -> $80,992 flip profit
A7: =Underwriting!$A7 -> 1318974-4 | B7: =Underwriting!$B7 -> 4 Downside: ARV 365k, Heavy, occupied | C7: =Underwriting!$C7 -> Flip | D7: =Underwriting!$D7 -> 123711.53 | E7: =IF(Underwriting!$A7="","",Underwriting!$D7) -> 123711.53 | F7: =IF(Underwriting!$A7="","",IF(Underwriting!$D7>0,"Y","N")) -> Y | G7: =IF(Underwriting!$A7="","",N(E7)*(DownPct+BuyerPremium)) -> 14226.825 | H7: =IF(Underwriting!$A7="","",IF(N(E7)>0,N(E7)*(1-DownPct)+35,0)) -> 111375.37 | I7: =IF(Underwriting!$A7="","",IF(C7="Value-add hold",Underwriting!$AA7,Underwriting!$S7)+((N(E7))*(1+BuyerPremium)+IF(N(Deals!S7)=0,0,MIN(N(Deals!S7),MAX(0,N(Deals!S7)+SheriffCostsFromBid-(N(E7))*(1-RTTPurchase)))))-N(E7)*(1+BuyerPremium)) -> 119688.47 | J7: =IF(Underwriting!$A7="","",G7+H7+I7) -> 245290.67 | K7: =IF(Underwriting!$A7="","",SUMIF($F$3:F7,"Y",$J$3:J7)) -> 1305387.5 | L7: =IF(Underwriting!$A7="","",IF(C7="Value-add hold",TEXT(IFERROR(Underwriting!$Z7/(((N(E7))*(1+BuyerPremium)+IF(N(Deals!S7)=0,0,MIN(N(Deals!S7),MAX(0,N(Deals!S7)+SheriffCostsFromBid-(N(E7))*(1-RTTPurchase)))))+Underwriting!$AA7),0),"0.0%")&" yield on cost",TEXT(Underwriting!$T7-((N(E7))*(1+BuyerPremium)+IF(N(Deals!S7)=0,0,MIN(N(Deals!S7),MAX(0,N(Deals!S7)+SheriffCostsFromBid-(N(E7))*(1-RTTPurchase))))),"$#,##0")&" flip profit")) -> $85,839 flip profit
A8: =Underwriting!$A8 -> 1318974-5 | B8: =Underwriting!$B8 -> 5 Upside: ARV 425k, Medium + half bath, occupied | C8: =Underwriting!$C8 -> Flip | D8: =Underwriting!$D8 -> 175356.6 | E8: =IF(Underwriting!$A8="","",Underwriting!$D8) -> 175356.6 | F8: =IF(Underwriting!$A8="","",IF(Underwriting!$D8>0,"Y","N")) -> Y | G8: =IF(Underwriting!$A8="","",N(E8)*(DownPct+BuyerPremium)) -> 20166.009 | H8: =IF(Underwriting!$A8="","",IF(N(E8)>0,N(E8)*(1-DownPct)+35,0)) -> 157855.94 | I8: =IF(Underwriting!$A8="","",IF(C8="Value-add hold",Underwriting!$AA8,Underwriting!$S8)+((N(E8))*(1+BuyerPremium)+IF(N(Deals!S8)=0,0,MIN(N(Deals!S8),MAX(0,N(Deals!S8)+SheriffCostsFromBid-(N(E8))*(1-RTTPurchase)))))-N(E8)*(1+BuyerPremium)) -> 112972.86 | J8: =IF(Underwriting!$A8="","",G8+H8+I8) -> 290994.81 | K8: =IF(Underwriting!$A8="","",SUMIF($F$3:F8,"Y",$J$3:J8)) -> 1596382.3 | L8: =IF(Underwriting!$A8="","",IF(C8="Value-add hold",TEXT(IFERROR(Underwriting!$Z8/(((N(E8))*(1+BuyerPremium)+IF(N(Deals!S8)=0,0,MIN(N(Deals!S8),MAX(0,N(Deals!S8)+SheriffCostsFromBid-(N(E8))*(1-RTTPurchase)))))+Underwriting!$AA8),0),"0.0%")&" yield on cost",TEXT(Underwriting!$T8-((N(E8))*(1+BuyerPremium)+IF(N(Deals!S8)=0,0,MIN(N(Deals!S8),MAX(0,N(Deals!S8)+SheriffCostsFromBid-(N(E8))*(1-RTTPurchase))))),"$#,##0")&" flip profit")) -> $94,562 flip profit
A9: =Underwriting!$A9 -> 1318974-6 | B9: =Underwriting!$B9 -> 6 Slow ejectment proxy: ARV 395k, Medium, occupied, Heavy timeline | C9: =Underwriting!$C9 -> Flip | D9: =Underwriting!$D9 -> 143571.62 | E9: =IF(Underwriting!$A9="","",Underwriting!$D9) -> 143571.62 | F9: =IF(Underwriting!$A9="","",IF(Underwriting!$D9>0,"Y","N")) -> Y | G9: =IF(Underwriting!$A9="","",N(E9)*(DownPct+BuyerPremium)) -> 16510.737 | H9: =IF(Underwriting!$A9="","",IF(N(E9)>0,N(E9)*(1-DownPct)+35,0)) -> 129249.46 | I9: =IF(Underwriting!$A9="","",IF(C9="Value-add hold",Underwriting!$AA9,Underwriting!$S9)+((N(E9))*(1+BuyerPremium)+IF(N(Deals!S9)=0,0,MIN(N(Deals!S9),MAX(0,N(Deals!S9)+SheriffCostsFromBid-(N(E9))*(1-RTTPurchase)))))-N(E9)*(1+BuyerPremium)) -> 119688.47 | J9: =IF(Underwriting!$A9="","",G9+H9+I9) -> 265448.67 | K9: =IF(Underwriting!$A9="","",SUMIF($F$3:F9,"Y",$J$3:J9)) -> 1861831 | L9: =IF(Underwriting!$A9="","",IF(C9="Value-add hold",TEXT(IFERROR(Underwriting!$Z9/(((N(E9))*(1+BuyerPremium)+IF(N(Deals!S9)=0,0,MIN(N(Deals!S9),MAX(0,N(Deals!S9)+SheriffCostsFromBid-(N(E9))*(1-RTTPurchase)))))+Underwriting!$AA9),0),"0.0%")&" yield on cost",TEXT(Underwriting!$T9-((N(E9))*(1+BuyerPremium)+IF(N(Deals!S9)=0,0,MIN(N(Deals!S9),MAX(0,N(Deals!S9)+SheriffCostsFromBid-(N(E9))*(1-RTTPurchase))))),"$#,##0")&" flip profit")) -> $92,895 flip profit
A10: =Underwriting!$A10 | B10: =Underwriting!$B10 | C10: =Underwriting!$C10 | D10: =Underwriting!$D10 | E10: =IF(Underwriting!$A10="","",Underwriting!$D10) | F10: =IF(Underwriting!$A10="","",IF(Underwriting!$D10>0,"Y","N")) | G10: =IF(Underwriting!$A10="","",N(E10)*(DownPct+BuyerPremium)) | H10: =IF(Underwriting!$A10="","",IF(N(E10)>0,N(E10)*(1-DownPct)+35,0)) | I10: =IF(Underwriting!$A10="","",IF(C10="Value-add hold",Underwriting!$AA10,Underwriting!$S10)+((N(E10))*(1+BuyerPremium)+IF(N(Deals!S10)=0,0,MIN(N(Deals!S10),MAX(0,N(Deals!S10)+SheriffCostsFromBid-(N(E10))*(1-RTTPurchase)))))-N(E10)*(1+BuyerPremium)) | J10: =IF(Underwriting!$A10="","",G10+H10+I10) | K10: =IF(Underwriting!$A10="","",SUMIF($F$3:F10,"Y",$J$3:J10)) | L10: =IF(Underwriting!$A10="","",IF(C10="Value-add hold",TEXT(IFERROR(Underwriting!$Z10/(((N(E10))*(1+BuyerPremium)+IF(N(Deals!S10)=0,0,MIN(N(Deals!S10),MAX(0,N(Deals!S10)+SheriffCostsFromBid-(N(E10))*(1-RTTPurchase)))))+Underwriting!$AA10),0),"0.0%")&" yield on cost",TEXT(Underwriting!$T10-((N(E10))*(1+BuyerPremium)+IF(N(Deals!S10)=0,0,MIN(N(Deals!S10),MAX(0,N(Deals!S10)+SheriffCostsFromBid-(N(E10))*(1-RTTPurchase))))),"$#,##0")&" flip profit"))
A11: =Underwriting!$A11 | B11: =Underwriting!$B11 | C11: =Underwriting!$C11 | D11: =Underwriting!$D11 | E11: =IF(Underwriting!$A11="","",Underwriting!$D11) | F11: =IF(Underwriting!$A11="","",IF(Underwriting!$D11>0,"Y","N")) | G11: =IF(Underwriting!$A11="","",N(E11)*(DownPct+BuyerPremium)) | H11: =IF(Underwriting!$A11="","",IF(N(E11)>0,N(E11)*(1-DownPct)+35,0)) | I11: =IF(Underwriting!$A11="","",IF(C11="Value-add hold",Underwriting!$AA11,Underwriting!$S11)+((N(E11))*(1+BuyerPremium)+IF(N(Deals!S11)=0,0,MIN(N(Deals!S11),MAX(0,N(Deals!S11)+SheriffCostsFromBid-(N(E11))*(1-RTTPurchase)))))-N(E11)*(1+BuyerPremium)) | J11: =IF(Underwriting!$A11="","",G11+H11+I11) | K11: =IF(Underwriting!$A11="","",SUMIF($F$3:F11,"Y",$J$3:J11)) | L11: =IF(Underwriting!$A11="","",IF(C11="Value-add hold",TEXT(IFERROR(Underwriting!$Z11/(((N(E11))*(1+BuyerPremium)+IF(N(Deals!S11)=0,0,MIN(N(Deals!S11),MAX(0,N(Deals!S11)+SheriffCostsFromBid-(N(E11))*(1-RTTPurchase)))))+Underwriting!$AA11),0),"0.0%")&" yield on cost",TEXT(Underwriting!$T11-((N(E11))*(1+BuyerPremium)+IF(N(Deals!S11)=0,0,MIN(N(Deals!S11),MAX(0,N(Deals!S11)+SheriffCostsFromBid-(N(E11))*(1-RTTPurchase))))),"$#,##0")&" flip profit"))
A12: =Underwriting!$A12 | B12: =Underwriting!$B12 | C12: =Underwriting!$C12 | D12: =Underwriting!$D12 | E12: =IF(Underwriting!$A12="","",Underwriting!$D12) | F12: =IF(Underwriting!$A12="","",IF(Underwriting!$D12>0,"Y","N")) | G12: =IF(Underwriting!$A12="","",N(E12)*(DownPct+BuyerPremium)) | H12: =IF(Underwriting!$A12="","",IF(N(E12)>0,N(E12)*(1-DownPct)+35,0)) | I12: =IF(Underwriting!$A12="","",IF(C12="Value-add hold",Underwriting!$AA12,Underwriting!$S12)+((N(E12))*(1+BuyerPremium)+IF(N(Deals!S12)=0,0,MIN(N(Deals!S12),MAX(0,N(Deals!S12)+SheriffCostsFromBid-(N(E12))*(1-RTTPurchase)))))-N(E12)*(1+BuyerPremium)) | J12: =IF(Underwriting!$A12="","",G12+H12+I12) | K12: =IF(Underwriting!$A12="","",SUMIF($F$3:F12,"Y",$J$3:J12)) | L12: =IF(Underwriting!$A12="","",IF(C12="Value-add hold",TEXT(IFERROR(Underwriting!$Z12/(((N(E12))*(1+BuyerPremium)+IF(N(Deals!S12)=0,0,MIN(N(Deals!S12),MAX(0,N(Deals!S12)+SheriffCostsFromBid-(N(E12))*(1-RTTPurchase)))))+Underwriting!$AA12),0),"0.0%")&" yield on cost",TEXT(Underwriting!$T12-((N(E12))*(1+BuyerPremium)+IF(N(Deals!S12)=0,0,MIN(N(Deals!S12),MAX(0,N(Deals!S12)+SheriffCostsFromBid-(N(E12))*(1-RTTPurchase))))),"$#,##0")&" flip profit"))
A13: =Underwriting!$A13 | B13: =Underwriting!$B13 | C13: =Underwriting!$C13 | D13: =Underwriting!$D13 | E13: =IF(Underwriting!$A13="","",Underwriting!$D13) | F13: =IF(Underwriting!$A13="","",IF(Underwriting!$D13>0,"Y","N")) | G13: =IF(Underwriting!$A13="","",N(E13)*(DownPct+BuyerPremium)) | H13: =IF(Underwriting!$A13="","",IF(N(E13)>0,N(E13)*(1-DownPct)+35,0)) | I13: =IF(Underwriting!$A13="","",IF(C13="Value-add hold",Underwriting!$AA13,Underwriting!$S13)+((N(E13))*(1+BuyerPremium)+IF(N(Deals!S13)=0,0,MIN(N(Deals!S13),MAX(0,N(Deals!S13)+SheriffCostsFromBid-(N(E13))*(1-RTTPurchase)))))-N(E13)*(1+BuyerPremium)) | J13: =IF(Underwriting!$A13="","",G13+H13+I13) | K13: =IF(Underwriting!$A13="","",SUMIF($F$3:F13,"Y",$J$3:J13)) | L13: =IF(Underwriting!$A13="","",IF(C13="Value-add hold",TEXT(IFERROR(Underwriting!$Z13/(((N(E13))*(1+BuyerPremium)+IF(N(Deals!S13)=0,0,MIN(N(Deals!S13),MAX(0,N(Deals!S13)+SheriffCostsFromBid-(N(E13))*(1-RTTPurchase)))))+Underwriting!$AA13),0),"0.0%")&" yield on cost",TEXT(Underwriting!$T13-((N(E13))*(1+BuyerPremium)+IF(N(Deals!S13)=0,0,MIN(N(Deals!S13),MAX(0,N(Deals!S13)+SheriffCostsFromBid-(N(E13))*(1-RTTPurchase))))),"$#,##0")&" flip profit"))
A14: =Underwriting!$A14 | B14: =Underwriting!$B14 | C14: =Underwriting!$C14 | D14: =Underwriting!$D14 | E14: =IF(Underwriting!$A14="","",Underwriting!$D14) | F14: =IF(Underwriting!$A14="","",IF(Underwriting!$D14>0,"Y","N")) | G14: =IF(Underwriting!$A14="","",N(E14)*(DownPct+BuyerPremium)) | H14: =IF(Underwriting!$A14="","",IF(N(E14)>0,N(E14)*(1-DownPct)+35,0)) | I14: =IF(Underwriting!$A14="","",IF(C14="Value-add hold",Underwriting!$AA14,Underwriting!$S14)+((N(E14))*(1+BuyerPremium)+IF(N(Deals!S14)=0,0,MIN(N(Deals!S14),MAX(0,N(Deals!S14)+SheriffCostsFromBid-(N(E14))*(1-RTTPurchase)))))-N(E14)*(1+BuyerPremium)) | J14: =IF(Underwriting!$A14="","",G14+H14+I14) | K14: =IF(Underwriting!$A14="","",SUMIF($F$3:F14,"Y",$J$3:J14)) | L14: =IF(Underwriting!$A14="","",IF(C14="Value-add hold",TEXT(IFERROR(Underwriting!$Z14/(((N(E14))*(1+BuyerPremium)+IF(N(Deals!S14)=0,0,MIN(N(Deals!S14),MAX(0,N(Deals!S14)+SheriffCostsFromBid-(N(E14))*(1-RTTPurchase)))))+Underwriting!$AA14),0),"0.0%")&" yield on cost",TEXT(Underwriting!$T14-((N(E14))*(1+BuyerPremium)+IF(N(Deals!S14)=0,0,MIN(N(Deals!S14),MAX(0,N(Deals!S14)+SheriffCostsFromBid-(N(E14))*(1-RTTPurchase))))),"$#,##0")&" flip profit"))
... A42: =Underwriting!$A42 | B42: =Underwriting!$B42 | C42: =Underwriting!$C42 | D42: =Underwriting!$D42 | E42: =IF(Underwriting!$A42="","",Underwriting!$D42) | F42: =IF(Underwriting!$A42="","",IF(Underwriting!$D42>0,"Y","N")) | G42: =IF(Underwriting!$A42="","",N(E42)*(DownPct+BuyerPremium)) | H42: =IF(Underwriting!$A42="","",IF(N(E42)>0,N(E42)*(1-DownPct)+35,0)) | I42: =IF(Underwriting!$A42="","",IF(C42="Value-add hold",Underwriting!$AA42,Underwriting!$S42)+((N(E42))*(1+BuyerPremium)+IF(N(Deals!S42)=0,0,MIN(N(Deals!S42),MAX(0,N(Deals!S42)+SheriffCostsFromBid-(N(E42))*(1-RTTPurchase)))))-N(E42)*(1+BuyerPremium)) | J42: =IF(Underwriting!$A42="","",G42+H42+I42) | K42: =IF(Underwriting!$A42="","",SUMIF($F$3:F42,"Y",$J$3:J42)) | L42: =IF(Underwriting!$A42="","",IF(C42="Value-add hold",TEXT(IFERROR(Underwriting!$Z42/(((N(E42))*(1+BuyerPremium)+IF(N(Deals!S42)=0,0,MIN(N(Deals!S42),MAX(0,N(Deals!S42)+SheriffCostsFromBid-(N(E42))*(1-RTTPurchase)))))+Underwriting!$AA42),0),"0.0%")&" yield on cost",TEXT(Underwriting!$T42-((N(E42))*(1+BuyerPremium)+IF(N(Deals!S42)=0,0,MIN(N(Deals!S42),MAX(0,N(Deals!S42)+SheriffCostsFromBid-(N(E42))*(1-RTTPurchase))))),"$#,##0")&" flip profit"))
A44: Cash due Nov 4 (included lots, less the bidder deposit) | B44: =MAX(0,SUMIF(F3:F42,"Y",G3:G42)-BidderDeposit) -> 123307.07
A45: Bidder deposit (wired before the sale) | B45: =BidderDeposit -> 5000
A46: Cash due Nov 18 (included lots) | B46: =SUMIF(F3:F42,"Y",H3:H42) -> 1004387.3
A47: Cash after the sale (included lots) | B47: =SUMIF(F3:F42,"Y",I3:I42) -> 729136.64
A48: Total cash if every included lot is won | B48: =SUMIF(F3:F42,"Y",J3:J42) -> 1861831
A49: Cash cap | B49: =CapitalCap -> 1000000
A50: Room under cap | B50: =B49-B48 -> -861831
